Workbook

Sheet Instructions
A1: CLIENT INVESTMENT TRACKER - TOTAL REVIEW
A2: Built to match the scheme-wise Profit & Loss export from the portfolio software.
B4: HOW TO USE
B5: 1. Clients | C5: Enter every client once - code, name, PAN, address, mobile, email, DOB, 'Rep By' / family head. This list drives the dropdowns, the client-wise review and the Client Report header.
B6: 2. Import Report | C6: The easy way to load data. Paste a whole Profit & Loss export on the left of that sheet; clean register rows appear on the right, ready to copy into Investments. Category headings, transaction sub-tables and total lines are dropped for you, and the scheme name and folio are split apart.
B7: 3. Investments | C7: One row per scheme per client. Columns A to O are one unbroken block, in the same order as the Import Report output, so a whole report goes in with a single Paste Special > Values on cell A6. Columns P to V are formulas - never paste over them.
B8: 4. Total Review | C8: Read-only dashboard: firm-level snapshot, client-wise review, asset-class review and category-wise review, with charts.
B9: 5. Client Report | C9: Pick one client from the dropdown to get that client's header block, summary and scheme list - the single-client view your software prints.
B11: HOW THE MATHS WORKS
B12: Total Invested | C12: Purchase + Switch In + Div Reinv
B13: Withdrawn | C13: Redemption + Switch Out + Div Pay
B14: Gain / Loss | C14: (Cur. Value + Withdrawn) - Total Invested
B15: Abs. Rtn. | C15: Gain / Loss ÷ Total Invested
B16: Net Invested | C16: Total Invested - Withdrawn (money still at work; shown for reference)
B17: Status | C17: Live when Cur. Value is above zero, otherwise Exited.
B18: XIRR | C18: Typed in from the software - it needs every cash-flow date, which this sheet does not hold. Client, category and firm level XIRR is a current-value-weighted average of the scheme XIRRs, so treat it as indicative, not as a recomputed XIRR.
B20: WHAT YOU EDIT
B21: Blue text on yellow fill | C21: Input cells - type or paste here.
B22: Black text on grey fill | C22: Formula cells - do not overwrite, they will stop calculating.
B23: EXAMPLE rows | C23: Clients row 4 and Investments row 6 are filled in as a format guide. Delete both before real use.
B24: Paste Special > Values | C24: Use this rather than a plain Ctrl+V when pasting into Investments: a plain paste drags the source formatting across and can wreck the column widths, fills and dropdowns.
B26: GOOD TO KNOW
B27: Capacity | C27: 200 clients, 1000 scheme rows, 100 schemes per client in the Client Report. To add rows, insert them INSIDE the existing table so the formulas extend with them.
B28: Asset Class | C28: Derived from the text before the ' - ' in Category, which is why categories are named 'Equity - Flexi Cap Fund' exactly as in the software.
B29: New categories | C29: Add them on the Lists sheet; the dropdown and the category-wise review pick them up. Keep the 'Asset - Category' naming.
B30: Currency | C30: Indian Rupee with lakh / crore grouping. To switch, select the amount columns > Format Cells > Custom and edit the symbol.
B31: Blank amounts | C31: Leave a column blank where the software prints 0.00 - blanks and zeros both total correctly.

Sheet Clients
A1: CLIENT MASTER
A2: One row per client. The name entered here is the key used by every other sheet.
A3: Client Code | B3: Client Name | C3: PAN | D3: Rep By / Family Head | E3: Segment | F3: Mobile No. | G3: Email | H3: DOB | I3: Address | J3: Advisor / RM | K3: Onboarding Date | L3: Remarks
A4: CL-0001 | B4: Sample Client (EXAMPLE) | C4: ABCDE1234F | D4: Rep By Family Head Name | E4: HNI | F4: 98xxxxxx61 | G4: client@example.com | H4: 2008-06-05 | I4: Flat 301, Sample Residency, Kothrud, Pune 411038 | J4: S. Kadam | K4: 2020-08-31 | L4: Delete this EXAMPLE row before use

Sheet Import Report
A1: IMPORT A PROFIT & LOSS REPORT
A2: Paste the report on the left - ready-to-paste register rows appear on the right.
A4: STEP 1 | B4: Open the client's Profit & Loss report, press Ctrl+A then Ctrl+C to copy the whole sheet.
A5: STEP 2 | B5: Click cell A9 below and press Ctrl+V. Category headings, transaction rows and total lines are ignored automatically. | Q5: Client Name | W5: =IFERROR(INDEX($A$9:$A$2008,MATCH(1,$V$9:$V$2008,0)),"")
A6: STEP 3 | B6: Check the Client Name box on the right. It is read from the report header - type over it, or pick from the list, so it matches the Clients sheet exactly. | Q6: read from report: | R6: =IF($W$5="","",TRIM(IF(ISNUMBER(SEARCH(" REP BY ",$W$5)),LEFT($W$5,SEARCH(" REP BY ",$W$5)-1),SUBSTITUTE($W$5,"()",""))))
A7: STEP 4 | B7: Select X9:AL... down to the last filled row, press Ctrl+C, then on the Investments sheet right-click cell A6 and choose Paste Special > Values. | X7: READY TO PASTE → copy these rows, then Investments!A6 → Paste Special → Values
A8: Scheme Name (+ Folio) | D8: Inv. Since | E8: Purchase | F8: Switch In | G8: Div Reinv | H8: Redemption | I8: Switch Out | J8: Div Pay | K8: Cur. Value | L8: Cur. Units | M8: Cur. NAV | N8: Gain/Loss | O8: Abs. Rtn. | P8: XIRR | X8: Client Name | Y8: Category | Z8: Scheme Name | AA8: Folio No. | AB8: Inv. Since | AC8: Purchase | AD8: Switch In | AE8: Div Reinv | AF8: Redemption | AG8: Switch Out | AH8: Div Pay | AI8: Cur. Value | AJ8: Cur. Units | AK8: Cur. NAV | AL8: XIRR
S9: =IF(AND(ISTEXT($A9),ISNUMBER(SEARCH(" - ",$A9)),ISERROR(SEARCH("Folio",$A9)),$D9=""),TRIM($A9),"") | T9: =IF(AND(ISNUMBER(SEARCH("Folio",$A9)),$D9<>""),1,"") | U9: =IF($T9=1,COUNTIF($T$9:$T9,1),"") | V9: =IF(AND(ISTEXT($A9),LEFT($A10,3)="Pan"),1,"") | W9: =IFERROR(MATCH(1,$U$9:$U$2008,0),"") | X9: =IF($W9="","",IF($R$5<>"",$R$5,$R$6)) | Y9: =IF($W9="","",INDEX($S$9:$S$2008,$W9)) | Z9: =IF($W9="","",IFERROR(TRIM(LEFT(SUBSTITUTE(INDEX($A$9:$A$2008,$W9),CHAR(10)," "),SEARCH("Folio",SUBSTITUTE(INDEX($A$9:$A$2008,$W9),CHAR(10)," "))-1)),TRIM(SUBSTITUTE(INDEX($A$9:$A$2008,$W9),CHAR(10)," ")))) | AA9: =IF($W9="","",IFERROR(TRIM(SUBSTITUTE(MID(SUBSTITUTE(INDEX($A$9:$A$2008,$W9),CHAR(10)," "),SEARCH("Folio",SUBSTITUTE(INDEX($A$9:$A$2008,$W9),CHAR(10)," "))+5,200),":","")),"")) | AB9: =IF($W9="","",IF(ISNUMBER(INDEX($D$9:$D$2008,$W9)),INDEX($D$9:$D$2008,$W9),IFERROR(DATE(2000+VALUE(RIGHT(INDEX($D$9:$D$2008,$W9),2)),VALUE(MID(INDEX($D$9:$D$2008,$W9),4,2)),VALUE(LEFT(INDEX($D$9:$D$2008,$W9),2))),""))) | AC9: =IF($W9="","",IFERROR(IF(ISNUMBER(INDEX($E$9:$E$2008,$W9)),INDEX($E$9:$E$2008,$W9),VALUE(SUBSTITUTE(INDEX($E$9:$E$2008,$W9),",",""))),"")) | AD9: =IF($W9="","",IFERROR(IF(ISNUMBER(INDEX($F$9:$F$2008,$W9)),INDEX($F$9:$F$2008,$W9),VALUE(SUBSTITUTE(INDEX($F$9:$F$2008,$W9),",",""))),"")) | AE9: =IF($W9="","",IFERROR(IF(ISNUMBER(INDEX($G$9:$G$2008,$W9)),INDEX($G$9:$G$2008,$W9),VALUE(SUBSTITUTE(INDEX($G$9:$G$2008,$W9),",",""))),"")) | AF9: =IF($W9="","",IFERROR(IF(ISNUMBER(INDEX($H$9:$H$2008,$W9)),INDEX($H$9:$H$2008,$W9),VALUE(SUBSTITUTE(INDEX($H$9:$H$2008,$W9),",",""))),"")) | AG9: =IF($W9="","",IFERROR(IF(ISNUMBER(INDEX($I$9:$I$2008,$W9)),INDEX($I$9:$I$2008,$W9),VALUE(SUBSTITUTE(INDEX($I$9:$I$2008,$W9),",",""))),"")) | AH9: =IF($W9="","",IFERROR(IF(ISNUMBER(INDEX($J$9:$J$2008,$W9)),INDEX($J$9:$J$2008,$W9),VALUE(SUBSTITUTE(INDEX($J$9:$J$2008,$W9),",",""))),"")) | AI9: =IF($W9="","",IFERROR(IF(ISNUMBER(INDEX($K$9:$K$2008,$W9)),INDEX($K$9:$K$2008,$W9),VALUE(SUBSTITUTE(INDEX($K$9:$K$2008,$W9),",",""))),"")) | AJ9: =IF($W9="","",IFERROR(IF(ISNUMBER(INDEX($L$9:$L$2008,$W9)),INDEX($L$9:$L$2008,$W9),VALUE(SUBSTITUTE(INDEX($L$9:$L$2008,$W9),",",""))),"")) | AK9: =IF($W9="","",IFERROR(IF(ISNUMBER(INDEX($M$9:$M$2008,$W9)),INDEX($M$9:$M$2008,$W9),VALUE(SUBSTITUTE(INDEX($M$9:$M$2008,$W9),",",""))),"")) | AL9: =IF($W9="","",IFERROR(IF(ISNUMBER(INDEX($P$9:$P$2008,$W9)),INDEX($P$9:$P$2008,$W9),VALUE(SUBSTITUTE(INDEX($P$9:$P$2008,$W9),"%",""))/100),""))
S10: =IF(AND(ISTEXT($A10),ISNUMBER(SEARCH(" - ",$A10)),ISERROR(SEARCH("Folio",$A10)),$D10=""),TRIM($A10),$S9) | T10: =IF(AND(ISNUMBER(SEARCH("Folio",$A10)),$D10<>""),1,"") | U10: =IF($T10=1,COUNTIF($T$9:$T10,1),"") | V10: =IF(AND(ISTEXT($A10),LEFT($A11,3)="Pan"),1,"") | W10: =IFERROR(MATCH(2,$U$9:$U$2008,0),"") | X10: =IF($W10="","",IF($R$5<>"",$R$5,$R$6)) | Y10: =IF($W10="","",INDEX($S$9:$S$2008,$W10)) | Z10: =IF($W10="","",IFERROR(TRIM(LEFT(SUBSTITUTE(INDEX($A$9:$A$2008,$W10),CHAR(10)," "),SEARCH("Folio",SUBSTITUTE(INDEX($A$9:$A$2008,$W10),CHAR(10)," "))-1)),TRIM(SUBSTITUTE(INDEX($A$9:$A$2008,$W10),CHAR(10)," ")))) | AA10: =IF($W10="","",IFERROR(TRIM(SUBSTITUTE(MID(SUBSTITUTE(INDEX($A$9:$A$2008,$W10),CHAR(10)," "),SEARCH("Folio",SUBSTITUTE(INDEX($A$9:$A$2008,$W10),CHAR(10)," "))+5,200),":","")),"")) | AB10: =IF($W10="","",IF(ISNUMBER(INDEX($D$9:$D$2008,$W10)),INDEX($D$9:$D$2008,$W10),IFERROR(DATE(2000+VALUE(RIGHT(INDEX($D$9:$D$2008,$W10),2)),VALUE(MID(INDEX($D$9:$D$2008,$W10),4,2)),VALUE(LEFT(INDEX($D$9:$D$2008,$W10),2))),""))) | AC10: =IF($W10="","",IFERROR(IF(ISNUMBER(INDEX($E$9:$E$2008,$W10)),INDEX($E$9:$E$2008,$W10),VALUE(SUBSTITUTE(INDEX($E$9:$E$2008,$W10),",",""))),"")) | AD10: =IF($W10="","",IFERROR(IF(ISNUMBER(INDEX($F$9:$F$2008,$W10)),INDEX($F$9:$F$2008,$W10),VALUE(SUBSTITUTE(INDEX($F$9:$F$2008,$W10),",",""))),"")) | AE10: =IF($W10="","",IFERROR(IF(ISNUMBER(INDEX($G$9:$G$2008,$W10)),INDEX($G$9:$G$2008,$W10),VALUE(SUBSTITUTE(INDEX($G$9:$G$2008,$W10),",",""))),"")) | AF10: =IF($W10="","",IFERROR(IF(ISNUMBER(INDEX($H$9:$H$2008,$W10)),INDEX($H$9:$H$2008,$W10),VALUE(SUBSTITUTE(INDEX($H$9:$H$2008,$W10),",",""))),"")) | AG10: =IF($W10="","",IFERROR(IF(ISNUMBER(INDEX($I$9:$I$2008,$W10)),INDEX($I$9:$I$2008,$W10),VALUE(SUBSTITUTE(INDEX($I$9:$I$2008,$W10),",",""))),"")) | AH10: =IF($W10="","",IFERROR(IF(ISNUMBER(INDEX($J$9:$J$2008,$W10)),INDEX($J$9:$J$2008,$W10),VALUE(SUBSTITUTE(INDEX($J$9:$J$2008,$W10),",",""))),"")) | AI10: =IF($W10="","",IFERROR(IF(ISNUMBER(INDEX($K$9:$K$2008,$W10)),INDEX($K$9:$K$2008,$W10),VALUE(SUBSTITUTE(INDEX($K$9:$K$2008,$W10),",",""))),"")) | AJ10: =IF($W10="","",IFERROR(IF(ISNUMBER(INDEX($L$9:$L$2008,$W10)),INDEX($L$9:$L$2008,$W10),VALUE(SUBSTITUTE(INDEX($L$9:$L$2008,$W10),",",""))),"")) | AK10: =IF($W10="","",IFERROR(IF(ISNUMBER(INDEX($M$9:$M$2008,$W10)),INDEX($M$9:$M$2008,$W10),VALUE(SUBSTITUTE(INDEX($M$9:$M$2008,$W10),",",""))),"")) | AL10: =IF($W10="","",IFERROR(IF(ISNUMBER(INDEX($P$9:$P$2008,$W10)),INDEX($P$9:$P$2008,$W10),VALUE(SUBSTITUTE(INDEX($P$9:$P$2008,$W10),"%",""))/100),""))
S11: =IF(AND(ISTEXT($A11),ISNUMBER(SEARCH(" - ",$A11)),ISERROR(SEARCH("Folio",$A11)),$D11=""),TRIM($A11),$S10) | T11: =IF(AND(ISNUMBER(SEARCH("Folio",$A11)),$D11<>""),1,"") | U11: =IF($T11=1,COUNTIF($T$9:$T11,1),"") | V11: =IF(AND(ISTEXT($A11),LEFT($A12,3)="Pan"),1,"") | W11: =IFERROR(MATCH(3,$U$9:$U$2008,0),"") | X11: =IF($W11="","",IF($R$5<>"",$R$5,$R$6)) | Y11: =IF($W11="","",INDEX($S$9:$S$2008,$W11)) | Z11: =IF($W11="","",IFERROR(TRIM(LEFT(SUBSTITUTE(INDEX($A$9:$A$2008,$W11),CHAR(10)," "),SEARCH("Folio",SUBSTITUTE(INDEX($A$9:$A$2008,$W11),CHAR(10)," "))-1)),TRIM(SUBSTITUTE(INDEX($A$9:$A$2008,$W11),CHAR(10)," ")))) | AA11: =IF($W11="","",IFERROR(TRIM(SUBSTITUTE(MID(SUBSTITUTE(INDEX($A$9:$A$2008,$W11),CHAR(10)," "),SEARCH("Folio",SUBSTITUTE(INDEX($A$9:$A$2008,$W11),CHAR(10)," "))+5,200),":","")),"")) | AB11: =IF($W11="","",IF(ISNUMBER(INDEX($D$9:$D$2008,$W11)),INDEX($D$9:$D$2008,$W11),IFERROR(DATE(2000+VALUE(RIGHT(INDEX($D$9:$D$2008,$W11),2)),VALUE(MID(INDEX($D$9:$D$2008,$W11),4,2)),VALUE(LEFT(INDEX($D$9:$D$2008,$W11),2))),""))) | AC11: =IF($W11="","",IFERROR(IF(ISNUMBER(INDEX($E$9:$E$2008,$W11)),INDEX($E$9:$E$2008,$W11),VALUE(SUBSTITUTE(INDEX($E$9:$E$2008,$W11),",",""))),"")) | AD11: =IF($W11="","",IFERROR(IF(ISNUMBER(INDEX($F$9:$F$2008,$W11)),INDEX($F$9:$F$2008,$W11),VALUE(SUBSTITUTE(INDEX($F$9:$F$2008,$W11),",",""))),"")) | AE11: =IF($W11="","",IFERROR(IF(ISNUMBER(INDEX($G$9:$G$2008,$W11)),INDEX($G$9:$G$2008,$W11),VALUE(SUBSTITUTE(INDEX($G$9:$G$2008,$W11),",",""))),"")) | AF11: =IF($W11="","",IFERROR(IF(ISNUMBER(INDEX($H$9:$H$2008,$W11)),INDEX($H$9:$H$2008,$W11),VALUE(SUBSTITUTE(INDEX($H$9:$H$2008,$W11),",",""))),"")) | AG11: =IF($W11="","",IFERROR(IF(ISNUMBER(INDEX($I$9:$I$2008,$W11)),INDEX($I$9:$I$2008,$W11),VALUE(SUBSTITUTE(INDEX($I$9:$I$2008,$W11),",",""))),"")) | AH11: =IF($W11="","",IFERROR(IF(ISNUMBER(INDEX($J$9:$J$2008,$W11)),INDEX($J$9:$J$2008,$W11),VALUE(SUBSTITUTE(INDEX($J$9:$J$2008,$W11),",",""))),"")) | AI11: =IF($W11="","",IFERROR(IF(ISNUMBER(INDEX($K$9:$K$2008,$W11)),INDEX($K$9:$K$2008,$W11),VALUE(SUBSTITUTE(INDEX($K$9:$K$2008,$W11),",",""))),"")) | AJ11: =IF($W11="","",IFERROR(IF(ISNUMBER(INDEX($L$9:$L$2008,$W11)),INDEX($L$9:$L$2008,$W11),VALUE(SUBSTITUTE(INDEX($L$9:$L$2008,$W11),",",""))),"")) | AK11: =IF($W11="","",IFERROR(IF(ISNUMBER(INDEX($M$9:$M$2008,$W11)),INDEX($M$9:$M$2008,$W11),VALUE(SUBSTITUTE(INDEX($M$9:$M$2008,$W11),",",""))),"")) | AL11: =IF($W11="","",IFERROR(IF(ISNUMBER(INDEX($P$9:$P$2008,$W11)),INDEX($P$9:$P$2008,$W11),VALUE(SUBSTITUTE(INDEX($P$9:$P$2008,$W11),"%",""))/100),""))
S12: =IF(AND(ISTEXT($A12),ISNUMBER(SEARCH(" - ",$A12)),ISERROR(SEARCH("Folio",$A12)),$D12=""),TRIM($A12),$S11) | T12: =IF(AND(ISNUMBER(SEARCH("Folio",$A12)),$D12<>""),1,"") | U12: =IF($T12=1,COUNTIF($T$9:$T12,1),"") | V12: =IF(AND(ISTEXT($A12),LEFT($A13,3)="Pan"),1,"") | W12: =IFERROR(MATCH(4,$U$9:$U$2008,0),"") | X12: =IF($W12="","",IF($R$5<>"",$R$5,$R$6)) | Y12: =IF($W12="","",INDEX($S$9:$S$2008,$W12)) | Z12: =IF($W12="","",IFERROR(TRIM(LEFT(SUBSTITUTE(INDEX($A$9:$A$2008,$W12),CHAR(10)," "),SEARCH("Folio",SUBSTITUTE(INDEX($A$9:$A$2008,$W12),CHAR(10)," "))-1)),TRIM(SUBSTITUTE(INDEX($A$9:$A$2008,$W12),CHAR(10)," ")))) | AA12: =IF($W12="","",IFERROR(TRIM(SUBSTITUTE(MID(SUBSTITUTE(INDEX($A$9:$A$2008,$W12),CHAR(10)," "),SEARCH("Folio",SUBSTITUTE(INDEX($A$9:$A$2008,$W12),CHAR(10)," "))+5,200),":","")),"")) | AB12: =IF($W12="","",IF(ISNUMBER(INDEX($D$9:$D$2008,$W12)),INDEX($D$9:$D$2008,$W12),IFERROR(DATE(2000+VALUE(RIGHT(INDEX($D$9:$D$2008,$W12),2)),VALUE(MID(INDEX($D$9:$D$2008,$W12),4,2)),VALUE(LEFT(INDEX($D$9:$D$2008,$W12),2))),""))) | AC12: =IF($W12="","",IFERROR(IF(ISNUMBER(INDEX($E$9:$E$2008,$W12)),INDEX($E$9:$E$2008,$W12),VALUE(SUBSTITUTE(INDEX($E$9:$E$2008,$W12),",",""))),"")) | AD12: =IF($W12="","",IFERROR(IF(ISNUMBER(INDEX($F$9:$F$2008,$W12)),INDEX($F$9:$F$2008,$W12),VALUE(SUBSTITUTE(INDEX($F$9:$F$2008,$W12),",",""))),"")) | AE12: =IF($W12="","",IFERROR(IF(ISNUMBER(INDEX($G$9:$G$2008,$W12)),INDEX($G$9:$G$2008,$W12),VALUE(SUBSTITUTE(INDEX($G$9:$G$2008,$W12),",",""))),"")) | AF12: =IF($W12="","",IFERROR(IF(ISNUMBER(INDEX($H$9:$H$2008,$W12)),INDEX($H$9:$H$2008,$W12),VALUE(SUBSTITUTE(INDEX($H$9:$H$2008,$W12),",",""))),"")) | AG12: =IF($W12="","",IFERROR(IF(ISNUMBER(INDEX($I$9:$I$2008,$W12)),INDEX($I$9:$I$2008,$W12),VALUE(SUBSTITUTE(INDEX($I$9:$I$2008,$W12),",",""))),"")) | AH12: =IF($W12="","",IFERROR(IF(ISNUMBER(INDEX($J$9:$J$2008,$W12)),INDEX($J$9:$J$2008,$W12),VALUE(SUBSTITUTE(INDEX($J$9:$J$2008,$W12),",",""))),"")) | AI12: =IF($W12="","",IFERROR(IF(ISNUMBER(INDEX($K$9:$K$2008,$W12)),INDEX($K$9:$K$2008,$W12),VALUE(SUBSTITUTE(INDEX($K$9:$K$2008,$W12),",",""))),"")) | AJ12: =IF($W12="","",IFERROR(IF(ISNUMBER(INDEX($L$9:$L$2008,$W12)),INDEX($L$9:$L$2008,$W12),VALUE(SUBSTITUTE(INDEX($L$9:$L$2008,$W12),",",""))),"")) | AK12: =IF($W12="","",IFERROR(IF(ISNUMBER(INDEX($M$9:$M$2008,$W12)),INDEX($M$9:$M$2008,$W12),VALUE(SUBSTITUTE(INDEX($M$9:$M$2008,$W12),",",""))),"")) | AL12: =IF($W12="","",IFERROR(IF(ISNUMBER(INDEX($P$9:$P$2008,$W12)),INDEX($P$9:$P$2008,$W12),VALUE(SUBSTITUTE(INDEX($P$9:$P$2008,$W12),"%",""))/100),""))
S13: =IF(AND(ISTEXT($A13),ISNUMBER(SEARCH(" - ",$A13)),ISERROR(SEARCH("Folio",$A13)),$D13=""),TRIM($A13),$S12) | T13: =IF(AND(ISNUMBER(SEARCH("Folio",$A13)),$D13<>""),1,"") | U13: =IF($T13=1,COUNTIF($T$9:$T13,1),"") | V13: =IF(AND(ISTEXT($A13),LEFT($A14,3)="Pan"),1,"") | W13: =IFERROR(MATCH(5,$U$9:$U$2008,0),"") | X13: =IF($W13="","",IF($R$5<>"",$R$5,$R$6)) | Y13: =IF($W13="","",INDEX($S$9:$S$2008,$W13)) | Z13: =IF($W13="","",IFERROR(TRIM(LEFT(SUBSTITUTE(INDEX($A$9:$A$2008,$W13),CHAR(10)," "),SEARCH("Folio",SUBSTITUTE(INDEX($A$9:$A$2008,$W13),CHAR(10)," "))-1)),TRIM(SUBSTITUTE(INDEX($A$9:$A$2008,$W13),CHAR(10)," ")))) | AA13: =IF($W13="","",IFERROR(TRIM(SUBSTITUTE(MID(SUBSTITUTE(INDEX($A$9:$A$2008,$W13),CHAR(10)," "),SEARCH("Folio",SUBSTITUTE(INDEX($A$9:$A$2008,$W13),CHAR(10)," "))+5,200),":","")),"")) | AB13: =IF($W13="","",IF(ISNUMBER(INDEX($D$9:$D$2008,$W13)),INDEX($D$9:$D$2008,$W13),IFERROR(DATE(2000+VALUE(RIGHT(INDEX($D$9:$D$2008,$W13),2)),VALUE(MID(INDEX($D$9:$D$2008,$W13),4,2)),VALUE(LEFT(INDEX($D$9:$D$2008,$W13),2))),""))) | AC13: =IF($W13="","",IFERROR(IF(ISNUMBER(INDEX($E$9:$E$2008,$W13)),INDEX($E$9:$E$2008,$W13),VALUE(SUBSTITUTE(INDEX($E$9:$E$2008,$W13),",",""))),"")) | AD13: =IF($W13="","",IFERROR(IF(ISNUMBER(INDEX($F$9:$F$2008,$W13)),INDEX($F$9:$F$2008,$W13),VALUE(SUBSTITUTE(INDEX($F$9:$F$2008,$W13),",",""))),"")) | AE13: =IF($W13="","",IFERROR(IF(ISNUMBER(INDEX($G$9:$G$2008,$W13)),INDEX($G$9:$G$2008,$W13),VALUE(SUBSTITUTE(INDEX($G$9:$G$2008,$W13),",",""))),"")) | AF13: =IF($W13="","",IFERROR(IF(ISNUMBER(INDEX($H$9:$H$2008,$W13)),INDEX($H$9:$H$2008,$W13),VALUE(SUBSTITUTE(INDEX($H$9:$H$2008,$W13),",",""))),"")) | AG13: =IF($W13="","",IFERROR(IF(ISNUMBER(INDEX($I$9:$I$2008,$W13)),INDEX($I$9:$I$2008,$W13),VALUE(SUBSTITUTE(INDEX($I$9:$I$2008,$W13),",",""))),"")) | AH13: =IF($W13="","",IFERROR(IF(ISNUMBER(INDEX($J$9:$J$2008,$W13)),INDEX($J$9:$J$2008,$W13),VALUE(SUBSTITUTE(INDEX($J$9:$J$2008,$W13),",",""))),"")) | AI13: =IF($W13="","",IFERROR(IF(ISNUMBER(INDEX($K$9:$K$2008,$W13)),INDEX($K$9:$K$2008,$W13),VALUE(SUBSTITUTE(INDEX($K$9:$K$2008,$W13),",",""))),"")) | AJ13: =IF($W13="","",IFERROR(IF(ISNUMBER(INDEX($L$9:$L$2008,$W13)),INDEX($L$9:$L$2008,$W13),VALUE(SUBSTITUTE(INDEX($L$9:$L$2008,$W13),",",""))),"")) | AK13: =IF($W13="","",IFERROR(IF(ISNUMBER(INDEX($M$9:$M$2008,$W13)),INDEX($M$9:$M$2008,$W13),VALUE(SUBSTITUTE(INDEX($M$9:$M$2008,$W13),",",""))),"")) | AL13: =IF($W13="","",IFERROR(IF(ISNUMBER(INDEX($P$9:$P$2008,$W13)),INDEX($P$9:$P$2008,$W13),VALUE(SUBSTITUTE(INDEX($P$9:$P$2008,$W13),"%",""))/100),""))
S14: =IF(AND(ISTEXT($A14),ISNUMBER(SEARCH(" - ",$A14)),ISERROR(SEARCH("Folio",$A14)),$D14=""),TRIM($A14),$S13) | T14: =IF(AND(ISNUMBER(SEARCH("Folio",$A14)),$D14<>""),1,"") | U14: =IF($T14=1,COUNTIF($T$9:$T14,1),"") | V14: =IF(AND(ISTEXT($A14),LEFT($A15,3)="Pan"),1,"") | W14: =IFERROR(MATCH(6,$U$9:$U$2008,0),"") | X14: =IF($W14="","",IF($R$5<>"",$R$5,$R$6)) | Y14: =IF($W14="","",INDEX($S$9:$S$2008,$W14)) | Z14: =IF($W14="","",IFERROR(TRIM(LEFT(SUBSTITUTE(INDEX($A$9:$A$2008,$W14),CHAR(10)," "),SEARCH("Folio",SUBSTITUTE(INDEX($A$9:$A$2008,$W14),CHAR(10)," "))-1)),TRIM(SUBSTITUTE(INDEX($A$9:$A$2008,$W14),CHAR(10)," ")))) | AA14: =IF($W14="","",IFERROR(TRIM(SUBSTITUTE(MID(SUBSTITUTE(INDEX($A$9:$A$2008,$W14),CHAR(10)," "),SEARCH("Folio",SUBSTITUTE(INDEX($A$9:$A$2008,$W14),CHAR(10)," "))+5,200),":","")),"")) | AB14: =IF($W14="","",IF(ISNUMBER(INDEX($D$9:$D$2008,$W14)),INDEX($D$9:$D$2008,$W14),IFERROR(DATE(2000+VALUE(RIGHT(INDEX($D$9:$D$2008,$W14),2)),VALUE(MID(INDEX($D$9:$D$2008,$W14),4,2)),VALUE(LEFT(INDEX($D$9:$D$2008,$W14),2))),""))) | AC14: =IF($W14="","",IFERROR(IF(ISNUMBER(INDEX($E$9:$E$2008,$W14)),INDEX($E$9:$E$2008,$W14),VALUE(SUBSTITUTE(INDEX($E$9:$E$2008,$W14),",",""))),"")) | AD14: =IF($W14="","",IFERROR(IF(ISNUMBER(INDEX($F$9:$F$2008,$W14)),INDEX($F$9:$F$2008,$W14),VALUE(SUBSTITUTE(INDEX($F$9:$F$2008,$W14),",",""))),"")) | AE14: =IF($W14="","",IFERROR(IF(ISNUMBER(INDEX($G$9:$G$2008,$W14)),INDEX($G$9:$G$2008,$W14),VALUE(SUBSTITUTE(INDEX($G$9:$G$2008,$W14),",",""))),"")) | AF14: =IF($W14="","",IFERROR(IF(ISNUMBER(INDEX($H$9:$H$2008,$W14)),INDEX($H$9:$H$2008,$W14),VALUE(SUBSTITUTE(INDEX($H$9:$H$2008,$W14),",",""))),"")) | AG14: =IF($W14="","",IFERROR(IF(ISNUMBER(INDEX($I$9:$I$2008,$W14)),INDEX($I$9:$I$2008,$W14),VALUE(SUBSTITUTE(INDEX($I$9:$I$2008,$W14),",",""))),"")) | AH14: =IF($W14="","",IFERROR(IF(ISNUMBER(INDEX($J$9:$J$2008,$W14)),INDEX($J$9:$J$2008,$W14),VALUE(SUBSTITUTE(INDEX($J$9:$J$2008,$W14),",",""))),"")) | AI14: =IF($W14="","",IFERROR(IF(ISNUMBER(INDEX($K$9:$K$2008,$W14)),INDEX($K$9:$K$2008,$W14),VALUE(SUBSTITUTE(INDEX($K$9:$K$2008,$W14),",",""))),"")) | AJ14: =IF($W14="","",IFERROR(IF(ISNUMBER(INDEX($L$9:$L$2008,$W14)),INDEX($L$9:$L$2008,$W14),VALUE(SUBSTITUTE(INDEX($L$9:$L$2008,$W14),",",""))),"")) | AK14: =IF($W14="","",IFERROR(IF(ISNUMBER(INDEX($M$9:$M$2008,$W14)),INDEX($M$9:$M$2008,$W14),VALUE(SUBSTITUTE(INDEX($M$9:$M$2008,$W14),",",""))),"")) | AL14: =IF($W14="","",IFERROR(IF(ISNUMBER(INDEX($P$9:$P$2008,$W14)),INDEX($P$9:$P$2008,$W14),VALUE(SUBSTITUTE(INDEX($P$9:$P$2008,$W14),"%",""))/100),""))
S15: =IF(AND(ISTEXT($A15),ISNUMBER(SEARCH(" - ",$A15)),ISERROR(SEARCH("Folio",$A15)),$D15=""),TRIM($A15),$S14) | T15: =IF(AND(ISNUMBER(SEARCH("Folio",$A15)),$D15<>""),1,"") | U15: =IF($T15=1,COUNTIF($T$9:$T15,1),"") | V15: =IF(AND(ISTEXT($A15),LEFT($A16,3)="Pan"),1,"") | W15: =IFERROR(MATCH(7,$U$9:$U$2008,0),"") | X15: =IF($W15="","",IF($R$5<>"",$R$5,$R$6)) | Y15: =IF($W15="","",INDEX($S$9:$S$2008,$W15)) | Z15: =IF($W15="","",IFERROR(TRIM(LEFT(SUBSTITUTE(INDEX($A$9:$A$2008,$W15),CHAR(10)," "),SEARCH("Folio",SUBSTITUTE(INDEX($A$9:$A$2008,$W15),CHAR(10)," "))-1)),TRIM(SUBSTITUTE(INDEX($A$9:$A$2008,$W15),CHAR(10)," ")))) | AA15: =IF($W15="","",IFERROR(TRIM(SUBSTITUTE(MID(SUBSTITUTE(INDEX($A$9:$A$2008,$W15),CHAR(10)," "),SEARCH("Folio",SUBSTITUTE(INDEX($A$9:$A$2008,$W15),CHAR(10)," "))+5,200),":","")),"")) | AB15: =IF($W15="","",IF(ISNUMBER(INDEX($D$9:$D$2008,$W15)),INDEX($D$9:$D$2008,$W15),IFERROR(DATE(2000+VALUE(RIGHT(INDEX($D$9:$D$2008,$W15),2)),VALUE(MID(INDEX($D$9:$D$2008,$W15),4,2)),VALUE(LEFT(INDEX($D$9:$D$2008,$W15),2))),""))) | AC15: =IF($W15="","",IFERROR(IF(ISNUMBER(INDEX($E$9:$E$2008,$W15)),INDEX($E$9:$E$2008,$W15),VALUE(SUBSTITUTE(INDEX($E$9:$E$2008,$W15),",",""))),"")) | AD15: =IF($W15="","",IFERROR(IF(ISNUMBER(INDEX($F$9:$F$2008,$W15)),INDEX($F$9:$F$2008,$W15),VALUE(SUBSTITUTE(INDEX($F$9:$F$2008,$W15),",",""))),"")) | AE15: =IF($W15="","",IFERROR(IF(ISNUMBER(INDEX($G$9:$G$2008,$W15)),INDEX($G$9:$G$2008,$W15),VALUE(SUBSTITUTE(INDEX($G$9:$G$2008,$W15),",",""))),"")) | AF15: =IF($W15="","",IFERROR(IF(ISNUMBER(INDEX($H$9:$H$2008,$W15)),INDEX($H$9:$H$2008,$W15),VALUE(SUBSTITUTE(INDEX($H$9:$H$2008,$W15),",",""))),"")) | AG15: =IF($W15="","",IFERROR(IF(ISNUMBER(INDEX($I$9:$I$2008,$W15)),INDEX($I$9:$I$2008,$W15),VALUE(SUBSTITUTE(INDEX($I$9:$I$2008,$W15),",",""))),"")) | AH15: =IF($W15="","",IFERROR(IF(ISNUMBER(INDEX($J$9:$J$2008,$W15)),INDEX($J$9:$J$2008,$W15),VALUE(SUBSTITUTE(INDEX($J$9:$J$2008,$W15),",",""))),"")) | AI15: =IF($W15="","",IFERROR(IF(ISNUMBER(INDEX($K$9:$K$2008,$W15)),INDEX($K$9:$K$2008,$W15),VALUE(SUBSTITUTE(INDEX($K$9:$K$2008,$W15),",",""))),"")) | AJ15: =IF($W15="","",IFERROR(IF(ISNUMBER(INDEX($L$9:$L$2008,$W15)),INDEX($L$9:$L$2008,$W15),VALUE(SUBSTITUTE(INDEX($L$9:$L$2008,$W15),",",""))),"")) | AK15: =IF($W15="","",IFERROR(IF(ISNUMBER(INDEX($M$9:$M$2008,$W15)),INDEX($M$9:$M$2008,$W15),VALUE(SUBSTITUTE(INDEX($M$9:$M$2008,$W15),",",""))),"")) | AL15: =IF($W15="","",IFERROR(IF(ISNUMBER(INDEX($P$9:$P$2008,$W15)),INDEX($P$9:$P$2008,$W15),VALUE(SUBSTITUTE(INDEX($P$9:$P$2008,$W15),"%",""))/100),""))
S16: =IF(AND(ISTEXT($A16),ISNUMBER(SEARCH(" - ",$A16)),ISERROR(SEARCH("Folio",$A16)),$D16=""),TRIM($A16),$S15) | T16: =IF(AND(ISNUMBER(SEARCH("Folio",$A16)),$D16<>""),1,"") | U16: =IF($T16=1,COUNTIF($T$9:$T16,1),"") | V16: =IF(AND(ISTEXT($A16),LEFT($A17,3)="Pan"),1,"") | W16: =IFERROR(MATCH(8,$U$9:$U$2008,0),"") | X16: =IF($W16="","",IF($R$5<>"",$R$5,$R$6)) | Y16: =IF($W16="","",INDEX($S$9:$S$2008,$W16)) | Z16: =IF($W16="","",IFERROR(TRIM(LEFT(SUBSTITUTE(INDEX($A$9:$A$2008,$W16),CHAR(10)," "),SEARCH("Folio",SUBSTITUTE(INDEX($A$9:$A$2008,$W16),CHAR(10)," "))-1)),TRIM(SUBSTITUTE(INDEX($A$9:$A$2008,$W16),CHAR(10)," ")))) | AA16: =IF($W16="","",IFERROR(TRIM(SUBSTITUTE(MID(SUBSTITUTE(INDEX($A$9:$A$2008,$W16),CHAR(10)," "),SEARCH("Folio",SUBSTITUTE(INDEX($A$9:$A$2008,$W16),CHAR(10)," "))+5,200),":","")),"")) | AB16: =IF($W16="","",IF(ISNUMBER(INDEX($D$9:$D$2008,$W16)),INDEX($D$9:$D$2008,$W16),IFERROR(DATE(2000+VALUE(RIGHT(INDEX($D$9:$D$2008,$W16),2)),VALUE(MID(INDEX($D$9:$D$2008,$W16),4,2)),VALUE(LEFT(INDEX($D$9:$D$2008,$W16),2))),""))) | AC16: =IF($W16="","",IFERROR(IF(ISNUMBER(INDEX($E$9:$E$2008,$W16)),INDEX($E$9:$E$2008,$W16),VALUE(SUBSTITUTE(INDEX($E$9:$E$2008,$W16),",",""))),"")) | AD16: =IF($W16="","",IFERROR(IF(ISNUMBER(INDEX($F$9:$F$2008,$W16)),INDEX($F$9:$F$2008,$W16),VALUE(SUBSTITUTE(INDEX($F$9:$F$2008,$W16),",",""))),"")) | AE16: =IF($W16="","",IFERROR(IF(ISNUMBER(INDEX($G$9:$G$2008,$W16)),INDEX($G$9:$G$2008,$W16),VALUE(SUBSTITUTE(INDEX($G$9:$G$2008,$W16),",",""))),"")) | AF16: =IF($W16="","",IFERROR(IF(ISNUMBER(INDEX($H$9:$H$2008,$W16)),INDEX($H$9:$H$2008,$W16),VALUE(SUBSTITUTE(INDEX($H$9:$H$2008,$W16),",",""))),"")) | AG16: =IF($W16="","",IFERROR(IF(ISNUMBER(INDEX($I$9:$I$2008,$W16)),INDEX($I$9:$I$2008,$W16),VALUE(SUBSTITUTE(INDEX($I$9:$I$2008,$W16),",",""))),"")) | AH16: =IF($W16="","",IFERROR(IF(ISNUMBER(INDEX($J$9:$J$2008,$W16)),INDEX($J$9:$J$2008,$W16),VALUE(SUBSTITUTE(INDEX($J$9:$J$2008,$W16),",",""))),"")) | AI16: =IF($W16="","",IFERROR(IF(ISNUMBER(INDEX($K$9:$K$2008,$W16)),INDEX($K$9:$K$2008,$W16),VALUE(SUBSTITUTE(INDEX($K$9:$K$2008,$W16),",",""))),"")) | AJ16: =IF($W16="","",IFERROR(IF(ISNUMBER(INDEX($L$9:$L$2008,$W16)),INDEX($L$9:$L$2008,$W16),VALUE(SUBSTITUTE(INDEX($L$9:$L$2008,$W16),",",""))),"")) | AK16: =IF($W16="","",IFERROR(IF(ISNUMBER(INDEX($M$9:$M$2008,$W16)),INDEX($M$9:$M$2008,$W16),VALUE(SUBSTITUTE(INDEX($M$9:$M$2008,$W16),",",""))),"")) | AL16: =IF($W16="","",IFERROR(IF(ISNUMBER(INDEX($P$9:$P$2008,$W16)),INDEX($P$9:$P$2008,$W16),VALUE(SUBSTITUTE(INDEX($P$9:$P$2008,$W16),"%",""))/100),""))
S17: =IF(AND(ISTEXT($A17),ISNUMBER(SEARCH(" - ",$A17)),ISERROR(SEARCH("Folio",$A17)),$D17=""),TRIM($A17),$S16) | T17: =IF(AND(ISNUMBER(SEARCH("Folio",$A17)),$D17<>""),1,"") | U17: =IF($T17=1,COUNTIF($T$9:$T17,1),"") | V17: =IF(AND(ISTEXT($A17),LEFT($A18,3)="Pan"),1,"") | W17: =IFERROR(MATCH(9,$U$9:$U$2008,0),"") | X17: =IF($W17="","",IF($R$5<>"",$R$5,$R$6)) | Y17: =IF($W17="","",INDEX($S$9:$S$2008,$W17)) | Z17: =IF($W17="","",IFERROR(TRIM(LEFT(SUBSTITUTE(INDEX($A$9:$A$2008,$W17),CHAR(10)," "),SEARCH("Folio",SUBSTITUTE(INDEX($A$9:$A$2008,$W17),CHAR(10)," "))-1)),TRIM(SUBSTITUTE(INDEX($A$9:$A$2008,$W17),CHAR(10)," ")))) | AA17: =IF($W17="","",IFERROR(TRIM(SUBSTITUTE(MID(SUBSTITUTE(INDEX($A$9:$A$2008,$W17),CHAR(10)," "),SEARCH("Folio",SUBSTITUTE(INDEX($A$9:$A$2008,$W17),CHAR(10)," "))+5,200),":","")),"")) | AB17: =IF($W17="","",IF(ISNUMBER(INDEX($D$9:$D$2008,$W17)),INDEX($D$9:$D$2008,$W17),IFERROR(DATE(2000+VALUE(RIGHT(INDEX($D$9:$D$2008,$W17),2)),VALUE(MID(INDEX($D$9:$D$2008,$W17),4,2)),VALUE(LEFT(INDEX($D$9:$D$2008,$W17),2))),""))) | AC17: =IF($W17="","",IFERROR(IF(ISNUMBER(INDEX($E$9:$E$2008,$W17)),INDEX($E$9:$E$2008,$W17),VALUE(SUBSTITUTE(INDEX($E$9:$E$2008,$W17),",",""))),"")) | AD17: =IF($W17="","",IFERROR(IF(ISNUMBER(INDEX($F$9:$F$2008,$W17)),INDEX($F$9:$F$2008,$W17),VALUE(SUBSTITUTE(INDEX($F$9:$F$2008,$W17),",",""))),"")) | AE17: =IF($W17="","",IFERROR(IF(ISNUMBER(INDEX($G$9:$G$2008,$W17)),INDEX($G$9:$G$2008,$W17),VALUE(SUBSTITUTE(INDEX($G$9:$G$2008,$W17),",",""))),"")) | AF17: =IF($W17="","",IFERROR(IF(ISNUMBER(INDEX($H$9:$H$2008,$W17)),INDEX($H$9:$H$2008,$W17),VALUE(SUBSTITUTE(INDEX($H$9:$H$2008,$W17),",",""))),"")) | AG17: =IF($W17="","",IFERROR(IF(ISNUMBER(INDEX($I$9:$I$2008,$W17)),INDEX($I$9:$I$2008,$W17),VALUE(SUBSTITUTE(INDEX($I$9:$I$2008,$W17),",",""))),"")) | AH17: =IF($W17="","",IFERROR(IF(ISNUMBER(INDEX($J$9:$J$2008,$W17)),INDEX($J$9:$J$2008,$W17),VALUE(SUBSTITUTE(INDEX($J$9:$J$2008,$W17),",",""))),"")) | AI17: =IF($W17="","",IFERROR(IF(ISNUMBER(INDEX($K$9:$K$2008,$W17)),INDEX($K$9:$K$2008,$W17),VALUE(SUBSTITUTE(INDEX($K$9:$K$2008,$W17),",",""))),"")) | AJ17: =IF($W17="","",IFERROR(IF(ISNUMBER(INDEX($L$9:$L$2008,$W17)),INDEX($L$9:$L$2008,$W17),VALUE(SUBSTITUTE(INDEX($L$9:$L$2008,$W17),",",""))),"")) | AK17: =IF($W17="","",IFERROR(IF(ISNUMBER(INDEX($M$9:$M$2008,$W17)),INDEX($M$9:$M$2008,$W17),VALUE(SUBSTITUTE(INDEX($M$9:$M$2008,$W17),",",""))),"")) | AL17: =IF($W17="","",IFERROR(IF(ISNUMBER(INDEX($P$9:$P$2008,$W17)),INDEX($P$9:$P$2008,$W17),VALUE(SUBSTITUTE(INDEX($P$9:$P$2008,$W17),"%",""))/100),""))
S18: =IF(AND(ISTEXT($A18),ISNUMBER(SEARCH(" - ",$A18)),ISERROR(SEARCH("Folio",$A18)),$D18=""),TRIM($A18),$S17) | T18: =IF(AND(ISNUMBER(SEARCH("Folio",$A18)),$D18<>""),1,"") | U18: =IF($T18=1,COUNTIF($T$9:$T18,1),"") | V18: =IF(AND(ISTEXT($A18),LEFT($A19,3)="Pan"),1,"") | W18: =IFERROR(MATCH(10,$U$9:$U$2008,0),"") | X18: =IF($W18="","",IF($R$5<>"",$R$5,$R$6)) | Y18: =IF($W18="","",INDEX($S$9:$S$2008,$W18)) | Z18: =IF($W18="","",IFERROR(TRIM(LEFT(SUBSTITUTE(INDEX($A$9:$A$2008,$W18),CHAR(10)," "),SEARCH("Folio",SUBSTITUTE(INDEX($A$9:$A$2008,$W18),CHAR(10)," "))-1)),TRIM(SUBSTITUTE(INDEX($A$9:$A$2008,$W18),CHAR(10)," ")))) | AA18: =IF($W18="","",IFERROR(TRIM(SUBSTITUTE(MID(SUBSTITUTE(INDEX($A$9:$A$2008,$W18),CHAR(10)," "),SEARCH("Folio",SUBSTITUTE(INDEX($A$9:$A$2008,$W18),CHAR(10)," "))+5,200),":","")),"")) | AB18: =IF($W18="","",IF(ISNUMBER(INDEX($D$9:$D$2008,$W18)),INDEX($D$9:$D$2008,$W18),IFERROR(DATE(2000+VALUE(RIGHT(INDEX($D$9:$D$2008,$W18),2)),VALUE(MID(INDEX($D$9:$D$2008,$W18),4,2)),VALUE(LEFT(INDEX($D$9:$D$2008,$W18),2))),""))) | AC18: =IF($W18="","",IFERROR(IF(ISNUMBER(INDEX($E$9:$E$2008,$W18)),INDEX($E$9:$E$2008,$W18),VALUE(SUBSTITUTE(INDEX($E$9:$E$2008,$W18),",",""))),"")) | AD18: =IF($W18="","",IFERROR(IF(ISNUMBER(INDEX($F$9:$F$2008,$W18)),INDEX($F$9:$F$2008,$W18),VALUE(SUBSTITUTE(INDEX($F$9:$F$2008,$W18),",",""))),"")) | AE18: =IF($W18="","",IFERROR(IF(ISNUMBER(INDEX($G$9:$G$2008,$W18)),INDEX($G$9:$G$2008,$W18),VALUE(SUBSTITUTE(INDEX($G$9:$G$2008,$W18),",",""))),"")) | AF18: =IF($W18="","",IFERROR(IF(ISNUMBER(INDEX($H$9:$H$2008,$W18)),INDEX($H$9:$H$2008,$W18),VALUE(SUBSTITUTE(INDEX($H$9:$H$2008,$W18),",",""))),"")) | AG18: =IF($W18="","",IFERROR(IF(ISNUMBER(INDEX($I$9:$I$2008,$W18)),INDEX($I$9:$I$2008,$W18),VALUE(SUBSTITUTE(INDEX($I$9:$I$2008,$W18),",",""))),"")) | AH18: =IF($W18="","",IFERROR(IF(ISNUMBER(INDEX($J$9:$J$2008,$W18)),INDEX($J$9:$J$2008,$W18),VALUE(SUBSTITUTE(INDEX($J$9:$J$2008,$W18),",",""))),"")) | AI18: =IF($W18="","",IFERROR(IF(ISNUMBER(INDEX($K$9:$K$2008,$W18)),INDEX($K$9:$K$2008,$W18),VALUE(SUBSTITUTE(INDEX($K$9:$K$2008,$W18),",",""))),"")) | AJ18: =IF($W18="","",IFERROR(IF(ISNUMBER(INDEX($L$9:$L$2008,$W18)),INDEX($L$9:$L$2008,$W18),VALUE(SUBSTITUTE(INDEX($L$9:$L$2008,$W18),",",""))),"")) | AK18: =IF($W18="","",IFERROR(IF(ISNUMBER(INDEX($M$9:$M$2008,$W18)),INDEX($M$9:$M$2008,$W18),VALUE(SUBSTITUTE(INDEX($M$9:$M$2008,$W18),",",""))),"")) | AL18: =IF($W18="","",IFERROR(IF(ISNUMBER(INDEX($P$9:$P$2008,$W18)),INDEX($P$9:$P$2008,$W18),VALUE(SUBSTITUTE(INDEX($P$9:$P$2008,$W18),"%",""))/100),""))
S19: =IF(AND(ISTEXT($A19),ISNUMBER(SEARCH(" - ",$A19)),ISERROR(SEARCH("Folio",$A19)),$D19=""),TRIM($A19),$S18) | T19: =IF(AND(ISNUMBER(SEARCH("Folio",$A19)),$D19<>""),1,"") | U19: =IF($T19=1,COUNTIF($T$9:$T19,1),"") | V19: =IF(AND(ISTEXT($A19),LEFT($A20,3)="Pan"),1,"") | W19: =IFERROR(MATCH(11,$U$9:$U$2008,0),"") | X19: =IF($W19="","",IF($R$5<>"",$R$5,$R$6)) | Y19: =IF($W19="","",INDEX($S$9:$S$2008,$W19)) | Z19: =IF($W19="","",IFERROR(TRIM(LEFT(SUBSTITUTE(INDEX($A$9:$A$2008,$W19),CHAR(10)," "),SEARCH("Folio",SUBSTITUTE(INDEX($A$9:$A$2008,$W19),CHAR(10)," "))-1)),TRIM(SUBSTITUTE(INDEX($A$9:$A$2008,$W19),CHAR(10)," ")))) | AA19: =IF($W19="","",IFERROR(TRIM(SUBSTITUTE(MID(SUBSTITUTE(INDEX($A$9:$A$2008,$W19),CHAR(10)," "),SEARCH("Folio",SUBSTITUTE(INDEX($A$9:$A$2008,$W19),CHAR(10)," "))+5,200),":","")),"")) | AB19: =IF($W19="","",IF(ISNUMBER(INDEX($D$9:$D$2008,$W19)),INDEX($D$9:$D$2008,$W19),IFERROR(DATE(2000+VALUE(RIGHT(INDEX($D$9:$D$2008,$W19),2)),VALUE(MID(INDEX($D$9:$D$2008,$W19),4,2)),VALUE(LEFT(INDEX($D$9:$D$2008,$W19),2))),""))) | AC19: =IF($W19="","",IFERROR(IF(ISNUMBER(INDEX($E$9:$E$2008,$W19)),INDEX($E$9:$E$2008,$W19),VALUE(SUBSTITUTE(INDEX($E$9:$E$2008,$W19),",",""))),"")) | AD19: =IF($W19="","",IFERROR(IF(ISNUMBER(INDEX($F$9:$F$2008,$W19)),INDEX($F$9:$F$2008,$W19),VALUE(SUBSTITUTE(INDEX($F$9:$F$2008,$W19),",",""))),"")) | AE19: =IF($W19="","",IFERROR(IF(ISNUMBER(INDEX($G$9:$G$2008,$W19)),INDEX($G$9:$G$2008,$W19),VALUE(SUBSTITUTE(INDEX($G$9:$G$2008,$W19),",",""))),"")) | AF19: =IF($W19="","",IFERROR(IF(ISNUMBER(INDEX($H$9:$H$2008,$W19)),INDEX($H$9:$H$2008,$W19),VALUE(SUBSTITUTE(INDEX($H$9:$H$2008,$W19),",",""))),"")) | AG19: =IF($W19="","",IFERROR(IF(ISNUMBER(INDEX($I$9:$I$2008,$W19)),INDEX($I$9:$I$2008,$W19),VALUE(SUBSTITUTE(INDEX($I$9:$I$2008,$W19),",",""))),"")) | AH19: =IF($W19="","",IFERROR(IF(ISNUMBER(INDEX($J$9:$J$2008,$W19)),INDEX($J$9:$J$2008,$W19),VALUE(SUBSTITUTE(INDEX($J$9:$J$2008,$W19),",",""))),"")) | AI19: =IF($W19="","",IFERROR(IF(ISNUMBER(INDEX($K$9:$K$2008,$W19)),INDEX($K$9:$K$2008,$W19),VALUE(SUBSTITUTE(INDEX($K$9:$K$2008,$W19),",",""))),"")) | AJ19: =IF($W19="","",IFERROR(IF(ISNUMBER(INDEX($L$9:$L$2008,$W19)),INDEX($L$9:$L$2008,$W19),VALUE(SUBSTITUTE(INDEX($L$9:$L$2008,$W19),",",""))),"")) | AK19: =IF($W19="","",IFERROR(IF(ISNUMBER(INDEX($M$9:$M$2008,$W19)),INDEX($M$9:$M$2008,$W19),VALUE(SUBSTITUTE(INDEX($M$9:$M$2008,$W19),",",""))),"")) | AL19: =IF($W19="","",IFERROR(IF(ISNUMBER(INDEX($P$9:$P$2008,$W19)),INDEX($P$9:$P$2008,$W19),VALUE(SUBSTITUTE(INDEX($P$9:$P$2008,$W19),"%",""))/100),""))
S20: =IF(AND(ISTEXT($A20),ISNUMBER(SEARCH(" - ",$A20)),ISERROR(SEARCH("Folio",$A20)),$D20=""),TRIM($A20),$S19) | T20: =IF(AND(ISNUMBER(SEARCH("Folio",$A20)),$D20<>""),1,"") | U20: =IF($T20=1,COUNTIF($T$9:$T20,1),"") | V20: =IF(AND(ISTEXT($A20),LEFT($A21,3)="Pan"),1,"") | W20: =IFERROR(MATCH(12,$U$9:$U$2008,0),"") | X20: =IF($W20="","",IF($R$5<>"",$R$5,$R$6)) | Y20: =IF($W20="","",INDEX($S$9:$S$2008,$W20)) | Z20: =IF($W20="","",IFERROR(TRIM(LEFT(SUBSTITUTE(INDEX($A$9:$A$2008,$W20),CHAR(10)," "),SEARCH("Folio",SUBSTITUTE(INDEX($A$9:$A$2008,$W20),CHAR(10)," "))-1)),TRIM(SUBSTITUTE(INDEX($A$9:$A$2008,$W20),CHAR(10)," ")))) | AA20: =IF($W20="","",IFERROR(TRIM(SUBSTITUTE(MID(SUBSTITUTE(INDEX($A$9:$A$2008,$W20),CHAR(10)," "),SEARCH("Folio",SUBSTITUTE(INDEX($A$9:$A$2008,$W20),CHAR(10)," "))+5,200),":","")),"")) | AB20: =IF($W20="","",IF(ISNUMBER(INDEX($D$9:$D$2008,$W20)),INDEX($D$9:$D$2008,$W20),IFERROR(DATE(2000+VALUE(RIGHT(INDEX($D$9:$D$2008,$W20),2)),VALUE(MID(INDEX($D$9:$D$2008,$W20),4,2)),VALUE(LEFT(INDEX($D$9:$D$2008,$W20),2))),""))) | AC20: =IF($W20="","",IFERROR(IF(ISNUMBER(INDEX($E$9:$E$2008,$W20)),INDEX($E$9:$E$2008,$W20),VALUE(SUBSTITUTE(INDEX($E$9:$E$2008,$W20),",",""))),"")) | AD20: =IF($W20="","",IFERROR(IF(ISNUMBER(INDEX($F$9:$F$2008,$W20)),INDEX($F$9:$F$2008,$W20),VALUE(SUBSTITUTE(INDEX($F$9:$F$2008,$W20),",",""))),"")) | AE20: =IF($W20="","",IFERROR(IF(ISNUMBER(INDEX($G$9:$G$2008,$W20)),INDEX($G$9:$G$2008,$W20),VALUE(SUBSTITUTE(INDEX($G$9:$G$2008,$W20),",",""))),"")) | AF20: =IF($W20="","",IFERROR(IF(ISNUMBER(INDEX($H$9:$H$2008,$W20)),INDEX($H$9:$H$2008,$W20),VALUE(SUBSTITUTE(INDEX($H$9:$H$2008,$W20),",",""))),"")) | AG20: =IF($W20="","",IFERROR(IF(ISNUMBER(INDEX($I$9:$I$2008,$W20)),INDEX($I$9:$I$2008,$W20),VALUE(SUBSTITUTE(INDEX($I$9:$I$2008,$W20),",",""))),"")) | AH20: =IF($W20="","",IFERROR(IF(ISNUMBER(INDEX($J$9:$J$2008,$W20)),INDEX($J$9:$J$2008,$W20),VALUE(SUBSTITUTE(INDEX($J$9:$J$2008,$W20),",",""))),"")) | AI20: =IF($W20="","",IFERROR(IF(ISNUMBER(INDEX($K$9:$K$2008,$W20)),INDEX($K$9:$K$2008,$W20),VALUE(SUBSTITUTE(INDEX($K$9:$K$2008,$W20),",",""))),"")) | AJ20: =IF($W20="","",IFERROR(IF(ISNUMBER(INDEX($L$9:$L$2008,$W20)),INDEX($L$9:$L$2008,$W20),VALUE(SUBSTITUTE(INDEX($L$9:$L$2008,$W20),",",""))),"")) | AK20: =IF($W20="","",IFERROR(IF(ISNUMBER(INDEX($M$9:$M$2008,$W20)),INDEX($M$9:$M$2008,$W20),VALUE(SUBSTITUTE(INDEX($M$9:$M$2008,$W20),",",""))),"")) | AL20: =IF($W20="","",IFERROR(IF(ISNUMBER(INDEX($P$9:$P$2008,$W20)),INDEX($P$9:$P$2008,$W20),VALUE(SUBSTITUTE(INDEX($P$9:$P$2008,$W20),"%",""))/100),""))
S21: =IF(AND(ISTEXT($A21),ISNUMBER(SEARCH(" - ",$A21)),ISERROR(SEARCH("Folio",$A21)),$D21=""),TRIM($A21),$S20) | T21: =IF(AND(ISNUMBER(SEARCH("Folio",$A21)),$D21<>""),1,"") | U21: =IF($T21=1,COUNTIF($T$9:$T21,1),"") | V21: =IF(AND(ISTEXT($A21),LEFT($A22,3)="Pan"),1,"") | W21: =IFERROR(MATCH(13,$U$9:$U$2008,0),"") | X21: =IF($W21="","",IF($R$5<>"",$R$5,$R$6)) | Y21: =IF($W21="","",INDEX($S$9:$S$2008,$W21)) | Z21: =IF($W21="","",IFERROR(TRIM(LEFT(SUBSTITUTE(INDEX($A$9:$A$2008,$W21),CHAR(10)," "),SEARCH("Folio",SUBSTITUTE(INDEX($A$9:$A$2008,$W21),CHAR(10)," "))-1)),TRIM(SUBSTITUTE(INDEX($A$9:$A$2008,$W21),CHAR(10)," ")))) | AA21: =IF($W21="","",IFERROR(TRIM(SUBSTITUTE(MID(SUBSTITUTE(INDEX($A$9:$A$2008,$W21),CHAR(10)," "),SEARCH("Folio",SUBSTITUTE(INDEX($A$9:$A$2008,$W21),CHAR(10)," "))+5,200),":","")),"")) | AB21: =IF($W21="","",IF(ISNUMBER(INDEX($D$9:$D$2008,$W21)),INDEX($D$9:$D$2008,$W21),IFERROR(DATE(2000+VALUE(RIGHT(INDEX($D$9:$D$2008,$W21),2)),VALUE(MID(INDEX($D$9:$D$2008,$W21),4,2)),VALUE(LEFT(INDEX($D$9:$D$2008,$W21),2))),""))) | AC21: =IF($W21="","",IFERROR(IF(ISNUMBER(INDEX($E$9:$E$2008,$W21)),INDEX($E$9:$E$2008,$W21),VALUE(SUBSTITUTE(INDEX($E$9:$E$2008,$W21),",",""))),"")) | AD21: =IF($W21="","",IFERROR(IF(ISNUMBER(INDEX($F$9:$F$2008,$W21)),INDEX($F$9:$F$2008,$W21),VALUE(SUBSTITUTE(INDEX($F$9:$F$2008,$W21),",",""))),"")) | AE21: =IF($W21="","",IFERROR(IF(ISNUMBER(INDEX($G$9:$G$2008,$W21)),INDEX($G$9:$G$2008,$W21),VALUE(SUBSTITUTE(INDEX($G$9:$G$2008,$W21),",",""))),"")) | AF21: =IF($W21="","",IFERROR(IF(ISNUMBER(INDEX($H$9:$H$2008,$W21)),INDEX($H$9:$H$2008,$W21),VALUE(SUBSTITUTE(INDEX($H$9:$H$2008,$W21),",",""))),"")) | AG21: =IF($W21="","",IFERROR(IF(ISNUMBER(INDEX($I$9:$I$2008,$W21)),INDEX($I$9:$I$2008,$W21),VALUE(SUBSTITUTE(INDEX($I$9:$I$2008,$W21),",",""))),"")) | AH21: =IF($W21="","",IFERROR(IF(ISNUMBER(INDEX($J$9:$J$2008,$W21)),INDEX($J$9:$J$2008,$W21),VALUE(SUBSTITUTE(INDEX($J$9:$J$2008,$W21),",",""))),"")) | AI21: =IF($W21="","",IFERROR(IF(ISNUMBER(INDEX($K$9:$K$2008,$W21)),INDEX($K$9:$K$2008,$W21),VALUE(SUBSTITUTE(INDEX($K$9:$K$2008,$W21),",",""))),"")) | AJ21: =IF($W21="","",IFERROR(IF(ISNUMBER(INDEX($L$9:$L$2008,$W21)),INDEX($L$9:$L$2008,$W21),VALUE(SUBSTITUTE(INDEX($L$9:$L$2008,$W21),",",""))),"")) | AK21: =IF($W21="","",IFERROR(IF(ISNUMBER(INDEX($M$9:$M$2008,$W21)),INDEX($M$9:$M$2008,$W21),VALUE(SUBSTITUTE(INDEX($M$9:$M$2008,$W21),",",""))),"")) | AL21: =IF($W21="","",IFERROR(IF(ISNUMBER(INDEX($P$9:$P$2008,$W21)),INDEX($P$9:$P$2008,$W21),VALUE(SUBSTITUTE(INDEX($P$9:$P$2008,$W21),"%",""))/100),""))
S22: =IF(AND(ISTEXT($A22),ISNUMBER(SEARCH(" - ",$A22)),ISERROR(SEARCH("Folio",$A22)),$D22=""),TRIM($A22),$S21) | T22: =IF(AND(ISNUMBER(SEARCH("Folio",$A22)),$D22<>""),1,"") | U22: =IF($T22=1,COUNTIF($T$9:$T22,1),"") | V22: =IF(AND(ISTEXT($A22),LEFT($A23,3)="Pan"),1,"") | W22: =IFERROR(MATCH(14,$U$9:$U$2008,0),"") | X22: =IF($W22="","",IF($R$5<>"",$R$5,$R$6)) | Y22: =IF($W22="","",INDEX($S$9:$S$2008,$W22)) | Z22: =IF($W22="","",IFERROR(TRIM(LEFT(SUBSTITUTE(INDEX($A$9:$A$2008,$W22),CHAR(10)," "),SEARCH("Folio",SUBSTITUTE(INDEX($A$9:$A$2008,$W22),CHAR(10)," "))-1)),TRIM(SUBSTITUTE(INDEX($A$9:$A$2008,$W22),CHAR(10)," ")))) | AA22: =IF($W22="","",IFERROR(TRIM(SUBSTITUTE(MID(SUBSTITUTE(INDEX($A$9:$A$2008,$W22),CHAR(10)," "),SEARCH("Folio",SUBSTITUTE(INDEX($A$9:$A$2008,$W22),CHAR(10)," "))+5,200),":","")),"")) | AB22: =IF($W22="","",IF(ISNUMBER(INDEX($D$9:$D$2008,$W22)),INDEX($D$9:$D$2008,$W22),IFERROR(DATE(2000+VALUE(RIGHT(INDEX($D$9:$D$2008,$W22),2)),VALUE(MID(INDEX($D$9:$D$2008,$W22),4,2)),VALUE(LEFT(INDEX($D$9:$D$2008,$W22),2))),""))) | AC22: =IF($W22="","",IFERROR(IF(ISNUMBER(INDEX($E$9:$E$2008,$W22)),INDEX($E$9:$E$2008,$W22),VALUE(SUBSTITUTE(INDEX($E$9:$E$2008,$W22),",",""))),"")) | AD22: =IF($W22="","",IFERROR(IF(ISNUMBER(INDEX($F$9:$F$2008,$W22)),INDEX($F$9:$F$2008,$W22),VALUE(SUBSTITUTE(INDEX($F$9:$F$2008,$W22),",",""))),"")) | AE22: =IF($W22="","",IFERROR(IF(ISNUMBER(INDEX($G$9:$G$2008,$W22)),INDEX($G$9:$G$2008,$W22),VALUE(SUBSTITUTE(INDEX($G$9:$G$2008,$W22),",",""))),"")) | AF22: =IF($W22="","",IFERROR(IF(ISNUMBER(INDEX($H$9:$H$2008,$W22)),INDEX($H$9:$H$2008,$W22),VALUE(SUBSTITUTE(INDEX($H$9:$H$2008,$W22),",",""))),"")) | AG22: =IF($W22="","",IFERROR(IF(ISNUMBER(INDEX($I$9:$I$2008,$W22)),INDEX($I$9:$I$2008,$W22),VALUE(SUBSTITUTE(INDEX($I$9:$I$2008,$W22),",",""))),"")) | AH22: =IF($W22="","",IFERROR(IF(ISNUMBER(INDEX($J$9:$J$2008,$W22)),INDEX($J$9:$J$2008,$W22),VALUE(SUBSTITUTE(INDEX($J$9:$J$2008,$W22),",",""))),"")) | AI22: =IF($W22="","",IFERROR(IF(ISNUMBER(INDEX($K$9:$K$2008,$W22)),INDEX($K$9:$K$2008,$W22),VALUE(SUBSTITUTE(INDEX($K$9:$K$2008,$W22),",",""))),"")) | AJ22: =IF($W22="","",IFERROR(IF(ISNUMBER(INDEX($L$9:$L$2008,$W22)),INDEX($L$9:$L$2008,$W22),VALUE(SUBSTITUTE(INDEX($L$9:$L$2008,$W22),",",""))),"")) | AK22: =IF($W22="","",IFERROR(IF(ISNUMBER(INDEX($M$9:$M$2008,$W22)),INDEX($M$9:$M$2008,$W22),VALUE(SUBSTITUTE(INDEX($M$9:$M$2008,$W22),",",""))),"")) | AL22: =IF($W22="","",IFERROR(IF(ISNUMBER(INDEX($P$9:$P$2008,$W22)),INDEX($P$9:$P$2008,$W22),VALUE(SUBSTITUTE(INDEX($P$9:$P$2008,$W22),"%",""))/100),""))
S23: =IF(AND(ISTEXT($A23),ISNUMBER(SEARCH(" - ",$A23)),ISERROR(SEARCH("Folio",$A23)),$D23=""),TRIM($A23),$S22) | T23: =IF(AND(ISNUMBER(SEARCH("Folio",$A23)),$D23<>""),1,"") | U23: =IF($T23=1,COUNTIF($T$9:$T23,1),"") | V23: =IF(AND(ISTEXT($A23),LEFT($A24,3)="Pan"),1,"") | W23: =IFERROR(MATCH(15,$U$9:$U$2008,0),"") | X23: =IF($W23="","",IF($R$5<>"",$R$5,$R$6)) | Y23: =IF($W23="","",INDEX($S$9:$S$2008,$W23)) | Z23: =IF($W23="","",IFERROR(TRIM(LEFT(SUBSTITUTE(INDEX($A$9:$A$2008,$W23),CHAR(10)," "),SEARCH("Folio",SUBSTITUTE(INDEX($A$9:$A$2008,$W23),CHAR(10)," "))-1)),TRIM(SUBSTITUTE(INDEX($A$9:$A$2008,$W23),CHAR(10)," ")))) | AA23: =IF($W23="","",IFERROR(TRIM(SUBSTITUTE(MID(SUBSTITUTE(INDEX($A$9:$A$2008,$W23),CHAR(10)," "),SEARCH("Folio",SUBSTITUTE(INDEX($A$9:$A$2008,$W23),CHAR(10)," "))+5,200),":","")),"")) | AB23: =IF($W23="","",IF(ISNUMBER(INDEX($D$9:$D$2008,$W23)),INDEX($D$9:$D$2008,$W23),IFERROR(DATE(2000+VALUE(RIGHT(INDEX($D$9:$D$2008,$W23),2)),VALUE(MID(INDEX($D$9:$D$2008,$W23),4,2)),VALUE(LEFT(INDEX($D$9:$D$2008,$W23),2))),""))) | AC23: =IF($W23="","",IFERROR(IF(ISNUMBER(INDEX($E$9:$E$2008,$W23)),INDEX($E$9:$E$2008,$W23),VALUE(SUBSTITUTE(INDEX($E$9:$E$2008,$W23),",",""))),"")) | AD23: =IF($W23="","",IFERROR(IF(ISNUMBER(INDEX($F$9:$F$2008,$W23)),INDEX($F$9:$F$2008,$W23),VALUE(SUBSTITUTE(INDEX($F$9:$F$2008,$W23),",",""))),"")) | AE23: =IF($W23="","",IFERROR(IF(ISNUMBER(INDEX($G$9:$G$2008,$W23)),INDEX($G$9:$G$2008,$W23),VALUE(SUBSTITUTE(INDEX($G$9:$G$2008,$W23),",",""))),"")) | AF23: =IF($W23="","",IFERROR(IF(ISNUMBER(INDEX($H$9:$H$2008,$W23)),INDEX($H$9:$H$2008,$W23),VALUE(SUBSTITUTE(INDEX($H$9:$H$2008,$W23),",",""))),"")) | AG23: =IF($W23="","",IFERROR(IF(ISNUMBER(INDEX($I$9:$I$2008,$W23)),INDEX($I$9:$I$2008,$W23),VALUE(SUBSTITUTE(INDEX($I$9:$I$2008,$W23),",",""))),"")) | AH23: =IF($W23="","",IFERROR(IF(ISNUMBER(INDEX($J$9:$J$2008,$W23)),INDEX($J$9:$J$2008,$W23),VALUE(SUBSTITUTE(INDEX($J$9:$J$2008,$W23),",",""))),"")) | AI23: =IF($W23="","",IFERROR(IF(ISNUMBER(INDEX($K$9:$K$2008,$W23)),INDEX($K$9:$K$2008,$W23),VALUE(SUBSTITUTE(INDEX($K$9:$K$2008,$W23),",",""))),"")) | AJ23: =IF($W23="","",IFERROR(IF(ISNUMBER(INDEX($L$9:$L$2008,$W23)),INDEX($L$9:$L$2008,$W23),VALUE(SUBSTITUTE(INDEX($L$9:$L$2008,$W23),",",""))),"")) | AK23: =IF($W23="","",IFERROR(IF(ISNUMBER(INDEX($M$9:$M$2008,$W23)),INDEX($M$9:$M$2008,$W23),VALUE(SUBSTITUTE(INDEX($M$9:$M$2008,$W23),",",""))),"")) | AL23: =IF($W23="","",IFERROR(IF(ISNUMBER(INDEX($P$9:$P$2008,$W23)),INDEX($P$9:$P$2008,$W23),VALUE(SUBSTITUTE(INDEX($P$9:$P$2008,$W23),"%",""))/100),""))
S24: =IF(AND(ISTEXT($A24),ISNUMBER(SEARCH(" - ",$A24)),ISERROR(SEARCH("Folio",$A24)),$D24=""),TRIM($A24),$S23) | T24: =IF(AND(ISNUMBER(SEARCH("Folio",$A24)),$D24<>""),1,"") | U24: =IF($T24=1,COUNTIF($T$9:$T24,1),"") | V24: =IF(AND(ISTEXT($A24),LEFT($A25,3)="Pan"),1,"") | W24: =IFERROR(MATCH(16,$U$9:$U$2008,0),"") | X24: =IF($W24="","",IF($R$5<>"",$R$5,$R$6)) | Y24: =IF($W24="","",INDEX($S$9:$S$2008,$W24)) | Z24: =IF($W24="","",IFERROR(TRIM(LEFT(SUBSTITUTE(INDEX($A$9:$A$2008,$W24),CHAR(10)," "),SEARCH("Folio",SUBSTITUTE(INDEX($A$9:$A$2008,$W24),CHAR(10)," "))-1)),TRIM(SUBSTITUTE(INDEX($A$9:$A$2008,$W24),CHAR(10)," ")))) | AA24: =IF($W24="","",IFERROR(TRIM(SUBSTITUTE(MID(SUBSTITUTE(INDEX($A$9:$A$2008,$W24),CHAR(10)," "),SEARCH("Folio",SUBSTITUTE(INDEX($A$9:$A$2008,$W24),CHAR(10)," "))+5,200),":","")),"")) | AB24: =IF($W24="","",IF(ISNUMBER(INDEX($D$9:$D$2008,$W24)),INDEX($D$9:$D$2008,$W24),IFERROR(DATE(2000+VALUE(RIGHT(INDEX($D$9:$D$2008,$W24),2)),VALUE(MID(INDEX($D$9:$D$2008,$W24),4,2)),VALUE(LEFT(INDEX($D$9:$D$2008,$W24),2))),""))) | AC24: =IF($W24="","",IFERROR(IF(ISNUMBER(INDEX($E$9:$E$2008,$W24)),INDEX($E$9:$E$2008,$W24),VALUE(SUBSTITUTE(INDEX($E$9:$E$2008,$W24),",",""))),"")) | AD24: =IF($W24="","",IFERROR(IF(ISNUMBER(INDEX($F$9:$F$2008,$W24)),INDEX($F$9:$F$2008,$W24),VALUE(SUBSTITUTE(INDEX($F$9:$F$2008,$W24),",",""))),"")) | AE24: =IF($W24="","",IFERROR(IF(ISNUMBER(INDEX($G$9:$G$2008,$W24)),INDEX($G$9:$G$2008,$W24),VALUE(SUBSTITUTE(INDEX($G$9:$G$2008,$W24),",",""))),"")) | AF24: =IF($W24="","",IFERROR(IF(ISNUMBER(INDEX($H$9:$H$2008,$W24)),INDEX($H$9:$H$2008,$W24),VALUE(SUBSTITUTE(INDEX($H$9:$H$2008,$W24),",",""))),"")) | AG24: =IF($W24="","",IFERROR(IF(ISNUMBER(INDEX($I$9:$I$2008,$W24)),INDEX($I$9:$I$2008,$W24),VALUE(SUBSTITUTE(INDEX($I$9:$I$2008,$W24),",",""))),"")) | AH24: =IF($W24="","",IFERROR(IF(ISNUMBER(INDEX($J$9:$J$2008,$W24)),INDEX($J$9:$J$2008,$W24),VALUE(SUBSTITUTE(INDEX($J$9:$J$2008,$W24),",",""))),"")) | AI24: =IF($W24="","",IFERROR(IF(ISNUMBER(INDEX($K$9:$K$2008,$W24)),INDEX($K$9:$K$2008,$W24),VALUE(SUBSTITUTE(INDEX($K$9:$K$2008,$W24),",",""))),"")) | AJ24: =IF($W24="","",IFERROR(IF(ISNUMBER(INDEX($L$9:$L$2008,$W24)),INDEX($L$9:$L$2008,$W24),VALUE(SUBSTITUTE(INDEX($L$9:$L$2008,$W24),",",""))),"")) | AK24: =IF($W24="","",IFERROR(IF(ISNUMBER(INDEX($M$9:$M$2008,$W24)),INDEX($M$9:$M$2008,$W24),VALUE(SUBSTITUTE(INDEX($M$9:$M$2008,$W24),",",""))),"")) | AL24: =IF($W24="","",IFERROR(IF(ISNUMBER(INDEX($P$9:$P$2008,$W24)),INDEX($P$9:$P$2008,$W24),VALUE(SUBSTITUTE(INDEX($P$9:$P$2008,$W24),"%",""))/100),""))
S25: =IF(AND(ISTEXT($A25),ISNUMBER(SEARCH(" - ",$A25)),ISERROR(SEARCH("Folio",$A25)),$D25=""),TRIM($A25),$S24) | T25: =IF(AND(ISNUMBER(SEARCH("Folio",$A25)),$D25<>""),1,"") | U25: =IF($T25=1,COUNTIF($T$9:$T25,1),"") | V25: =IF(AND(ISTEXT($A25),LEFT($A26,3)="Pan"),1,"") | W25: =IFERROR(MATCH(17,$U$9:$U$2008,0),"") | X25: =IF($W25="","",IF($R$5<>"",$R$5,$R$6)) | Y25: =IF($W25="","",INDEX($S$9:$S$2008,$W25)) | Z25: =IF($W25="","",IFERROR(TRIM(LEFT(SUBSTITUTE(INDEX($A$9:$A$2008,$W25),CHAR(10)," "),SEARCH("Folio",SUBSTITUTE(INDEX($A$9:$A$2008,$W25),CHAR(10)," "))-1)),TRIM(SUBSTITUTE(INDEX($A$9:$A$2008,$W25),CHAR(10)," ")))) | AA25: =IF($W25="","",IFERROR(TRIM(SUBSTITUTE(MID(SUBSTITUTE(INDEX($A$9:$A$2008,$W25),CHAR(10)," "),SEARCH("Folio",SUBSTITUTE(INDEX($A$9:$A$2008,$W25),CHAR(10)," "))+5,200),":","")),"")) | AB25: =IF($W25="","",IF(ISNUMBER(INDEX($D$9:$D$2008,$W25)),INDEX($D$9:$D$2008,$W25),IFERROR(DATE(2000+VALUE(RIGHT(INDEX($D$9:$D$2008,$W25),2)),VALUE(MID(INDEX($D$9:$D$2008,$W25),4,2)),VALUE(LEFT(INDEX($D$9:$D$2008,$W25),2))),""))) | AC25: =IF($W25="","",IFERROR(IF(ISNUMBER(INDEX($E$9:$E$2008,$W25)),INDEX($E$9:$E$2008,$W25),VALUE(SUBSTITUTE(INDEX($E$9:$E$2008,$W25),",",""))),"")) | AD25: =IF($W25="","",IFERROR(IF(ISNUMBER(INDEX($F$9:$F$2008,$W25)),INDEX($F$9:$F$2008,$W25),VALUE(SUBSTITUTE(INDEX($F$9:$F$2008,$W25),",",""))),"")) | AE25: =IF($W25="","",IFERROR(IF(ISNUMBER(INDEX($G$9:$G$2008,$W25)),INDEX($G$9:$G$2008,$W25),VALUE(SUBSTITUTE(INDEX($G$9:$G$2008,$W25),",",""))),"")) | AF25: =IF($W25="","",IFERROR(IF(ISNUMBER(INDEX($H$9:$H$2008,$W25)),INDEX($H$9:$H$2008,$W25),VALUE(SUBSTITUTE(INDEX($H$9:$H$2008,$W25),",",""))),"")) | AG25: =IF($W25="","",IFERROR(IF(ISNUMBER(INDEX($I$9:$I$2008,$W25)),INDEX($I$9:$I$2008,$W25),VALUE(SUBSTITUTE(INDEX($I$9:$I$2008,$W25),",",""))),"")) | AH25: =IF($W25="","",IFERROR(IF(ISNUMBER(INDEX($J$9:$J$2008,$W25)),INDEX($J$9:$J$2008,$W25),VALUE(SUBSTITUTE(INDEX($J$9:$J$2008,$W25),",",""))),"")) | AI25: =IF($W25="","",IFERROR(IF(ISNUMBER(INDEX($K$9:$K$2008,$W25)),INDEX($K$9:$K$2008,$W25),VALUE(SUBSTITUTE(INDEX($K$9:$K$2008,$W25),",",""))),"")) | AJ25: =IF($W25="","",IFERROR(IF(ISNUMBER(INDEX($L$9:$L$2008,$W25)),INDEX($L$9:$L$2008,$W25),VALUE(SUBSTITUTE(INDEX($L$9:$L$2008,$W25),",",""))),"")) | AK25: =IF($W25="","",IFERROR(IF(ISNUMBER(INDEX($M$9:$M$2008,$W25)),INDEX($M$9:$M$2008,$W25),VALUE(SUBSTITUTE(INDEX($M$9:$M$2008,$W25),",",""))),"")) | AL25: =IF($W25="","",IFERROR(IF(ISNUMBER(INDEX($P$9:$P$2008,$W25)),INDEX($P$9:$P$2008,$W25),VALUE(SUBSTITUTE(INDEX($P$9:$P$2008,$W25),"%",""))/100),""))
S26: =IF(AND(ISTEXT($A26),ISNUMBER(SEARCH(" - ",$A26)),ISERROR(SEARCH("Folio",$A26)),$D26=""),TRIM($A26),$S25) | T26: =IF(AND(ISNUMBER(SEARCH("Folio",$A26)),$D26<>""),1,"") | U26: =IF($T26=1,COUNTIF($T$9:$T26,1),"") | V26: =IF(AND(ISTEXT($A26),LEFT($A27,3)="Pan"),1,"") | W26: =IFERROR(MATCH(18,$U$9:$U$2008,0),"") | X26: =IF($W26="","",IF($R$5<>"",$R$5,$R$6)) | Y26: =IF($W26="","",INDEX($S$9:$S$2008,$W26)) | Z26: =IF($W26="","",IFERROR(TRIM(LEFT(SUBSTITUTE(INDEX($A$9:$A$2008,$W26),CHAR(10)," "),SEARCH("Folio",SUBSTITUTE(INDEX($A$9:$A$2008,$W26),CHAR(10)," "))-1)),TRIM(SUBSTITUTE(INDEX($A$9:$A$2008,$W26),CHAR(10)," ")))) | AA26: =IF($W26="","",IFERROR(TRIM(SUBSTITUTE(MID(SUBSTITUTE(INDEX($A$9:$A$2008,$W26),CHAR(10)," "),SEARCH("Folio",SUBSTITUTE(INDEX($A$9:$A$2008,$W26),CHAR(10)," "))+5,200),":","")),"")) | AB26: =IF($W26="","",IF(ISNUMBER(INDEX($D$9:$D$2008,$W26)),INDEX($D$9:$D$2008,$W26),IFERROR(DATE(2000+VALUE(RIGHT(INDEX($D$9:$D$2008,$W26),2)),VALUE(MID(INDEX($D$9:$D$2008,$W26),4,2)),VALUE(LEFT(INDEX($D$9:$D$2008,$W26),2))),""))) | AC26: =IF($W26="","",IFERROR(IF(ISNUMBER(INDEX($E$9:$E$2008,$W26)),INDEX($E$9:$E$2008,$W26),VALUE(SUBSTITUTE(INDEX($E$9:$E$2008,$W26),",",""))),"")) | AD26: =IF($W26="","",IFERROR(IF(ISNUMBER(INDEX($F$9:$F$2008,$W26)),INDEX($F$9:$F$2008,$W26),VALUE(SUBSTITUTE(INDEX($F$9:$F$2008,$W26),",",""))),"")) | AE26: =IF($W26="","",IFERROR(IF(ISNUMBER(INDEX($G$9:$G$2008,$W26)),INDEX($G$9:$G$2008,$W26),VALUE(SUBSTITUTE(INDEX($G$9:$G$2008,$W26),",",""))),"")) | AF26: =IF($W26="","",IFERROR(IF(ISNUMBER(INDEX($H$9:$H$2008,$W26)),INDEX($H$9:$H$2008,$W26),VALUE(SUBSTITUTE(INDEX($H$9:$H$2008,$W26),",",""))),"")) | AG26: =IF($W26="","",IFERROR(IF(ISNUMBER(INDEX($I$9:$I$2008,$W26)),INDEX($I$9:$I$2008,$W26),VALUE(SUBSTITUTE(INDEX($I$9:$I$2008,$W26),",",""))),"")) | AH26: =IF($W26="","",IFERROR(IF(ISNUMBER(INDEX($J$9:$J$2008,$W26)),INDEX($J$9:$J$2008,$W26),VALUE(SUBSTITUTE(INDEX($J$9:$J$2008,$W26),",",""))),"")) | AI26: =IF($W26="","",IFERROR(IF(ISNUMBER(INDEX($K$9:$K$2008,$W26)),INDEX($K$9:$K$2008,$W26),VALUE(SUBSTITUTE(INDEX($K$9:$K$2008,$W26),",",""))),"")) | AJ26: =IF($W26="","",IFERROR(IF(ISNUMBER(INDEX($L$9:$L$2008,$W26)),INDEX($L$9:$L$2008,$W26),VALUE(SUBSTITUTE(INDEX($L$9:$L$2008,$W26),",",""))),"")) | AK26: =IF($W26="","",IFERROR(IF(ISNUMBER(INDEX($M$9:$M$2008,$W26)),INDEX($M$9:$M$2008,$W26),VALUE(SUBSTITUTE(INDEX($M$9:$M$2008,$W26),",",""))),"")) | AL26: =IF($W26="","",IFERROR(IF(ISNUMBER(INDEX($P$9:$P$2008,$W26)),INDEX($P$9:$P$2008,$W26),VALUE(SUBSTITUTE(INDEX($P$9:$P$2008,$W26),"%",""))/100),""))
S27: =IF(AND(ISTEXT($A27),ISNUMBER(SEARCH(" - ",$A27)),ISERROR(SEARCH("Folio",$A27)),$D27=""),TRIM($A27),$S26) | T27: =IF(AND(ISNUMBER(SEARCH("Folio",$A27)),$D27<>""),1,"") | U27: =IF($T27=1,COUNTIF($T$9:$T27,1),"") | V27: =IF(AND(ISTEXT($A27),LEFT($A28,3)="Pan"),1,"") | W27: =IFERROR(MATCH(19,$U$9:$U$2008,0),"") | X27: =IF($W27="","",IF($R$5<>"",$R$5,$R$6)) | Y27: =IF($W27="","",INDEX($S$9:$S$2008,$W27)) | Z27: =IF($W27="","",IFERROR(TRIM(LEFT(SUBSTITUTE(INDEX($A$9:$A$2008,$W27),CHAR(10)," "),SEARCH("Folio",SUBSTITUTE(INDEX($A$9:$A$2008,$W27),CHAR(10)," "))-1)),TRIM(SUBSTITUTE(INDEX($A$9:$A$2008,$W27),CHAR(10)," ")))) | AA27: =IF($W27="","",IFERROR(TRIM(SUBSTITUTE(MID(SUBSTITUTE(INDEX($A$9:$A$2008,$W27),CHAR(10)," "),SEARCH("Folio",SUBSTITUTE(INDEX($A$9:$A$2008,$W27),CHAR(10)," "))+5,200),":","")),"")) | AB27: =IF($W27="","",IF(ISNUMBER(INDEX($D$9:$D$2008,$W27)),INDEX($D$9:$D$2008,$W27),IFERROR(DATE(2000+VALUE(RIGHT(INDEX($D$9:$D$2008,$W27),2)),VALUE(MID(INDEX($D$9:$D$2008,$W27),4,2)),VALUE(LEFT(INDEX($D$9:$D$2008,$W27),2))),""))) | AC27: =IF($W27="","",IFERROR(IF(ISNUMBER(INDEX($E$9:$E$2008,$W27)),INDEX($E$9:$E$2008,$W27),VALUE(SUBSTITUTE(INDEX($E$9:$E$2008,$W27),",",""))),"")) | AD27: =IF($W27="","",IFERROR(IF(ISNUMBER(INDEX($F$9:$F$2008,$W27)),INDEX($F$9:$F$2008,$W27),VALUE(SUBSTITUTE(INDEX($F$9:$F$2008,$W27),",",""))),"")) | AE27: =IF($W27="","",IFERROR(IF(ISNUMBER(INDEX($G$9:$G$2008,$W27)),INDEX($G$9:$G$2008,$W27),VALUE(SUBSTITUTE(INDEX($G$9:$G$2008,$W27),",",""))),"")) | AF27: =IF($W27="","",IFERROR(IF(ISNUMBER(INDEX($H$9:$H$2008,$W27)),INDEX($H$9:$H$2008,$W27),VALUE(SUBSTITUTE(INDEX($H$9:$H$2008,$W27),",",""))),"")) | AG27: =IF($W27="","",IFERROR(IF(ISNUMBER(INDEX($I$9:$I$2008,$W27)),INDEX($I$9:$I$2008,$W27),VALUE(SUBSTITUTE(INDEX($I$9:$I$2008,$W27),",",""))),"")) | AH27: =IF($W27="","",IFERROR(IF(ISNUMBER(INDEX($J$9:$J$2008,$W27)),INDEX($J$9:$J$2008,$W27),VALUE(SUBSTITUTE(INDEX($J$9:$J$2008,$W27),",",""))),"")) | AI27: =IF($W27="","",IFERROR(IF(ISNUMBER(INDEX($K$9:$K$2008,$W27)),INDEX($K$9:$K$2008,$W27),VALUE(SUBSTITUTE(INDEX($K$9:$K$2008,$W27),",",""))),"")) | AJ27: =IF($W27="","",IFERROR(IF(ISNUMBER(INDEX($L$9:$L$2008,$W27)),INDEX($L$9:$L$2008,$W27),VALUE(SUBSTITUTE(INDEX($L$9:$L$2008,$W27),",",""))),"")) | AK27: =IF($W27="","",IFERROR(IF(ISNUMBER(INDEX($M$9:$M$2008,$W27)),INDEX($M$9:$M$2008,$W27),VALUE(SUBSTITUTE(INDEX($M$9:$M$2008,$W27),",",""))),"")) | AL27: =IF($W27="","",IFERROR(IF(ISNUMBER(INDEX($P$9:$P$2008,$W27)),INDEX($P$9:$P$2008,$W27),VALUE(SUBSTITUTE(INDEX($P$9:$P$2008,$W27),"%",""))/100),""))
S28: =IF(AND(ISTEXT($A28),ISNUMBER(SEARCH(" - ",$A28)),ISERROR(SEARCH("Folio",$A28)),$D28=""),TRIM($A28),$S27) | T28: =IF(AND(ISNUMBER(SEARCH("Folio",$A28)),$D28<>""),1,"") | U28: =IF($T28=1,COUNTIF($T$9:$T28,1),"") | V28: =IF(AND(ISTEXT($A28),LEFT($A29,3)="Pan"),1,"") | W28: =IFERROR(MATCH(20,$U$9:$U$2008,0),"") | X28: =IF($W28="","",IF($R$5<>"",$R$5,$R$6)) | Y28: =IF($W28="","",INDEX($S$9:$S$2008,$W28)) | Z28: =IF($W28="","",IFERROR(TRIM(LEFT(SUBSTITUTE(INDEX($A$9:$A$2008,$W28),CHAR(10)," "),SEARCH("Folio",SUBSTITUTE(INDEX($A$9:$A$2008,$W28),CHAR(10)," "))-1)),TRIM(SUBSTITUTE(INDEX($A$9:$A$2008,$W28),CHAR(10)," ")))) | AA28: =IF($W28="","",IFERROR(TRIM(SUBSTITUTE(MID(SUBSTITUTE(INDEX($A$9:$A$2008,$W28),CHAR(10)," "),SEARCH("Folio",SUBSTITUTE(INDEX($A$9:$A$2008,$W28),CHAR(10)," "))+5,200),":","")),"")) | AB28: =IF($W28="","",IF(ISNUMBER(INDEX($D$9:$D$2008,$W28)),INDEX($D$9:$D$2008,$W28),IFERROR(DATE(2000+VALUE(RIGHT(INDEX($D$9:$D$2008,$W28),2)),VALUE(MID(INDEX($D$9:$D$2008,$W28),4,2)),VALUE(LEFT(INDEX($D$9:$D$2008,$W28),2))),""))) | AC28: =IF($W28="","",IFERROR(IF(ISNUMBER(INDEX($E$9:$E$2008,$W28)),INDEX($E$9:$E$2008,$W28),VALUE(SUBSTITUTE(INDEX($E$9:$E$2008,$W28),",",""))),"")) | AD28: =IF($W28="","",IFERROR(IF(ISNUMBER(INDEX($F$9:$F$2008,$W28)),INDEX($F$9:$F$2008,$W28),VALUE(SUBSTITUTE(INDEX($F$9:$F$2008,$W28),",",""))),"")) | AE28: =IF($W28="","",IFERROR(IF(ISNUMBER(INDEX($G$9:$G$2008,$W28)),INDEX($G$9:$G$2008,$W28),VALUE(SUBSTITUTE(INDEX($G$9:$G$2008,$W28),",",""))),"")) | AF28: =IF($W28="","",IFERROR(IF(ISNUMBER(INDEX($H$9:$H$2008,$W28)),INDEX($H$9:$H$2008,$W28),VALUE(SUBSTITUTE(INDEX($H$9:$H$2008,$W28),",",""))),"")) | AG28: =IF($W28="","",IFERROR(IF(ISNUMBER(INDEX($I$9:$I$2008,$W28)),INDEX($I$9:$I$2008,$W28),VALUE(SUBSTITUTE(INDEX($I$9:$I$2008,$W28),",",""))),"")) | AH28: =IF($W28="","",IFERROR(IF(ISNUMBER(INDEX($J$9:$J$2008,$W28)),INDEX($J$9:$J$2008,$W28),VALUE(SUBSTITUTE(INDEX($J$9:$J$2008,$W28),",",""))),"")) | AI28: =IF($W28="","",IFERROR(IF(ISNUMBER(INDEX($K$9:$K$2008,$W28)),INDEX($K$9:$K$2008,$W28),VALUE(SUBSTITUTE(INDEX($K$9:$K$2008,$W28),",",""))),"")) | AJ28: =IF($W28="","",IFERROR(IF(ISNUMBER(INDEX($L$9:$L$2008,$W28)),INDEX($L$9:$L$2008,$W28),VALUE(SUBSTITUTE(INDEX($L$9:$L$2008,$W28),",",""))),"")) | AK28: =IF($W28="","",IFERROR(IF(ISNUMBER(INDEX($M$9:$M$2008,$W28)),INDEX($M$9:$M$2008,$W28),VALUE(SUBSTITUTE(INDEX($M$9:$M$2008,$W28),",",""))),"")) | AL28: =IF($W28="","",IFERROR(IF(ISNUMBER(INDEX($P$9:$P$2008,$W28)),INDEX($P$9:$P$2008,$W28),VALUE(SUBSTITUTE(INDEX($P$9:$P$2008,$W28),"%",""))/100),""))
S29: =IF(AND(ISTEXT($A29),ISNUMBER(SEARCH(" - ",$A29)),ISERROR(SEARCH("Folio",$A29)),$D29=""),TRIM($A29),$S28) | T29: =IF(AND(ISNUMBER(SEARCH("Folio",$A29)),$D29<>""),1,"") | U29: =IF($T29=1,COUNTIF($T$9:$T29,1),"") | V29: =IF(AND(ISTEXT($A29),LEFT($A30,3)="Pan"),1,"") | W29: =IFERROR(MATCH(21,$U$9:$U$2008,0),"") | X29: =IF($W29="","",IF($R$5<>"",$R$5,$R$6)) | Y29: =IF($W29="","",INDEX($S$9:$S$2008,$W29)) | Z29: =IF($W29="","",IFERROR(TRIM(LEFT(SUBSTITUTE(INDEX($A$9:$A$2008,$W29),CHAR(10)," "),SEARCH("Folio",SUBSTITUTE(INDEX($A$9:$A$2008,$W29),CHAR(10)," "))-1)),TRIM(SUBSTITUTE(INDEX($A$9:$A$2008,$W29),CHAR(10)," ")))) | AA29: =IF($W29="","",IFERROR(TRIM(SUBSTITUTE(MID(SUBSTITUTE(INDEX($A$9:$A$2008,$W29),CHAR(10)," "),SEARCH("Folio",SUBSTITUTE(INDEX($A$9:$A$2008,$W29),CHAR(10)," "))+5,200),":","")),"")) | AB29: =IF($W29="","",IF(ISNUMBER(INDEX($D$9:$D$2008,$W29)),INDEX($D$9:$D$2008,$W29),IFERROR(DATE(2000+VALUE(RIGHT(INDEX($D$9:$D$2008,$W29),2)),VALUE(MID(INDEX($D$9:$D$2008,$W29),4,2)),VALUE(LEFT(INDEX($D$9:$D$2008,$W29),2))),""))) | AC29: =IF($W29="","",IFERROR(IF(ISNUMBER(INDEX($E$9:$E$2008,$W29)),INDEX($E$9:$E$2008,$W29),VALUE(SUBSTITUTE(INDEX($E$9:$E$2008,$W29),",",""))),"")) | AD29: =IF($W29="","",IFERROR(IF(ISNUMBER(INDEX($F$9:$F$2008,$W29)),INDEX($F$9:$F$2008,$W29),VALUE(SUBSTITUTE(INDEX($F$9:$F$2008,$W29),",",""))),"")) | AE29: =IF($W29="","",IFERROR(IF(ISNUMBER(INDEX($G$9:$G$2008,$W29)),INDEX($G$9:$G$2008,$W29),VALUE(SUBSTITUTE(INDEX($G$9:$G$2008,$W29),",",""))),"")) | AF29: =IF($W29="","",IFERROR(IF(ISNUMBER(INDEX($H$9:$H$2008,$W29)),INDEX($H$9:$H$2008,$W29),VALUE(SUBSTITUTE(INDEX($H$9:$H$2008,$W29),",",""))),"")) | AG29: =IF($W29="","",IFERROR(IF(ISNUMBER(INDEX($I$9:$I$2008,$W29)),INDEX($I$9:$I$2008,$W29),VALUE(SUBSTITUTE(INDEX($I$9:$I$2008,$W29),",",""))),"")) | AH29: =IF($W29="","",IFERROR(IF(ISNUMBER(INDEX($J$9:$J$2008,$W29)),INDEX($J$9:$J$2008,$W29),VALUE(SUBSTITUTE(INDEX($J$9:$J$2008,$W29),",",""))),"")) | AI29: =IF($W29="","",IFERROR(IF(ISNUMBER(INDEX($K$9:$K$2008,$W29)),INDEX($K$9:$K$2008,$W29),VALUE(SUBSTITUTE(INDEX($K$9:$K$2008,$W29),",",""))),"")) | AJ29: =IF($W29="","",IFERROR(IF(ISNUMBER(INDEX($L$9:$L$2008,$W29)),INDEX($L$9:$L$2008,$W29),VALUE(SUBSTITUTE(INDEX($L$9:$L$2008,$W29),",",""))),"")) | AK29: =IF($W29="","",IFERROR(IF(ISNUMBER(INDEX($M$9:$M$2008,$W29)),INDEX($M$9:$M$2008,$W29),VALUE(SUBSTITUTE(INDEX($M$9:$M$2008,$W29),",",""))),"")) | AL29: =IF($W29="","",IFERROR(IF(ISNUMBER(INDEX($P$9:$P$2008,$W29)),INDEX($P$9:$P$2008,$W29),VALUE(SUBSTITUTE(INDEX($P$9:$P$2008,$W29),"%",""))/100),""))
S30: =IF(AND(ISTEXT($A30),ISNUMBER(SEARCH(" - ",$A30)),ISERROR(SEARCH("Folio",$A30)),$D30=""),TRIM($A30),$S29) | T30: =IF(AND(ISNUMBER(SEARCH("Folio",$A30)),$D30<>""),1,"") | U30: =IF($T30=1,COUNTIF($T$9:$T30,1),"") | V30: =IF(AND(ISTEXT($A30),LEFT($A31,3)="Pan"),1,"") | W30: =IFERROR(MATCH(22,$U$9:$U$2008,0),"") | X30: =IF($W30="","",IF($R$5<>"",$R$5,$R$6)) | Y30: =IF($W30="","",INDEX($S$9:$S$2008,$W30)) | Z30: =IF($W30="","",IFERROR(TRIM(LEFT(SUBSTITUTE(INDEX($A$9:$A$2008,$W30),CHAR(10)," "),SEARCH("Folio",SUBSTITUTE(INDEX($A$9:$A$2008,$W30),CHAR(10)," "))-1)),TRIM(SUBSTITUTE(INDEX($A$9:$A$2008,$W30),CHAR(10)," ")))) | AA30: =IF($W30="","",IFERROR(TRIM(SUBSTITUTE(MID(SUBSTITUTE(INDEX($A$9:$A$2008,$W30),CHAR(10)," "),SEARCH("Folio",SUBSTITUTE(INDEX($A$9:$A$2008,$W30),CHAR(10)," "))+5,200),":","")),"")) | AB30: =IF($W30="","",IF(ISNUMBER(INDEX($D$9:$D$2008,$W30)),INDEX($D$9:$D$2008,$W30),IFERROR(DATE(2000+VALUE(RIGHT(INDEX($D$9:$D$2008,$W30),2)),VALUE(MID(INDEX($D$9:$D$2008,$W30),4,2)),VALUE(LEFT(INDEX($D$9:$D$2008,$W30),2))),""))) | AC30: =IF($W30="","",IFERROR(IF(ISNUMBER(INDEX($E$9:$E$2008,$W30)),INDEX($E$9:$E$2008,$W30),VALUE(SUBSTITUTE(INDEX($E$9:$E$2008,$W30),",",""))),"")) | AD30: =IF($W30="","",IFERROR(IF(ISNUMBER(INDEX($F$9:$F$2008,$W30)),INDEX($F$9:$F$2008,$W30),VALUE(SUBSTITUTE(INDEX($F$9:$F$2008,$W30),",",""))),"")) | AE30: =IF($W30="","",IFERROR(IF(ISNUMBER(INDEX($G$9:$G$2008,$W30)),INDEX($G$9:$G$2008,$W30),VALUE(SUBSTITUTE(INDEX($G$9:$G$2008,$W30),",",""))),"")) | AF30: =IF($W30="","",IFERROR(IF(ISNUMBER(INDEX($H$9:$H$2008,$W30)),INDEX($H$9:$H$2008,$W30),VALUE(SUBSTITUTE(INDEX($H$9:$H$2008,$W30),",",""))),"")) | AG30: =IF($W30="","",IFERROR(IF(ISNUMBER(INDEX($I$9:$I$2008,$W30)),INDEX($I$9:$I$2008,$W30),VALUE(SUBSTITUTE(INDEX($I$9:$I$2008,$W30),",",""))),"")) | AH30: =IF($W30="","",IFERROR(IF(ISNUMBER(INDEX($J$9:$J$2008,$W30)),INDEX($J$9:$J$2008,$W30),VALUE(SUBSTITUTE(INDEX($J$9:$J$2008,$W30),",",""))),"")) | AI30: =IF($W30="","",IFERROR(IF(ISNUMBER(INDEX($K$9:$K$2008,$W30)),INDEX($K$9:$K$2008,$W30),VALUE(SUBSTITUTE(INDEX($K$9:$K$2008,$W30),",",""))),"")) | AJ30: =IF($W30="","",IFERROR(IF(ISNUMBER(INDEX($L$9:$L$2008,$W30)),INDEX($L$9:$L$2008,$W30),VALUE(SUBSTITUTE(INDEX($L$9:$L$2008,$W30),",",""))),"")) | AK30: =IF($W30="","",IFERROR(IF(ISNUMBER(INDEX($M$9:$M$2008,$W30)),INDEX($M$9:$M$2008,$W30),VALUE(SUBSTITUTE(INDEX($M$9:$M$2008,$W30),",",""))),"")) | AL30: =IF($W30="","",IFERROR(IF(ISNUMBER(INDEX($P$9:$P$2008,$W30)),INDEX($P$9:$P$2008,$W30),VALUE(SUBSTITUTE(INDEX($P$9:$P$2008,$W30),"%",""))/100),""))
S31: =IF(AND(ISTEXT($A31),ISNUMBER(SEARCH(" - ",$A31)),ISERROR(SEARCH("Folio",$A31)),$D31=""),TRIM($A31),$S30) | T31: =IF(AND(ISNUMBER(SEARCH("Folio",$A31)),$D31<>""),1,"") | U31: =IF($T31=1,COUNTIF($T$9:$T31,1),"") | V31: =IF(AND(ISTEXT($A31),LEFT($A32,3)="Pan"),1,"") | W31: =IFERROR(MATCH(23,$U$9:$U$2008,0),"") | X31: =IF($W31="","",IF($R$5<>"",$R$5,$R$6)) | Y31: =IF($W31="","",INDEX($S$9:$S$2008,$W31)) | Z31: =IF($W31="","",IFERROR(TRIM(LEFT(SUBSTITUTE(INDEX($A$9:$A$2008,$W31),CHAR(10)," "),SEARCH("Folio",SUBSTITUTE(INDEX($A$9:$A$2008,$W31),CHAR(10)," "))-1)),TRIM(SUBSTITUTE(INDEX($A$9:$A$2008,$W31),CHAR(10)," ")))) | AA31: =IF($W31="","",IFERROR(TRIM(SUBSTITUTE(MID(SUBSTITUTE(INDEX($A$9:$A$2008,$W31),CHAR(10)," "),SEARCH("Folio",SUBSTITUTE(INDEX($A$9:$A$2008,$W31),CHAR(10)," "))+5,200),":","")),"")) | AB31: =IF($W31="","",IF(ISNUMBER(INDEX($D$9:$D$2008,$W31)),INDEX($D$9:$D$2008,$W31),IFERROR(DATE(2000+VALUE(RIGHT(INDEX($D$9:$D$2008,$W31),2)),VALUE(MID(INDEX($D$9:$D$2008,$W31),4,2)),VALUE(LEFT(INDEX($D$9:$D$2008,$W31),2))),""))) | AC31: =IF($W31="","",IFERROR(IF(ISNUMBER(INDEX($E$9:$E$2008,$W31)),INDEX($E$9:$E$2008,$W31),VALUE(SUBSTITUTE(INDEX($E$9:$E$2008,$W31),",",""))),"")) | AD31: =IF($W31="","",IFERROR(IF(ISNUMBER(INDEX($F$9:$F$2008,$W31)),INDEX($F$9:$F$2008,$W31),VALUE(SUBSTITUTE(INDEX($F$9:$F$2008,$W31),",",""))),"")) | AE31: =IF($W31="","",IFERROR(IF(ISNUMBER(INDEX($G$9:$G$2008,$W31)),INDEX($G$9:$G$2008,$W31),VALUE(SUBSTITUTE(INDEX($G$9:$G$2008,$W31),",",""))),"")) | AF31: =IF($W31="","",IFERROR(IF(ISNUMBER(INDEX($H$9:$H$2008,$W31)),INDEX($H$9:$H$2008,$W31),VALUE(SUBSTITUTE(INDEX($H$9:$H$2008,$W31),",",""))),"")) | AG31: =IF($W31="","",IFERROR(IF(ISNUMBER(INDEX($I$9:$I$2008,$W31)),INDEX($I$9:$I$2008,$W31),VALUE(SUBSTITUTE(INDEX($I$9:$I$2008,$W31),",",""))),"")) | AH31: =IF($W31="","",IFERROR(IF(ISNUMBER(INDEX($J$9:$J$2008,$W31)),INDEX($J$9:$J$2008,$W31),VALUE(SUBSTITUTE(INDEX($J$9:$J$2008,$W31),",",""))),"")) | AI31: =IF($W31="","",IFERROR(IF(ISNUMBER(INDEX($K$9:$K$2008,$W31)),INDEX($K$9:$K$2008,$W31),VALUE(SUBSTITUTE(INDEX($K$9:$K$2008,$W31),",",""))),"")) | AJ31: =IF($W31="","",IFERROR(IF(ISNUMBER(INDEX($L$9:$L$2008,$W31)),INDEX($L$9:$L$2008,$W31),VALUE(SUBSTITUTE(INDEX($L$9:$L$2008,$W31),",",""))),"")) | AK31: =IF($W31="","",IFERROR(IF(ISNUMBER(INDEX($M$9:$M$2008,$W31)),INDEX($M$9:$M$2008,$W31),VALUE(SUBSTITUTE(INDEX($M$9:$M$2008,$W31),",",""))),"")) | AL31: =IF($W31="","",IFERROR(IF(ISNUMBER(INDEX($P$9:$P$2008,$W31)),INDEX($P$9:$P$2008,$W31),VALUE(SUBSTITUTE(INDEX($P$9:$P$2008,$W31),"%",""))/100),""))
S32: =IF(AND(ISTEXT($A32),ISNUMBER(SEARCH(" - ",$A32)),ISERROR(SEARCH("Folio",$A32)),$D32=""),TRIM($A32),$S31) | T32: =IF(AND(ISNUMBER(SEARCH("Folio",$A32)),$D32<>""),1,"") | U32: =IF($T32=1,COUNTIF($T$9:$T32,1),"") | V32: =IF(AND(ISTEXT($A32),LEFT($A33,3)="Pan"),1,"") | W32: =IFERROR(MATCH(24,$U$9:$U$2008,0),"") | X32: =IF($W32="","",IF($R$5<>"",$R$5,$R$6)) | Y32: =IF($W32="","",INDEX($S$9:$S$2008,$W32)) | Z32: =IF($W32="","",IFERROR(TRIM(LEFT(SUBSTITUTE(INDEX($A$9:$A$2008,$W32),CHAR(10)," "),SEARCH("Folio",SUBSTITUTE(INDEX($A$9:$A$2008,$W32),CHAR(10)," "))-1)),TRIM(SUBSTITUTE(INDEX($A$9:$A$2008,$W32),CHAR(10)," ")))) | AA32: =IF($W32="","",IFERROR(TRIM(SUBSTITUTE(MID(SUBSTITUTE(INDEX($A$9:$A$2008,$W32),CHAR(10)," "),SEARCH("Folio",SUBSTITUTE(INDEX($A$9:$A$2008,$W32),CHAR(10)," "))+5,200),":","")),"")) | AB32: =IF($W32="","",IF(ISNUMBER(INDEX($D$9:$D$2008,$W32)),INDEX($D$9:$D$2008,$W32),IFERROR(DATE(2000+VALUE(RIGHT(INDEX($D$9:$D$2008,$W32),2)),VALUE(MID(INDEX($D$9:$D$2008,$W32),4,2)),VALUE(LEFT(INDEX($D$9:$D$2008,$W32),2))),""))) | AC32: =IF($W32="","",IFERROR(IF(ISNUMBER(INDEX($E$9:$E$2008,$W32)),INDEX($E$9:$E$2008,$W32),VALUE(SUBSTITUTE(INDEX($E$9:$E$2008,$W32),",",""))),"")) | AD32: =IF($W32="","",IFERROR(IF(ISNUMBER(INDEX($F$9:$F$2008,$W32)),INDEX($F$9:$F$2008,$W32),VALUE(SUBSTITUTE(INDEX($F$9:$F$2008,$W32),",",""))),"")) | AE32: =IF($W32="","",IFERROR(IF(ISNUMBER(INDEX($G$9:$G$2008,$W32)),INDEX($G$9:$G$2008,$W32),VALUE(SUBSTITUTE(INDEX($G$9:$G$2008,$W32),",",""))),"")) | AF32: =IF($W32="","",IFERROR(IF(ISNUMBER(INDEX($H$9:$H$2008,$W32)),INDEX($H$9:$H$2008,$W32),VALUE(SUBSTITUTE(INDEX($H$9:$H$2008,$W32),",",""))),"")) | AG32: =IF($W32="","",IFERROR(IF(ISNUMBER(INDEX($I$9:$I$2008,$W32)),INDEX($I$9:$I$2008,$W32),VALUE(SUBSTITUTE(INDEX($I$9:$I$2008,$W32),",",""))),"")) | AH32: =IF($W32="","",IFERROR(IF(ISNUMBER(INDEX($J$9:$J$2008,$W32)),INDEX($J$9:$J$2008,$W32),VALUE(SUBSTITUTE(INDEX($J$9:$J$2008,$W32),",",""))),"")) | AI32: =IF($W32="","",IFERROR(IF(ISNUMBER(INDEX($K$9:$K$2008,$W32)),INDEX($K$9:$K$2008,$W32),VALUE(SUBSTITUTE(INDEX($K$9:$K$2008,$W32),",",""))),"")) | AJ32: =IF($W32="","",IFERROR(IF(ISNUMBER(INDEX($L$9:$L$2008,$W32)),INDEX($L$9:$L$2008,$W32),VALUE(SUBSTITUTE(INDEX($L$9:$L$2008,$W32),",",""))),"")) | AK32: =IF($W32="","",IFERROR(IF(ISNUMBER(INDEX($M$9:$M$2008,$W32)),INDEX($M$9:$M$2008,$W32),VALUE(SUBSTITUTE(INDEX($M$9:$M$2008,$W32),",",""))),"")) | AL32: =IF($W32="","",IFERROR(IF(ISNUMBER(INDEX($P$9:$P$2008,$W32)),INDEX($P$9:$P$2008,$W32),VALUE(SUBSTITUTE(INDEX($P$9:$P$2008,$W32),"%",""))/100),""))
S33: =IF(AND(ISTEXT($A33),ISNUMBER(SEARCH(" - ",$A33)),ISERROR(SEARCH("Folio",$A33)),$D33=""),TRIM($A33),$S32) | T33: =IF(AND(ISNUMBER(SEARCH("Folio",$A33)),$D33<>""),1,"") | U33: =IF($T33=1,COUNTIF($T$9:$T33,1),"") | V33: =IF(AND(ISTEXT($A33),LEFT($A34,3)="Pan"),1,"") | W33: =IFERROR(MATCH(25,$U$9:$U$2008,0),"") | X33: =IF($W33="","",IF($R$5<>"",$R$5,$R$6)) | Y33: =IF($W33="","",INDEX($S$9:$S$2008,$W33)) | Z33: =IF($W33="","",IFERROR(TRIM(LEFT(SUBSTITUTE(INDEX($A$9:$A$2008,$W33),CHAR(10)," "),SEARCH("Folio",SUBSTITUTE(INDEX($A$9:$A$2008,$W33),CHAR(10)," "))-1)),TRIM(SUBSTITUTE(INDEX($A$9:$A$2008,$W33),CHAR(10)," ")))) | AA33: =IF($W33="","",IFERROR(TRIM(SUBSTITUTE(MID(SUBSTITUTE(INDEX($A$9:$A$2008,$W33),CHAR(10)," "),SEARCH("Folio",SUBSTITUTE(INDEX($A$9:$A$2008,$W33),CHAR(10)," "))+5,200),":","")),"")) | AB33: =IF($W33="","",IF(ISNUMBER(INDEX($D$9:$D$2008,$W33)),INDEX($D$9:$D$2008,$W33),IFERROR(DATE(2000+VALUE(RIGHT(INDEX($D$9:$D$2008,$W33),2)),VALUE(MID(INDEX($D$9:$D$2008,$W33),4,2)),VALUE(LEFT(INDEX($D$9:$D$2008,$W33),2))),""))) | AC33: =IF($W33="","",IFERROR(IF(ISNUMBER(INDEX($E$9:$E$2008,$W33)),INDEX($E$9:$E$2008,$W33),VALUE(SUBSTITUTE(INDEX($E$9:$E$2008,$W33),",",""))),"")) | AD33: =IF($W33="","",IFERROR(IF(ISNUMBER(INDEX($F$9:$F$2008,$W33)),INDEX($F$9:$F$2008,$W33),VALUE(SUBSTITUTE(INDEX($F$9:$F$2008,$W33),",",""))),"")) | AE33: =IF($W33="","",IFERROR(IF(ISNUMBER(INDEX($G$9:$G$2008,$W33)),INDEX($G$9:$G$2008,$W33),VALUE(SUBSTITUTE(INDEX($G$9:$G$2008,$W33),",",""))),"")) | AF33: =IF($W33="","",IFERROR(IF(ISNUMBER(INDEX($H$9:$H$2008,$W33)),INDEX($H$9:$H$2008,$W33),VALUE(SUBSTITUTE(INDEX($H$9:$H$2008,$W33),",",""))),"")) | AG33: =IF($W33="","",IFERROR(IF(ISNUMBER(INDEX($I$9:$I$2008,$W33)),INDEX($I$9:$I$2008,$W33),VALUE(SUBSTITUTE(INDEX($I$9:$I$2008,$W33),",",""))),"")) | AH33: =IF($W33="","",IFERROR(IF(ISNUMBER(INDEX($J$9:$J$2008,$W33)),INDEX($J$9:$J$2008,$W33),VALUE(SUBSTITUTE(INDEX($J$9:$J$2008,$W33),",",""))),"")) | AI33: =IF($W33="","",IFERROR(IF(ISNUMBER(INDEX($K$9:$K$2008,$W33)),INDEX($K$9:$K$2008,$W33),VALUE(SUBSTITUTE(INDEX($K$9:$K$2008,$W33),",",""))),"")) | AJ33: =IF($W33="","",IFERROR(IF(ISNUMBER(INDEX($L$9:$L$2008,$W33)),INDEX($L$9:$L$2008,$W33),VALUE(SUBSTITUTE(INDEX($L$9:$L$2008,$W33),",",""))),"")) | AK33: =IF($W33="","",IFERROR(IF(ISNUMBER(INDEX($M$9:$M$2008,$W33)),INDEX($M$9:$M$2008,$W33),VALUE(SUBSTITUTE(INDEX($M$9:$M$2008,$W33),",",""))),"")) | AL33: =IF($W33="","",IFERROR(IF(ISNUMBER(INDEX($P$9:$P$2008,$W33)),INDEX($P$9:$P$2008,$W33),VALUE(SUBSTITUTE(INDEX($P$9:$P$2008,$W33),"%",""))/100),""))
S34: =IF(AND(ISTEXT($A34),ISNUMBER(SEARCH(" - ",$A34)),ISERROR(SEARCH("Folio",$A34)),$D34=""),TRIM($A34),$S33) | T34: =IF(AND(ISNUMBER(SEARCH("Folio",$A34)),$D34<>""),1,"") | U34: =IF($T34=1,COUNTIF($T$9:$T34,1),"") | V34: =IF(AND(ISTEXT($A34),LEFT($A35,3)="Pan"),1,"") | W34: =IFERROR(MATCH(26,$U$9:$U$2008,0),"") | X34: =IF($W34="","",IF($R$5<>"",$R$5,$R$6)) | Y34: =IF($W34="","",INDEX($S$9:$S$2008,$W34)) | Z34: =IF($W34="","",IFERROR(TRIM(LEFT(SUBSTITUTE(INDEX($A$9:$A$2008,$W34),CHAR(10)," "),SEARCH("Folio",SUBSTITUTE(INDEX($A$9:$A$2008,$W34),CHAR(10)," "))-1)),TRIM(SUBSTITUTE(INDEX($A$9:$A$2008,$W34),CHAR(10)," ")))) | AA34: =IF($W34="","",IFERROR(TRIM(SUBSTITUTE(MID(SUBSTITUTE(INDEX($A$9:$A$2008,$W34),CHAR(10)," "),SEARCH("Folio",SUBSTITUTE(INDEX($A$9:$A$2008,$W34),CHAR(10)," "))+5,200),":","")),"")) | AB34: =IF($W34="","",IF(ISNUMBER(INDEX($D$9:$D$2008,$W34)),INDEX($D$9:$D$2008,$W34),IFERROR(DATE(2000+VALUE(RIGHT(INDEX($D$9:$D$2008,$W34),2)),VALUE(MID(INDEX($D$9:$D$2008,$W34),4,2)),VALUE(LEFT(INDEX($D$9:$D$2008,$W34),2))),""))) | AC34: =IF($W34="","",IFERROR(IF(ISNUMBER(INDEX($E$9:$E$2008,$W34)),INDEX($E$9:$E$2008,$W34),VALUE(SUBSTITUTE(INDEX($E$9:$E$2008,$W34),",",""))),"")) | AD34: =IF($W34="","",IFERROR(IF(ISNUMBER(INDEX($F$9:$F$2008,$W34)),INDEX($F$9:$F$2008,$W34),VALUE(SUBSTITUTE(INDEX($F$9:$F$2008,$W34),",",""))),"")) | AE34: =IF($W34="","",IFERROR(IF(ISNUMBER(INDEX($G$9:$G$2008,$W34)),INDEX($G$9:$G$2008,$W34),VALUE(SUBSTITUTE(INDEX($G$9:$G$2008,$W34),",",""))),"")) | AF34: =IF($W34="","",IFERROR(IF(ISNUMBER(INDEX($H$9:$H$2008,$W34)),INDEX($H$9:$H$2008,$W34),VALUE(SUBSTITUTE(INDEX($H$9:$H$2008,$W34),",",""))),"")) | AG34: =IF($W34="","",IFERROR(IF(ISNUMBER(INDEX($I$9:$I$2008,$W34)),INDEX($I$9:$I$2008,$W34),VALUE(SUBSTITUTE(INDEX($I$9:$I$2008,$W34),",",""))),"")) | AH34: =IF($W34="","",IFERROR(IF(ISNUMBER(INDEX($J$9:$J$2008,$W34)),INDEX($J$9:$J$2008,$W34),VALUE(SUBSTITUTE(INDEX($J$9:$J$2008,$W34),",",""))),"")) | AI34: =IF($W34="","",IFERROR(IF(ISNUMBER(INDEX($K$9:$K$2008,$W34)),INDEX($K$9:$K$2008,$W34),VALUE(SUBSTITUTE(INDEX($K$9:$K$2008,$W34),",",""))),"")) | AJ34: =IF($W34="","",IFERROR(IF(ISNUMBER(INDEX($L$9:$L$2008,$W34)),INDEX($L$9:$L$2008,$W34),VALUE(SUBSTITUTE(INDEX($L$9:$L$2008,$W34),",",""))),"")) | AK34: =IF($W34="","",IFERROR(IF(ISNUMBER(INDEX($M$9:$M$2008,$W34)),INDEX($M$9:$M$2008,$W34),VALUE(SUBSTITUTE(INDEX($M$9:$M$2008,$W34),",",""))),"")) | AL34: =IF($W34="","",IFERROR(IF(ISNUMBER(INDEX($P$9:$P$2008,$W34)),INDEX($P$9:$P$2008,$W34),VALUE(SUBSTITUTE(INDEX($P$9:$P$2008,$W34),"%",""))/100),""))
S35: =IF(AND(ISTEXT($A35),ISNUMBER(SEARCH(" - ",$A35)),ISERROR(SEARCH("Folio",$A35)),$D35=""),TRIM($A35),$S34) | T35: =IF(AND(ISNUMBER(SEARCH("Folio",$A35)),$D35<>""),1,"") | U35: =IF($T35=1,COUNTIF($T$9:$T35,1),"") | V35: =IF(AND(ISTEXT($A35),LEFT($A36,3)="Pan"),1,"") | W35: =IFERROR(MATCH(27,$U$9:$U$2008,0),"") | X35: =IF($W35="","",IF($R$5<>"",$R$5,$R$6)) | Y35: =IF($W35="","",INDEX($S$9:$S$2008,$W35)) | Z35: =IF($W35="","",IFERROR(TRIM(LEFT(SUBSTITUTE(INDEX($A$9:$A$2008,$W35),CHAR(10)," "),SEARCH("Folio",SUBSTITUTE(INDEX($A$9:$A$2008,$W35),CHAR(10)," "))-1)),TRIM(SUBSTITUTE(INDEX($A$9:$A$2008,$W35),CHAR(10)," ")))) | AA35: =IF($W35="","",IFERROR(TRIM(SUBSTITUTE(MID(SUBSTITUTE(INDEX($A$9:$A$2008,$W35),CHAR(10)," "),SEARCH("Folio",SUBSTITUTE(INDEX($A$9:$A$2008,$W35),CHAR(10)," "))+5,200),":","")),"")) | AB35: =IF($W35="","",IF(ISNUMBER(INDEX($D$9:$D$2008,$W35)),INDEX($D$9:$D$2008,$W35),IFERROR(DATE(2000+VALUE(RIGHT(INDEX($D$9:$D$2008,$W35),2)),VALUE(MID(INDEX($D$9:$D$2008,$W35),4,2)),VALUE(LEFT(INDEX($D$9:$D$2008,$W35),2))),""))) | AC35: =IF($W35="","",IFERROR(IF(ISNUMBER(INDEX($E$9:$E$2008,$W35)),INDEX($E$9:$E$2008,$W35),VALUE(SUBSTITUTE(INDEX($E$9:$E$2008,$W35),",",""))),"")) | AD35: =IF($W35="","",IFERROR(IF(ISNUMBER(INDEX($F$9:$F$2008,$W35)),INDEX($F$9:$F$2008,$W35),VALUE(SUBSTITUTE(INDEX($F$9:$F$2008,$W35),",",""))),"")) | AE35: =IF($W35="","",IFERROR(IF(ISNUMBER(INDEX($G$9:$G$2008,$W35)),INDEX($G$9:$G$2008,$W35),VALUE(SUBSTITUTE(INDEX($G$9:$G$2008,$W35),",",""))),"")) | AF35: =IF($W35="","",IFERROR(IF(ISNUMBER(INDEX($H$9:$H$2008,$W35)),INDEX($H$9:$H$2008,$W35),VALUE(SUBSTITUTE(INDEX($H$9:$H$2008,$W35),",",""))),"")) | AG35: =IF($W35="","",IFERROR(IF(ISNUMBER(INDEX($I$9:$I$2008,$W35)),INDEX($I$9:$I$2008,$W35),VALUE(SUBSTITUTE(INDEX($I$9:$I$2008,$W35),",",""))),"")) | AH35: =IF($W35="","",IFERROR(IF(ISNUMBER(INDEX($J$9:$J$2008,$W35)),INDEX($J$9:$J$2008,$W35),VALUE(SUBSTITUTE(INDEX($J$9:$J$2008,$W35),",",""))),"")) | AI35: =IF($W35="","",IFERROR(IF(ISNUMBER(INDEX($K$9:$K$2008,$W35)),INDEX($K$9:$K$2008,$W35),VALUE(SUBSTITUTE(INDEX($K$9:$K$2008,$W35),",",""))),"")) | AJ35: =IF($W35="","",IFERROR(IF(ISNUMBER(INDEX($L$9:$L$2008,$W35)),INDEX($L$9:$L$2008,$W35),VALUE(SUBSTITUTE(INDEX($L$9:$L$2008,$W35),",",""))),"")) | AK35: =IF($W35="","",IFERROR(IF(ISNUMBER(INDEX($M$9:$M$2008,$W35)),INDEX($M$9:$M$2008,$W35),VALUE(SUBSTITUTE(INDEX($M$9:$M$2008,$W35),",",""))),"")) | AL35: =IF($W35="","",IFERROR(IF(ISNUMBER(INDEX($P$9:$P$2008,$W35)),INDEX($P$9:$P$2008,$W35),VALUE(SUBSTITUTE(INDEX($P$9:$P$2008,$W35),"%",""))/100),""))
S36: =IF(AND(ISTEXT($A36),ISNUMBER(SEARCH(" - ",$A36)),ISERROR(SEARCH("Folio",$A36)),$D36=""),TRIM($A36),$S35) | T36: =IF(AND(ISNUMBER(SEARCH("Folio",$A36)),$D36<>""),1,"") | U36: =IF($T36=1,COUNTIF($T$9:$T36,1),"") | V36: =IF(AND(ISTEXT($A36),LEFT($A37,3)="Pan"),1,"") | W36: =IFERROR(MATCH(28,$U$9:$U$2008,0),"") | X36: =IF($W36="","",IF($R$5<>"",$R$5,$R$6)) | Y36: =IF($W36="","",INDEX($S$9:$S$2008,$W36)) | Z36: =IF($W36="","",IFERROR(TRIM(LEFT(SUBSTITUTE(INDEX($A$9:$A$2008,$W36),CHAR(10)," "),SEARCH("Folio",SUBSTITUTE(INDEX($A$9:$A$2008,$W36),CHAR(10)," "))-1)),TRIM(SUBSTITUTE(INDEX($A$9:$A$2008,$W36),CHAR(10)," ")))) | AA36: =IF($W36="","",IFERROR(TRIM(SUBSTITUTE(MID(SUBSTITUTE(INDEX($A$9:$A$2008,$W36),CHAR(10)," "),SEARCH("Folio",SUBSTITUTE(INDEX($A$9:$A$2008,$W36),CHAR(10)," "))+5,200),":","")),"")) | AB36: =IF($W36="","",IF(ISNUMBER(INDEX($D$9:$D$2008,$W36)),INDEX($D$9:$D$2008,$W36),IFERROR(DATE(2000+VALUE(RIGHT(INDEX($D$9:$D$2008,$W36),2)),VALUE(MID(INDEX($D$9:$D$2008,$W36),4,2)),VALUE(LEFT(INDEX($D$9:$D$2008,$W36),2))),""))) | AC36: =IF($W36="","",IFERROR(IF(ISNUMBER(INDEX($E$9:$E$2008,$W36)),INDEX($E$9:$E$2008,$W36),VALUE(SUBSTITUTE(INDEX($E$9:$E$2008,$W36),",",""))),"")) | AD36: =IF($W36="","",IFERROR(IF(ISNUMBER(INDEX($F$9:$F$2008,$W36)),INDEX($F$9:$F$2008,$W36),VALUE(SUBSTITUTE(INDEX($F$9:$F$2008,$W36),",",""))),"")) | AE36: =IF($W36="","",IFERROR(IF(ISNUMBER(INDEX($G$9:$G$2008,$W36)),INDEX($G$9:$G$2008,$W36),VALUE(SUBSTITUTE(INDEX($G$9:$G$2008,$W36),",",""))),"")) | AF36: =IF($W36="","",IFERROR(IF(ISNUMBER(INDEX($H$9:$H$2008,$W36)),INDEX($H$9:$H$2008,$W36),VALUE(SUBSTITUTE(INDEX($H$9:$H$2008,$W36),",",""))),"")) | AG36: =IF($W36="","",IFERROR(IF(ISNUMBER(INDEX($I$9:$I$2008,$W36)),INDEX($I$9:$I$2008,$W36),VALUE(SUBSTITUTE(INDEX($I$9:$I$2008,$W36),",",""))),"")) | AH36: =IF($W36="","",IFERROR(IF(ISNUMBER(INDEX($J$9:$J$2008,$W36)),INDEX($J$9:$J$2008,$W36),VALUE(SUBSTITUTE(INDEX($J$9:$J$2008,$W36),",",""))),"")) | AI36: =IF($W36="","",IFERROR(IF(ISNUMBER(INDEX($K$9:$K$2008,$W36)),INDEX($K$9:$K$2008,$W36),VALUE(SUBSTITUTE(INDEX($K$9:$K$2008,$W36),",",""))),"")) | AJ36: =IF($W36="","",IFERROR(IF(ISNUMBER(INDEX($L$9:$L$2008,$W36)),INDEX($L$9:$L$2008,$W36),VALUE(SUBSTITUTE(INDEX($L$9:$L$2008,$W36),",",""))),"")) | AK36: =IF($W36="","",IFERROR(IF(ISNUMBER(INDEX($M$9:$M$2008,$W36)),INDEX($M$9:$M$2008,$W36),VALUE(SUBSTITUTE(INDEX($M$9:$M$2008,$W36),",",""))),"")) | AL36: =IF($W36="","",IFERROR(IF(ISNUMBER(INDEX($P$9:$P$2008,$W36)),INDEX($P$9:$P$2008,$W36),VALUE(SUBSTITUTE(INDEX($P$9:$P$2008,$W36),"%",""))/100),""))
S37: =IF(AND(ISTEXT($A37),ISNUMBER(SEARCH(" - ",$A37)),ISERROR(SEARCH("Folio",$A37)),$D37=""),TRIM($A37),$S36) | T37: =IF(AND(ISNUMBER(SEARCH("Folio",$A37)),$D37<>""),1,"") | U37: =IF($T37=1,COUNTIF($T$9:$T37,1),"") | V37: =IF(AND(ISTEXT($A37),LEFT($A38,3)="Pan"),1,"") | W37: =IFERROR(MATCH(29,$U$9:$U$2008,0),"") | X37: =IF($W37="","",IF($R$5<>"",$R$5,$R$6)) | Y37: =IF($W37="","",INDEX($S$9:$S$2008,$W37)) | Z37: =IF($W37="","",IFERROR(TRIM(LEFT(SUBSTITUTE(INDEX($A$9:$A$2008,$W37),CHAR(10)," "),SEARCH("Folio",SUBSTITUTE(INDEX($A$9:$A$2008,$W37),CHAR(10)," "))-1)),TRIM(SUBSTITUTE(INDEX($A$9:$A$2008,$W37),CHAR(10)," ")))) | AA37: =IF($W37="","",IFERROR(TRIM(SUBSTITUTE(MID(SUBSTITUTE(INDEX($A$9:$A$2008,$W37),CHAR(10)," "),SEARCH("Folio",SUBSTITUTE(INDEX($A$9:$A$2008,$W37),CHAR(10)," "))+5,200),":","")),"")) | AB37: =IF($W37="","",IF(ISNUMBER(INDEX($D$9:$D$2008,$W37)),INDEX($D$9:$D$2008,$W37),IFERROR(DATE(2000+VALUE(RIGHT(INDEX($D$9:$D$2008,$W37),2)),VALUE(MID(INDEX($D$9:$D$2008,$W37),4,2)),VALUE(LEFT(INDEX($D$9:$D$2008,$W37),2))),""))) | AC37: =IF($W37="","",IFERROR(IF(ISNUMBER(INDEX($E$9:$E$2008,$W37)),INDEX($E$9:$E$2008,$W37),VALUE(SUBSTITUTE(INDEX($E$9:$E$2008,$W37),",",""))),"")) | AD37: =IF($W37="","",IFERROR(IF(ISNUMBER(INDEX($F$9:$F$2008,$W37)),INDEX($F$9:$F$2008,$W37),VALUE(SUBSTITUTE(INDEX($F$9:$F$2008,$W37),",",""))),"")) | AE37: =IF($W37="","",IFERROR(IF(ISNUMBER(INDEX($G$9:$G$2008,$W37)),INDEX($G$9:$G$2008,$W37),VALUE(SUBSTITUTE(INDEX($G$9:$G$2008,$W37),",",""))),"")) | AF37: =IF($W37="","",IFERROR(IF(ISNUMBER(INDEX($H$9:$H$2008,$W37)),INDEX($H$9:$H$2008,$W37),VALUE(SUBSTITUTE(INDEX($H$9:$H$2008,$W37),",",""))),"")) | AG37: =IF($W37="","",IFERROR(IF(ISNUMBER(INDEX($I$9:$I$2008,$W37)),INDEX($I$9:$I$2008,$W37),VALUE(SUBSTITUTE(INDEX($I$9:$I$2008,$W37),",",""))),"")) | AH37: =IF($W37="","",IFERROR(IF(ISNUMBER(INDEX($J$9:$J$2008,$W37)),INDEX($J$9:$J$2008,$W37),VALUE(SUBSTITUTE(INDEX($J$9:$J$2008,$W37),",",""))),"")) | AI37: =IF($W37="","",IFERROR(IF(ISNUMBER(INDEX($K$9:$K$2008,$W37)),INDEX($K$9:$K$2008,$W37),VALUE(SUBSTITUTE(INDEX($K$9:$K$2008,$W37),",",""))),"")) | AJ37: =IF($W37="","",IFERROR(IF(ISNUMBER(INDEX($L$9:$L$2008,$W37)),INDEX($L$9:$L$2008,$W37),VALUE(SUBSTITUTE(INDEX($L$9:$L$2008,$W37),",",""))),"")) | AK37: =IF($W37="","",IFERROR(IF(ISNUMBER(INDEX($M$9:$M$2008,$W37)),INDEX($M$9:$M$2008,$W37),VALUE(SUBSTITUTE(INDEX($M$9:$M$2008,$W37),",",""))),"")) | AL37: =IF($W37="","",IFERROR(IF(ISNUMBER(INDEX($P$9:$P$2008,$W37)),INDEX($P$9:$P$2008,$W37),VALUE(SUBSTITUTE(INDEX($P$9:$P$2008,$W37),"%",""))/100),""))
S38: =IF(AND(ISTEXT($A38),ISNUMBER(SEARCH(" - ",$A38)),ISERROR(SEARCH("Folio",$A38)),$D38=""),TRIM($A38),$S37) | T38: =IF(AND(ISNUMBER(SEARCH("Folio",$A38)),$D38<>""),1,"") | U38: =IF($T38=1,COUNTIF($T$9:$T38,1),"") | V38: =IF(AND(ISTEXT($A38),LEFT($A39,3)="Pan"),1,"") | W38: =IFERROR(MATCH(30,$U$9:$U$2008,0),"") | X38: =IF($W38="","",IF($R$5<>"",$R$5,$R$6)) | Y38: =IF($W38="","",INDEX($S$9:$S$2008,$W38)) | Z38: =IF($W38="","",IFERROR(TRIM(LEFT(SUBSTITUTE(INDEX($A$9:$A$2008,$W38),CHAR(10)," "),SEARCH("Folio",SUBSTITUTE(INDEX($A$9:$A$2008,$W38),CHAR(10)," "))-1)),TRIM(SUBSTITUTE(INDEX($A$9:$A$2008,$W38),CHAR(10)," ")))) | AA38: =IF($W38="","",IFERROR(TRIM(SUBSTITUTE(MID(SUBSTITUTE(INDEX($A$9:$A$2008,$W38),CHAR(10)," "),SEARCH("Folio",SUBSTITUTE(INDEX($A$9:$A$2008,$W38),CHAR(10)," "))+5,200),":","")),"")) | AB38: =IF($W38="","",IF(ISNUMBER(INDEX($D$9:$D$2008,$W38)),INDEX($D$9:$D$2008,$W38),IFERROR(DATE(2000+VALUE(RIGHT(INDEX($D$9:$D$2008,$W38),2)),VALUE(MID(INDEX($D$9:$D$2008,$W38),4,2)),VALUE(LEFT(INDEX($D$9:$D$2008,$W38),2))),""))) | AC38: =IF($W38="","",IFERROR(IF(ISNUMBER(INDEX($E$9:$E$2008,$W38)),INDEX($E$9:$E$2008,$W38),VALUE(SUBSTITUTE(INDEX($E$9:$E$2008,$W38),",",""))),"")) | AD38: =IF($W38="","",IFERROR(IF(ISNUMBER(INDEX($F$9:$F$2008,$W38)),INDEX($F$9:$F$2008,$W38),VALUE(SUBSTITUTE(INDEX($F$9:$F$2008,$W38),",",""))),"")) | AE38: =IF($W38="","",IFERROR(IF(ISNUMBER(INDEX($G$9:$G$2008,$W38)),INDEX($G$9:$G$2008,$W38),VALUE(SUBSTITUTE(INDEX($G$9:$G$2008,$W38),",",""))),"")) | AF38: =IF($W38="","",IFERROR(IF(ISNUMBER(INDEX($H$9:$H$2008,$W38)),INDEX($H$9:$H$2008,$W38),VALUE(SUBSTITUTE(INDEX($H$9:$H$2008,$W38),",",""))),"")) | AG38: =IF($W38="","",IFERROR(IF(ISNUMBER(INDEX($I$9:$I$2008,$W38)),INDEX($I$9:$I$2008,$W38),VALUE(SUBSTITUTE(INDEX($I$9:$I$2008,$W38),",",""))),"")) | AH38: =IF($W38="","",IFERROR(IF(ISNUMBER(INDEX($J$9:$J$2008,$W38)),INDEX($J$9:$J$2008,$W38),VALUE(SUBSTITUTE(INDEX($J$9:$J$2008,$W38),",",""))),"")) | AI38: =IF($W38="","",IFERROR(IF(ISNUMBER(INDEX($K$9:$K$2008,$W38)),INDEX($K$9:$K$2008,$W38),VALUE(SUBSTITUTE(INDEX($K$9:$K$2008,$W38),",",""))),"")) | AJ38: =IF($W38="","",IFERROR(IF(ISNUMBER(INDEX($L$9:$L$2008,$W38)),INDEX($L$9:$L$2008,$W38),VALUE(SUBSTITUTE(INDEX($L$9:$L$2008,$W38),",",""))),"")) | AK38: =IF($W38="","",IFERROR(IF(ISNUMBER(INDEX($M$9:$M$2008,$W38)),INDEX($M$9:$M$2008,$W38),VALUE(SUBSTITUTE(INDEX($M$9:$M$2008,$W38),",",""))),"")) | AL38: =IF($W38="","",IFERROR(IF(ISNUMBER(INDEX($P$9:$P$2008,$W38)),INDEX($P$9:$P$2008,$W38),VALUE(SUBSTITUTE(INDEX($P$9:$P$2008,$W38),"%",""))/100),""))
S39: =IF(AND(ISTEXT($A39),ISNUMBER(SEARCH(" - ",$A39)),ISERROR(SEARCH("Folio",$A39)),$D39=""),TRIM($A39),$S38) | T39: =IF(AND(ISNUMBER(SEARCH("Folio",$A39)),$D39<>""),1,"") | U39: =IF($T39=1,COUNTIF($T$9:$T39,1),"") | V39: =IF(AND(ISTEXT($A39),LEFT($A40,3)="Pan"),1,"") | W39: =IFERROR(MATCH(31,$U$9:$U$2008,0),"") | X39: =IF($W39="","",IF($R$5<>"",$R$5,$R$6)) | Y39: =IF($W39="","",INDEX($S$9:$S$2008,$W39)) | Z39: =IF($W39="","",IFERROR(TRIM(LEFT(SUBSTITUTE(INDEX($A$9:$A$2008,$W39),CHAR(10)," "),SEARCH("Folio",SUBSTITUTE(INDEX($A$9:$A$2008,$W39),CHAR(10)," "))-1)),TRIM(SUBSTITUTE(INDEX($A$9:$A$2008,$W39),CHAR(10)," ")))) | AA39: =IF($W39="","",IFERROR(TRIM(SUBSTITUTE(MID(SUBSTITUTE(INDEX($A$9:$A$2008,$W39),CHAR(10)," "),SEARCH("Folio",SUBSTITUTE(INDEX($A$9:$A$2008,$W39),CHAR(10)," "))+5,200),":","")),"")) | AB39: =IF($W39="","",IF(ISNUMBER(INDEX($D$9:$D$2008,$W39)),INDEX($D$9:$D$2008,$W39),IFERROR(DATE(2000+VALUE(RIGHT(INDEX($D$9:$D$2008,$W39),2)),VALUE(MID(INDEX($D$9:$D$2008,$W39),4,2)),VALUE(LEFT(INDEX($D$9:$D$2008,$W39),2))),""))) | AC39: =IF($W39="","",IFERROR(IF(ISNUMBER(INDEX($E$9:$E$2008,$W39)),INDEX($E$9:$E$2008,$W39),VALUE(SUBSTITUTE(INDEX($E$9:$E$2008,$W39),",",""))),"")) | AD39: =IF($W39="","",IFERROR(IF(ISNUMBER(INDEX($F$9:$F$2008,$W39)),INDEX($F$9:$F$2008,$W39),VALUE(SUBSTITUTE(INDEX($F$9:$F$2008,$W39),",",""))),"")) | AE39: =IF($W39="","",IFERROR(IF(ISNUMBER(INDEX($G$9:$G$2008,$W39)),INDEX($G$9:$G$2008,$W39),VALUE(SUBSTITUTE(INDEX($G$9:$G$2008,$W39),",",""))),"")) | AF39: =IF($W39="","",IFERROR(IF(ISNUMBER(INDEX($H$9:$H$2008,$W39)),INDEX($H$9:$H$2008,$W39),VALUE(SUBSTITUTE(INDEX($H$9:$H$2008,$W39),",",""))),"")) | AG39: =IF($W39="","",IFERROR(IF(ISNUMBER(INDEX($I$9:$I$2008,$W39)),INDEX($I$9:$I$2008,$W39),VALUE(SUBSTITUTE(INDEX($I$9:$I$2008,$W39),",",""))),"")) | AH39: =IF($W39="","",IFERROR(IF(ISNUMBER(INDEX($J$9:$J$2008,$W39)),INDEX($J$9:$J$2008,$W39),VALUE(SUBSTITUTE(INDEX($J$9:$J$2008,$W39),",",""))),"")) | AI39: =IF($W39="","",IFERROR(IF(ISNUMBER(INDEX($K$9:$K$2008,$W39)),INDEX($K$9:$K$2008,$W39),VALUE(SUBSTITUTE(INDEX($K$9:$K$2008,$W39),",",""))),"")) | AJ39: =IF($W39="","",IFERROR(IF(ISNUMBER(INDEX($L$9:$L$2008,$W39)),INDEX($L$9:$L$2008,$W39),VALUE(SUBSTITUTE(INDEX($L$9:$L$2008,$W39),",",""))),"")) | AK39: =IF($W39="","",IFERROR(IF(ISNUMBER(INDEX($M$9:$M$2008,$W39)),INDEX($M$9:$M$2008,$W39),VALUE(SUBSTITUTE(INDEX($M$9:$M$2008,$W39),",",""))),"")) | AL39: =IF($W39="","",IFERROR(IF(ISNUMBER(INDEX($P$9:$P$2008,$W39)),INDEX($P$9:$P$2008,$W39),VALUE(SUBSTITUTE(INDEX($P$9:$P$2008,$W39),"%",""))/100),""))
S40: =IF(AND(ISTEXT($A40),ISNUMBER(SEARCH(" - ",$A40)),ISERROR(SEARCH("Folio",$A40)),$D40=""),TRIM($A40),$S39) | T40: =IF(AND(ISNUMBER(SEARCH("Folio",$A40)),$D40<>""),1,"") | U40: =IF($T40=1,COUNTIF($T$9:$T40,1),"") | V40: =IF(AND(ISTEXT($A40),LEFT($A41,3)="Pan"),1,"") | W40: =IFERROR(MATCH(32,$U$9:$U$2008,0),"") | X40: =IF($W40="","",IF($R$5<>"",$R$5,$R$6)) | Y40: =IF($W40="","",INDEX($S$9:$S$2008,$W40)) | Z40: =IF($W40="","",IFERROR(TRIM(LEFT(SUBSTITUTE(INDEX($A$9:$A$2008,$W40),CHAR(10)," "),SEARCH("Folio",SUBSTITUTE(INDEX($A$9:$A$2008,$W40),CHAR(10)," "))-1)),TRIM(SUBSTITUTE(INDEX($A$9:$A$2008,$W40),CHAR(10)," ")))) | AA40: =IF($W40="","",IFERROR(TRIM(SUBSTITUTE(MID(SUBSTITUTE(INDEX($A$9:$A$2008,$W40),CHAR(10)," "),SEARCH("Folio",SUBSTITUTE(INDEX($A$9:$A$2008,$W40),CHAR(10)," "))+5,200),":","")),"")) | AB40: =IF($W40="","",IF(ISNUMBER(INDEX($D$9:$D$2008,$W40)),INDEX($D$9:$D$2008,$W40),IFERROR(DATE(2000+VALUE(RIGHT(INDEX($D$9:$D$2008,$W40),2)),VALUE(MID(INDEX($D$9:$D$2008,$W40),4,2)),VALUE(LEFT(INDEX($D$9:$D$2008,$W40),2))),""))) | AC40: =IF($W40="","",IFERROR(IF(ISNUMBER(INDEX($E$9:$E$2008,$W40)),INDEX($E$9:$E$2008,$W40),VALUE(SUBSTITUTE(INDEX($E$9:$E$2008,$W40),",",""))),"")) | AD40: =IF($W40="","",IFERROR(IF(ISNUMBER(INDEX($F$9:$F$2008,$W40)),INDEX($F$9:$F$2008,$W40),VALUE(SUBSTITUTE(INDEX($F$9:$F$2008,$W40),",",""))),"")) | AE40: =IF($W40="","",IFERROR(IF(ISNUMBER(INDEX($G$9:$G$2008,$W40)),INDEX($G$9:$G$2008,$W40),VALUE(SUBSTITUTE(INDEX($G$9:$G$2008,$W40),",",""))),"")) | AF40: =IF($W40="","",IFERROR(IF(ISNUMBER(INDEX($H$9:$H$2008,$W40)),INDEX($H$9:$H$2008,$W40),VALUE(SUBSTITUTE(INDEX($H$9:$H$2008,$W40),",",""))),"")) | AG40: =IF($W40="","",IFERROR(IF(ISNUMBER(INDEX($I$9:$I$2008,$W40)),INDEX($I$9:$I$2008,$W40),VALUE(SUBSTITUTE(INDEX($I$9:$I$2008,$W40),",",""))),"")) | AH40: =IF($W40="","",IFERROR(IF(ISNUMBER(INDEX($J$9:$J$2008,$W40)),INDEX($J$9:$J$2008,$W40),VALUE(SUBSTITUTE(INDEX($J$9:$J$2008,$W40),",",""))),"")) | AI40: =IF($W40="","",IFERROR(IF(ISNUMBER(INDEX($K$9:$K$2008,$W40)),INDEX($K$9:$K$2008,$W40),VALUE(SUBSTITUTE(INDEX($K$9:$K$2008,$W40),",",""))),"")) | AJ40: =IF($W40="","",IFERROR(IF(ISNUMBER(INDEX($L$9:$L$2008,$W40)),INDEX($L$9:$L$2008,$W40),VALUE(SUBSTITUTE(INDEX($L$9:$L$2008,$W40),",",""))),"")) | AK40: =IF($W40="","",IFERROR(IF(ISNUMBER(INDEX($M$9:$M$2008,$W40)),INDEX($M$9:$M$2008,$W40),VALUE(SUBSTITUTE(INDEX($M$9:$M$2008,$W40),",",""))),"")) | AL40: =IF($W40="","",IFERROR(IF(ISNUMBER(INDEX($P$9:$P$2008,$W40)),INDEX($P$9:$P$2008,$W40),VALUE(SUBSTITUTE(INDEX($P$9:$P$2008,$W40),"%",""))/100),""))
S41: =IF(AND(ISTEXT($A41),ISNUMBER(SEARCH(" - ",$A41)),ISERROR(SEARCH("Folio",$A41)),$D41=""),TRIM($A41),$S40) | T41: =IF(AND(ISNUMBER(SEARCH("Folio",$A41)),$D41<>""),1,"") | U41: =IF($T41=1,COUNTIF($T$9:$T41,1),"") | V41: =IF(AND(ISTEXT($A41),LEFT($A42,3)="Pan"),1,"") | W41: =IFERROR(MATCH(33,$U$9:$U$2008,0),"") | X41: =IF($W41="","",IF($R$5<>"",$R$5,$R$6)) | Y41: =IF($W41="","",INDEX($S$9:$S$2008,$W41)) | Z41: =IF($W41="","",IFERROR(TRIM(LEFT(SUBSTITUTE(INDEX($A$9:$A$2008,$W41),CHAR(10)," "),SEARCH("Folio",SUBSTITUTE(INDEX($A$9:$A$2008,$W41),CHAR(10)," "))-1)),TRIM(SUBSTITUTE(INDEX($A$9:$A$2008,$W41),CHAR(10)," ")))) | AA41: =IF($W41="","",IFERROR(TRIM(SUBSTITUTE(MID(SUBSTITUTE(INDEX($A$9:$A$2008,$W41),CHAR(10)," "),SEARCH("Folio",SUBSTITUTE(INDEX($A$9:$A$2008,$W41),CHAR(10)," "))+5,200),":","")),"")) | AB41: =IF($W41="","",IF(ISNUMBER(INDEX($D$9:$D$2008,$W41)),INDEX($D$9:$D$2008,$W41),IFERROR(DATE(2000+VALUE(RIGHT(INDEX($D$9:$D$2008,$W41),2)),VALUE(MID(INDEX($D$9:$D$2008,$W41),4,2)),VALUE(LEFT(INDEX($D$9:$D$2008,$W41),2))),""))) | AC41: =IF($W41="","",IFERROR(IF(ISNUMBER(INDEX($E$9:$E$2008,$W41)),INDEX($E$9:$E$2008,$W41),VALUE(SUBSTITUTE(INDEX($E$9:$E$2008,$W41),",",""))),"")) | AD41: =IF($W41="","",IFERROR(IF(ISNUMBER(INDEX($F$9:$F$2008,$W41)),INDEX($F$9:$F$2008,$W41),VALUE(SUBSTITUTE(INDEX($F$9:$F$2008,$W41),",",""))),"")) | AE41: =IF($W41="","",IFERROR(IF(ISNUMBER(INDEX($G$9:$G$2008,$W41)),INDEX($G$9:$G$2008,$W41),VALUE(SUBSTITUTE(INDEX($G$9:$G$2008,$W41),",",""))),"")) | AF41: =IF($W41="","",IFERROR(IF(ISNUMBER(INDEX($H$9:$H$2008,$W41)),INDEX($H$9:$H$2008,$W41),VALUE(SUBSTITUTE(INDEX($H$9:$H$2008,$W41),",",""))),"")) | AG41: =IF($W41="","",IFERROR(IF(ISNUMBER(INDEX($I$9:$I$2008,$W41)),INDEX($I$9:$I$2008,$W41),VALUE(SUBSTITUTE(INDEX($I$9:$I$2008,$W41),",",""))),"")) | AH41: =IF($W41="","",IFERROR(IF(ISNUMBER(INDEX($J$9:$J$2008,$W41)),INDEX($J$9:$J$2008,$W41),VALUE(SUBSTITUTE(INDEX($J$9:$J$2008,$W41),",",""))),"")) | AI41: =IF($W41="","",IFERROR(IF(ISNUMBER(INDEX($K$9:$K$2008,$W41)),INDEX($K$9:$K$2008,$W41),VALUE(SUBSTITUTE(INDEX($K$9:$K$2008,$W41),",",""))),"")) | AJ41: =IF($W41="","",IFERROR(IF(ISNUMBER(INDEX($L$9:$L$2008,$W41)),INDEX($L$9:$L$2008,$W41),VALUE(SUBSTITUTE(INDEX($L$9:$L$2008,$W41),",",""))),"")) | AK41: =IF($W41="","",IFERROR(IF(ISNUMBER(INDEX($M$9:$M$2008,$W41)),INDEX($M$9:$M$2008,$W41),VALUE(SUBSTITUTE(INDEX($M$9:$M$2008,$W41),",",""))),"")) | AL41: =IF($W41="","",IFERROR(IF(ISNUMBER(INDEX($P$9:$P$2008,$W41)),INDEX($P$9:$P$2008,$W41),VALUE(SUBSTITUTE(INDEX($P$9:$P$2008,$W41),"%",""))/100),""))
S42: =IF(AND(ISTEXT($A42),ISNUMBER(SEARCH(" - ",$A42)),ISERROR(SEARCH("Folio",$A42)),$D42=""),TRIM($A42),$S41) | T42: =IF(AND(ISNUMBER(SEARCH("Folio",$A42)),$D42<>""),1,"") | U42: =IF($T42=1,COUNTIF($T$9:$T42,1),"") | V42: =IF(AND(ISTEXT($A42),LEFT($A43,3)="Pan"),1,"") | W42: =IFERROR(MATCH(34,$U$9:$U$2008,0),"") | X42: =IF($W42="","",IF($R$5<>"",$R$5,$R$6)) | Y42: =IF($W42="","",INDEX($S$9:$S$2008,$W42)) | Z42: =IF($W42="","",IFERROR(TRIM(LEFT(SUBSTITUTE(INDEX($A$9:$A$2008,$W42),CHAR(10)," "),SEARCH("Folio",SUBSTITUTE(INDEX($A$9:$A$2008,$W42),CHAR(10)," "))-1)),TRIM(SUBSTITUTE(INDEX($A$9:$A$2008,$W42),CHAR(10)," ")))) | AA42: =IF($W42="","",IFERROR(TRIM(SUBSTITUTE(MID(SUBSTITUTE(INDEX($A$9:$A$2008,$W42),CHAR(10)," "),SEARCH("Folio",SUBSTITUTE(INDEX($A$9:$A$2008,$W42),CHAR(10)," "))+5,200),":","")),"")) | AB42: =IF($W42="","",IF(ISNUMBER(INDEX($D$9:$D$2008,$W42)),INDEX($D$9:$D$2008,$W42),IFERROR(DATE(2000+VALUE(RIGHT(INDEX($D$9:$D$2008,$W42),2)),VALUE(MID(INDEX($D$9:$D$2008,$W42),4,2)),VALUE(LEFT(INDEX($D$9:$D$2008,$W42),2))),""))) | AC42: =IF($W42="","",IFERROR(IF(ISNUMBER(INDEX($E$9:$E$2008,$W42)),INDEX($E$9:$E$2008,$W42),VALUE(SUBSTITUTE(INDEX($E$9:$E$2008,$W42),",",""))),"")) | AD42: =IF($W42="","",IFERROR(IF(ISNUMBER(INDEX($F$9:$F$2008,$W42)),INDEX($F$9:$F$2008,$W42),VALUE(SUBSTITUTE(INDEX($F$9:$F$2008,$W42),",",""))),"")) | AE42: =IF($W42="","",IFERROR(IF(ISNUMBER(INDEX($G$9:$G$2008,$W42)),INDEX($G$9:$G$2008,$W42),VALUE(SUBSTITUTE(INDEX($G$9:$G$2008,$W42),",",""))),"")) | AF42: =IF($W42="","",IFERROR(IF(ISNUMBER(INDEX($H$9:$H$2008,$W42)),INDEX($H$9:$H$2008,$W42),VALUE(SUBSTITUTE(INDEX($H$9:$H$2008,$W42),",",""))),"")) | AG42: =IF($W42="","",IFERROR(IF(ISNUMBER(INDEX($I$9:$I$2008,$W42)),INDEX($I$9:$I$2008,$W42),VALUE(SUBSTITUTE(INDEX($I$9:$I$2008,$W42),",",""))),"")) | AH42: =IF($W42="","",IFERROR(IF(ISNUMBER(INDEX($J$9:$J$2008,$W42)),INDEX($J$9:$J$2008,$W42),VALUE(SUBSTITUTE(INDEX($J$9:$J$2008,$W42),",",""))),"")) | AI42: =IF($W42="","",IFERROR(IF(ISNUMBER(INDEX($K$9:$K$2008,$W42)),INDEX($K$9:$K$2008,$W42),VALUE(SUBSTITUTE(INDEX($K$9:$K$2008,$W42),",",""))),"")) | AJ42: =IF($W42="","",IFERROR(IF(ISNUMBER(INDEX($L$9:$L$2008,$W42)),INDEX($L$9:$L$2008,$W42),VALUE(SUBSTITUTE(INDEX($L$9:$L$2008,$W42),",",""))),"")) | AK42: =IF($W42="","",IFERROR(IF(ISNUMBER(INDEX($M$9:$M$2008,$W42)),INDEX($M$9:$M$2008,$W42),VALUE(SUBSTITUTE(INDEX($M$9:$M$2008,$W42),",",""))),"")) | AL42: =IF($W42="","",IFERROR(IF(ISNUMBER(INDEX($P$9:$P$2008,$W42)),INDEX($P$9:$P$2008,$W42),VALUE(SUBSTITUTE(INDEX($P$9:$P$2008,$W42),"%",""))/100),""))
S43: =IF(AND(ISTEXT($A43),ISNUMBER(SEARCH(" - ",$A43)),ISERROR(SEARCH("Folio",$A43)),$D43=""),TRIM($A43),$S42) | T43: =IF(AND(ISNUMBER(SEARCH("Folio",$A43)),$D43<>""),1,"") | U43: =IF($T43=1,COUNTIF($T$9:$T43,1),"") | V43: =IF(AND(ISTEXT($A43),LEFT($A44,3)="Pan"),1,"") | W43: =IFERROR(MATCH(35,$U$9:$U$2008,0),"") | X43: =IF($W43="","",IF($R$5<>"",$R$5,$R$6)) | Y43: =IF($W43="","",INDEX($S$9:$S$2008,$W43)) | Z43: =IF($W43="","",IFERROR(TRIM(LEFT(SUBSTITUTE(INDEX($A$9:$A$2008,$W43),CHAR(10)," "),SEARCH("Folio",SUBSTITUTE(INDEX($A$9:$A$2008,$W43),CHAR(10)," "))-1)),TRIM(SUBSTITUTE(INDEX($A$9:$A$2008,$W43),CHAR(10)," ")))) | AA43: =IF($W43="","",IFERROR(TRIM(SUBSTITUTE(MID(SUBSTITUTE(INDEX($A$9:$A$2008,$W43),CHAR(10)," "),SEARCH("Folio",SUBSTITUTE(INDEX($A$9:$A$2008,$W43),CHAR(10)," "))+5,200),":","")),"")) | AB43: =IF($W43="","",IF(ISNUMBER(INDEX($D$9:$D$2008,$W43)),INDEX($D$9:$D$2008,$W43),IFERROR(DATE(2000+VALUE(RIGHT(INDEX($D$9:$D$2008,$W43),2)),VALUE(MID(INDEX($D$9:$D$2008,$W43),4,2)),VALUE(LEFT(INDEX($D$9:$D$2008,$W43),2))),""))) | AC43: =IF($W43="","",IFERROR(IF(ISNUMBER(INDEX($E$9:$E$2008,$W43)),INDEX($E$9:$E$2008,$W43),VALUE(SUBSTITUTE(INDEX($E$9:$E$2008,$W43),",",""))),"")) | AD43: =IF($W43="","",IFERROR(IF(ISNUMBER(INDEX($F$9:$F$2008,$W43)),INDEX($F$9:$F$2008,$W43),VALUE(SUBSTITUTE(INDEX($F$9:$F$2008,$W43),",",""))),"")) | AE43: =IF($W43="","",IFERROR(IF(ISNUMBER(INDEX($G$9:$G$2008,$W43)),INDEX($G$9:$G$2008,$W43),VALUE(SUBSTITUTE(INDEX($G$9:$G$2008,$W43),",",""))),"")) | AF43: =IF($W43="","",IFERROR(IF(ISNUMBER(INDEX($H$9:$H$2008,$W43)),INDEX($H$9:$H$2008,$W43),VALUE(SUBSTITUTE(INDEX($H$9:$H$2008,$W43),",",""))),"")) | AG43: =IF($W43="","",IFERROR(IF(ISNUMBER(INDEX($I$9:$I$2008,$W43)),INDEX($I$9:$I$2008,$W43),VALUE(SUBSTITUTE(INDEX($I$9:$I$2008,$W43),",",""))),"")) | AH43: =IF($W43="","",IFERROR(IF(ISNUMBER(INDEX($J$9:$J$2008,$W43)),INDEX($J$9:$J$2008,$W43),VALUE(SUBSTITUTE(INDEX($J$9:$J$2008,$W43),",",""))),"")) | AI43: =IF($W43="","",IFERROR(IF(ISNUMBER(INDEX($K$9:$K$2008,$W43)),INDEX($K$9:$K$2008,$W43),VALUE(SUBSTITUTE(INDEX($K$9:$K$2008,$W43),",",""))),"")) | AJ43: =IF($W43="","",IFERROR(IF(ISNUMBER(INDEX($L$9:$L$2008,$W43)),INDEX($L$9:$L$2008,$W43),VALUE(SUBSTITUTE(INDEX($L$9:$L$2008,$W43),",",""))),"")) | AK43: =IF($W43="","",IFERROR(IF(ISNUMBER(INDEX($M$9:$M$2008,$W43)),INDEX($M$9:$M$2008,$W43),VALUE(SUBSTITUTE(INDEX($M$9:$M$2008,$W43),",",""))),"")) | AL43: =IF($W43="","",IFERROR(IF(ISNUMBER(INDEX($P$9:$P$2008,$W43)),INDEX($P$9:$P$2008,$W43),VALUE(SUBSTITUTE(INDEX($P$9:$P$2008,$W43),"%",""))/100),""))
S44: =IF(AND(ISTEXT($A44),ISNUMBER(SEARCH(" - ",$A44)),ISERROR(SEARCH("Folio",$A44)),$D44=""),TRIM($A44),$S43) | T44: =IF(AND(ISNUMBER(SEARCH("Folio",$A44)),$D44<>""),1,"") | U44: =IF($T44=1,COUNTIF($T$9:$T44,1),"") | V44: =IF(AND(ISTEXT($A44),LEFT($A45,3)="Pan"),1,"") | W44: =IFERROR(MATCH(36,$U$9:$U$2008,0),"") | X44: =IF($W44="","",IF($R$5<>"",$R$5,$R$6)) | Y44: =IF($W44="","",INDEX($S$9:$S$2008,$W44)) | Z44: =IF($W44="","",IFERROR(TRIM(LEFT(SUBSTITUTE(INDEX($A$9:$A$2008,$W44),CHAR(10)," "),SEARCH("Folio",SUBSTITUTE(INDEX($A$9:$A$2008,$W44),CHAR(10)," "))-1)),TRIM(SUBSTITUTE(INDEX($A$9:$A$2008,$W44),CHAR(10)," ")))) | AA44: =IF($W44="","",IFERROR(TRIM(SUBSTITUTE(MID(SUBSTITUTE(INDEX($A$9:$A$2008,$W44),CHAR(10)," "),SEARCH("Folio",SUBSTITUTE(INDEX($A$9:$A$2008,$W44),CHAR(10)," "))+5,200),":","")),"")) | AB44: =IF($W44="","",IF(ISNUMBER(INDEX($D$9:$D$2008,$W44)),INDEX($D$9:$D$2008,$W44),IFERROR(DATE(2000+VALUE(RIGHT(INDEX($D$9:$D$2008,$W44),2)),VALUE(MID(INDEX($D$9:$D$2008,$W44),4,2)),VALUE(LEFT(INDEX($D$9:$D$2008,$W44),2))),""))) | AC44: =IF($W44="","",IFERROR(IF(ISNUMBER(INDEX($E$9:$E$2008,$W44)),INDEX($E$9:$E$2008,$W44),VALUE(SUBSTITUTE(INDEX($E$9:$E$2008,$W44),",",""))),"")) | AD44: =IF($W44="","",IFERROR(IF(ISNUMBER(INDEX($F$9:$F$2008,$W44)),INDEX($F$9:$F$2008,$W44),VALUE(SUBSTITUTE(INDEX($F$9:$F$2008,$W44),",",""))),"")) | AE44: =IF($W44="","",IFERROR(IF(ISNUMBER(INDEX($G$9:$G$2008,$W44)),INDEX($G$9:$G$2008,$W44),VALUE(SUBSTITUTE(INDEX($G$9:$G$2008,$W44),",",""))),"")) | AF44: =IF($W44="","",IFERROR(IF(ISNUMBER(INDEX($H$9:$H$2008,$W44)),INDEX($H$9:$H$2008,$W44),VALUE(SUBSTITUTE(INDEX($H$9:$H$2008,$W44),",",""))),"")) | AG44: =IF($W44="","",IFERROR(IF(ISNUMBER(INDEX($I$9:$I$2008,$W44)),INDEX($I$9:$I$2008,$W44),VALUE(SUBSTITUTE(INDEX($I$9:$I$2008,$W44),",",""))),"")) | AH44: =IF($W44="","",IFERROR(IF(ISNUMBER(INDEX($J$9:$J$2008,$W44)),INDEX($J$9:$J$2008,$W44),VALUE(SUBSTITUTE(INDEX($J$9:$J$2008,$W44),",",""))),"")) | AI44: =IF($W44="","",IFERROR(IF(ISNUMBER(INDEX($K$9:$K$2008,$W44)),INDEX($K$9:$K$2008,$W44),VALUE(SUBSTITUTE(INDEX($K$9:$K$2008,$W44),",",""))),"")) | AJ44: =IF($W44="","",IFERROR(IF(ISNUMBER(INDEX($L$9:$L$2008,$W44)),INDEX($L$9:$L$2008,$W44),VALUE(SUBSTITUTE(INDEX($L$9:$L$2008,$W44),",",""))),"")) | AK44: =IF($W44="","",IFERROR(IF(ISNUMBER(INDEX($M$9:$M$2008,$W44)),INDEX($M$9:$M$2008,$W44),VALUE(SUBSTITUTE(INDEX($M$9:$M$2008,$W44),",",""))),"")) | AL44: =IF($W44="","",IFERROR(IF(ISNUMBER(INDEX($P$9:$P$2008,$W44)),INDEX($P$9:$P$2008,$W44),VALUE(SUBSTITUTE(INDEX($P$9:$P$2008,$W44),"%",""))/100),""))
S45: =IF(AND(ISTEXT($A45),ISNUMBER(SEARCH(" - ",$A45)),ISERROR(SEARCH("Folio",$A45)),$D45=""),TRIM($A45),$S44) | T45: =IF(AND(ISNUMBER(SEARCH("Folio",$A45)),$D45<>""),1,"") | U45: =IF($T45=1,COUNTIF($T$9:$T45,1),"") | V45: =IF(AND(ISTEXT($A45),LEFT($A46,3)="Pan"),1,"") | W45: =IFERROR(MATCH(37,$U$9:$U$2008,0),"") | X45: =IF($W45="","",IF($R$5<>"",$R$5,$R$6)) | Y45: =IF($W45="","",INDEX($S$9:$S$2008,$W45)) | Z45: =IF($W45="","",IFERROR(TRIM(LEFT(SUBSTITUTE(INDEX($A$9:$A$2008,$W45),CHAR(10)," "),SEARCH("Folio",SUBSTITUTE(INDEX($A$9:$A$2008,$W45),CHAR(10)," "))-1)),TRIM(SUBSTITUTE(INDEX($A$9:$A$2008,$W45),CHAR(10)," ")))) | AA45: =IF($W45="","",IFERROR(TRIM(SUBSTITUTE(MID(SUBSTITUTE(INDEX($A$9:$A$2008,$W45),CHAR(10)," "),SEARCH("Folio",SUBSTITUTE(INDEX($A$9:$A$2008,$W45),CHAR(10)," "))+5,200),":","")),"")) | AB45: =IF($W45="","",IF(ISNUMBER(INDEX($D$9:$D$2008,$W45)),INDEX($D$9:$D$2008,$W45),IFERROR(DATE(2000+VALUE(RIGHT(INDEX($D$9:$D$2008,$W45),2)),VALUE(MID(INDEX($D$9:$D$2008,$W45),4,2)),VALUE(LEFT(INDEX($D$9:$D$2008,$W45),2))),""))) | AC45: =IF($W45="","",IFERROR(IF(ISNUMBER(INDEX($E$9:$E$2008,$W45)),INDEX($E$9:$E$2008,$W45),VALUE(SUBSTITUTE(INDEX($E$9:$E$2008,$W45),",",""))),"")) | AD45: =IF($W45="","",IFERROR(IF(ISNUMBER(INDEX($F$9:$F$2008,$W45)),INDEX($F$9:$F$2008,$W45),VALUE(SUBSTITUTE(INDEX($F$9:$F$2008,$W45),",",""))),"")) | AE45: =IF($W45="","",IFERROR(IF(ISNUMBER(INDEX($G$9:$G$2008,$W45)),INDEX($G$9:$G$2008,$W45),VALUE(SUBSTITUTE(INDEX($G$9:$G$2008,$W45),",",""))),"")) | AF45: =IF($W45="","",IFERROR(IF(ISNUMBER(INDEX($H$9:$H$2008,$W45)),INDEX($H$9:$H$2008,$W45),VALUE(SUBSTITUTE(INDEX($H$9:$H$2008,$W45),",",""))),"")) | AG45: =IF($W45="","",IFERROR(IF(ISNUMBER(INDEX($I$9:$I$2008,$W45)),INDEX($I$9:$I$2008,$W45),VALUE(SUBSTITUTE(INDEX($I$9:$I$2008,$W45),",",""))),"")) | AH45: =IF($W45="","",IFERROR(IF(ISNUMBER(INDEX($J$9:$J$2008,$W45)),INDEX($J$9:$J$2008,$W45),VALUE(SUBSTITUTE(INDEX($J$9:$J$2008,$W45),",",""))),"")) | AI45: =IF($W45="","",IFERROR(IF(ISNUMBER(INDEX($K$9:$K$2008,$W45)),INDEX($K$9:$K$2008,$W45),VALUE(SUBSTITUTE(INDEX($K$9:$K$2008,$W45),",",""))),"")) | AJ45: =IF($W45="","",IFERROR(IF(ISNUMBER(INDEX($L$9:$L$2008,$W45)),INDEX($L$9:$L$2008,$W45),VALUE(SUBSTITUTE(INDEX($L$9:$L$2008,$W45),",",""))),"")) | AK45: =IF($W45="","",IFERROR(IF(ISNUMBER(INDEX($M$9:$M$2008,$W45)),INDEX($M$9:$M$2008,$W45),VALUE(SUBSTITUTE(INDEX($M$9:$M$2008,$W45),",",""))),"")) | AL45: =IF($W45="","",IFERROR(IF(ISNUMBER(INDEX($P$9:$P$2008,$W45)),INDEX($P$9:$P$2008,$W45),VALUE(SUBSTITUTE(INDEX($P$9:$P$2008,$W45),"%",""))/100),""))
S46: =IF(AND(ISTEXT($A46),ISNUMBER(SEARCH(" - ",$A46)),ISERROR(SEARCH("Folio",$A46)),$D46=""),TRIM($A46),$S45) | T46: =IF(AND(ISNUMBER(SEARCH("Folio",$A46)),$D46<>""),1,"") | U46: =IF($T46=1,COUNTIF($T$9:$T46,1),"") | V46: =IF(AND(ISTEXT($A46),LEFT($A47,3)="Pan"),1,"") | W46: =IFERROR(MATCH(38,$U$9:$U$2008,0),"") | X46: =IF($W46="","",IF($R$5<>"",$R$5,$R$6)) | Y46: =IF($W46="","",INDEX($S$9:$S$2008,$W46)) | Z46: =IF($W46="","",IFERROR(TRIM(LEFT(SUBSTITUTE(INDEX($A$9:$A$2008,$W46),CHAR(10)," "),SEARCH("Folio",SUBSTITUTE(INDEX($A$9:$A$2008,$W46),CHAR(10)," "))-1)),TRIM(SUBSTITUTE(INDEX($A$9:$A$2008,$W46),CHAR(10)," ")))) | AA46: =IF($W46="","",IFERROR(TRIM(SUBSTITUTE(MID(SUBSTITUTE(INDEX($A$9:$A$2008,$W46),CHAR(10)," "),SEARCH("Folio",SUBSTITUTE(INDEX($A$9:$A$2008,$W46),CHAR(10)," "))+5,200),":","")),"")) | AB46: =IF($W46="","",IF(ISNUMBER(INDEX($D$9:$D$2008,$W46)),INDEX($D$9:$D$2008,$W46),IFERROR(DATE(2000+VALUE(RIGHT(INDEX($D$9:$D$2008,$W46),2)),VALUE(MID(INDEX($D$9:$D$2008,$W46),4,2)),VALUE(LEFT(INDEX($D$9:$D$2008,$W46),2))),""))) | AC46: =IF($W46="","",IFERROR(IF(ISNUMBER(INDEX($E$9:$E$2008,$W46)),INDEX($E$9:$E$2008,$W46),VALUE(SUBSTITUTE(INDEX($E$9:$E$2008,$W46),",",""))),"")) | AD46: =IF($W46="","",IFERROR(IF(ISNUMBER(INDEX($F$9:$F$2008,$W46)),INDEX($F$9:$F$2008,$W46),VALUE(SUBSTITUTE(INDEX($F$9:$F$2008,$W46),",",""))),"")) | AE46: =IF($W46="","",IFERROR(IF(ISNUMBER(INDEX($G$9:$G$2008,$W46)),INDEX($G$9:$G$2008,$W46),VALUE(SUBSTITUTE(INDEX($G$9:$G$2008,$W46),",",""))),"")) | AF46: =IF($W46="","",IFERROR(IF(ISNUMBER(INDEX($H$9:$H$2008,$W46)),INDEX($H$9:$H$2008,$W46),VALUE(SUBSTITUTE(INDEX($H$9:$H$2008,$W46),",",""))),"")) | AG46: =IF($W46="","",IFERROR(IF(ISNUMBER(INDEX($I$9:$I$2008,$W46)),INDEX($I$9:$I$2008,$W46),VALUE(SUBSTITUTE(INDEX($I$9:$I$2008,$W46),",",""))),"")) | AH46: =IF($W46="","",IFERROR(IF(ISNUMBER(INDEX($J$9:$J$2008,$W46)),INDEX($J$9:$J$2008,$W46),VALUE(SUBSTITUTE(INDEX($J$9:$J$2008,$W46),",",""))),"")) | AI46: =IF($W46="","",IFERROR(IF(ISNUMBER(INDEX($K$9:$K$2008,$W46)),INDEX($K$9:$K$2008,$W46),VALUE(SUBSTITUTE(INDEX($K$9:$K$2008,$W46),",",""))),"")) | AJ46: =IF($W46="","",IFERROR(IF(ISNUMBER(INDEX($L$9:$L$2008,$W46)),INDEX($L$9:$L$2008,$W46),VALUE(SUBSTITUTE(INDEX($L$9:$L$2008,$W46),",",""))),"")) | AK46: =IF($W46="","",IFERROR(IF(ISNUMBER(INDEX($M$9:$M$2008,$W46)),INDEX($M$9:$M$2008,$W46),VALUE(SUBSTITUTE(INDEX($M$9:$M$2008,$W46),",",""))),"")) | AL46: =IF($W46="","",IFERROR(IF(ISNUMBER(INDEX($P$9:$P$2008,$W46)),INDEX($P$9:$P$2008,$W46),VALUE(SUBSTITUTE(INDEX($P$9:$P$2008,$W46),"%",""))/100),""))
S47: =IF(AND(ISTEXT($A47),ISNUMBER(SEARCH(" - ",$A47)),ISERROR(SEARCH("Folio",$A47)),$D47=""),TRIM($A47),$S46) | T47: =IF(AND(ISNUMBER(SEARCH("Folio",$A47)),$D47<>""),1,"") | U47: =IF($T47=1,COUNTIF($T$9:$T47,1),"") | V47: =IF(AND(ISTEXT($A47),LEFT($A48,3)="Pan"),1,"") | W47: =IFERROR(MATCH(39,$U$9:$U$2008,0),"") | X47: =IF($W47="","",IF($R$5<>"",$R$5,$R$6)) | Y47: =IF($W47="","",INDEX($S$9:$S$2008,$W47)) | Z47: =IF($W47="","",IFERROR(TRIM(LEFT(SUBSTITUTE(INDEX($A$9:$A$2008,$W47),CHAR(10)," "),SEARCH("Folio",SUBSTITUTE(INDEX($A$9:$A$2008,$W47),CHAR(10)," "))-1)),TRIM(SUBSTITUTE(INDEX($A$9:$A$2008,$W47),CHAR(10)," ")))) | AA47: =IF($W47="","",IFERROR(TRIM(SUBSTITUTE(MID(SUBSTITUTE(INDEX($A$9:$A$2008,$W47),CHAR(10)," "),SEARCH("Folio",SUBSTITUTE(INDEX($A$9:$A$2008,$W47),CHAR(10)," "))+5,200),":","")),"")) | AB47: =IF($W47="","",IF(ISNUMBER(INDEX($D$9:$D$2008,$W47)),INDEX($D$9:$D$2008,$W47),IFERROR(DATE(2000+VALUE(RIGHT(INDEX($D$9:$D$2008,$W47),2)),VALUE(MID(INDEX($D$9:$D$2008,$W47),4,2)),VALUE(LEFT(INDEX($D$9:$D$2008,$W47),2))),""))) | AC47: =IF($W47="","",IFERROR(IF(ISNUMBER(INDEX($E$9:$E$2008,$W47)),INDEX($E$9:$E$2008,$W47),VALUE(SUBSTITUTE(INDEX($E$9:$E$2008,$W47),",",""))),"")) | AD47: =IF($W47="","",IFERROR(IF(ISNUMBER(INDEX($F$9:$F$2008,$W47)),INDEX($F$9:$F$2008,$W47),VALUE(SUBSTITUTE(INDEX($F$9:$F$2008,$W47),",",""))),"")) | AE47: =IF($W47="","",IFERROR(IF(ISNUMBER(INDEX($G$9:$G$2008,$W47)),INDEX($G$9:$G$2008,$W47),VALUE(SUBSTITUTE(INDEX($G$9:$G$2008,$W47),",",""))),"")) | AF47: =IF($W47="","",IFERROR(IF(ISNUMBER(INDEX($H$9:$H$2008,$W47)),INDEX($H$9:$H$2008,$W47),VALUE(SUBSTITUTE(INDEX($H$9:$H$2008,$W47),",",""))),"")) | AG47: =IF($W47="","",IFERROR(IF(ISNUMBER(INDEX($I$9:$I$2008,$W47)),INDEX($I$9:$I$2008,$W47),VALUE(SUBSTITUTE(INDEX($I$9:$I$2008,$W47),",",""))),"")) | AH47: =IF($W47="","",IFERROR(IF(ISNUMBER(INDEX($J$9:$J$2008,$W47)),INDEX($J$9:$J$2008,$W47),VALUE(SUBSTITUTE(INDEX($J$9:$J$2008,$W47),",",""))),"")) | AI47: =IF($W47="","",IFERROR(IF(ISNUMBER(INDEX($K$9:$K$2008,$W47)),INDEX($K$9:$K$2008,$W47),VALUE(SUBSTITUTE(INDEX($K$9:$K$2008,$W47),",",""))),"")) | AJ47: =IF($W47="","",IFERROR(IF(ISNUMBER(INDEX($L$9:$L$2008,$W47)),INDEX($L$9:$L$2008,$W47),VALUE(SUBSTITUTE(INDEX($L$9:$L$2008,$W47),",",""))),"")) | AK47: =IF($W47="","",IFERROR(IF(ISNUMBER(INDEX($M$9:$M$2008,$W47)),INDEX($M$9:$M$2008,$W47),VALUE(SUBSTITUTE(INDEX($M$9:$M$2008,$W47),",",""))),"")) | AL47: =IF($W47="","",IFERROR(IF(ISNUMBER(INDEX($P$9:$P$2008,$W47)),INDEX($P$9:$P$2008,$W47),VALUE(SUBSTITUTE(INDEX($P$9:$P$2008,$W47),"%",""))/100),""))
S48: =IF(AND(ISTEXT($A48),ISNUMBER(SEARCH(" - ",$A48)),ISERROR(SEARCH("Folio",$A48)),$D48=""),TRIM($A48),$S47) | T48: =IF(AND(ISNUMBER(SEARCH("Folio",$A48)),$D48<>""),1,"") | U48: =IF($T48=1,COUNTIF($T$9:$T48,1),"") | V48: =IF(AND(ISTEXT($A48),LEFT($A49,3)="Pan"),1,"") | W48: =IFERROR(MATCH(40,$U$9:$U$2008,0),"") | X48: =IF($W48="","",IF($R$5<>"",$R$5,$R$6)) | Y48: =IF($W48="","",INDEX($S$9:$S$2008,$W48)) | Z48: =IF($W48="","",IFERROR(TRIM(LEFT(SUBSTITUTE(INDEX($A$9:$A$2008,$W48),CHAR(10)," "),SEARCH("Folio",SUBSTITUTE(INDEX($A$9:$A$2008,$W48),CHAR(10)," "))-1)),TRIM(SUBSTITUTE(INDEX($A$9:$A$2008,$W48),CHAR(10)," ")))) | AA48: =IF($W48="","",IFERROR(TRIM(SUBSTITUTE(MID(SUBSTITUTE(INDEX($A$9:$A$2008,$W48),CHAR(10)," "),SEARCH("Folio",SUBSTITUTE(INDEX($A$9:$A$2008,$W48),CHAR(10)," "))+5,200),":","")),"")) | AB48: =IF($W48="","",IF(ISNUMBER(INDEX($D$9:$D$2008,$W48)),INDEX($D$9:$D$2008,$W48),IFERROR(DATE(2000+VALUE(RIGHT(INDEX($D$9:$D$2008,$W48),2)),VALUE(MID(INDEX($D$9:$D$2008,$W48),4,2)),VALUE(LEFT(INDEX($D$9:$D$2008,$W48),2))),""))) | AC48: =IF($W48="","",IFERROR(IF(ISNUMBER(INDEX($E$9:$E$2008,$W48)),INDEX($E$9:$E$2008,$W48),VALUE(SUBSTITUTE(INDEX($E$9:$E$2008,$W48),",",""))),"")) | AD48: =IF($W48="","",IFERROR(IF(ISNUMBER(INDEX($F$9:$F$2008,$W48)),INDEX($F$9:$F$2008,$W48),VALUE(SUBSTITUTE(INDEX($F$9:$F$2008,$W48),",",""))),"")) | AE48: =IF($W48="","",IFERROR(IF(ISNUMBER(INDEX($G$9:$G$2008,$W48)),INDEX($G$9:$G$2008,$W48),VALUE(SUBSTITUTE(INDEX($G$9:$G$2008,$W48),",",""))),"")) | AF48: =IF($W48="","",IFERROR(IF(ISNUMBER(INDEX($H$9:$H$2008,$W48)),INDEX($H$9:$H$2008,$W48),VALUE(SUBSTITUTE(INDEX($H$9:$H$2008,$W48),",",""))),"")) | AG48: =IF($W48="","",IFERROR(IF(ISNUMBER(INDEX($I$9:$I$2008,$W48)),INDEX($I$9:$I$2008,$W48),VALUE(SUBSTITUTE(INDEX($I$9:$I$2008,$W48),",",""))),"")) | AH48: =IF($W48="","",IFERROR(IF(ISNUMBER(INDEX($J$9:$J$2008,$W48)),INDEX($J$9:$J$2008,$W48),VALUE(SUBSTITUTE(INDEX($J$9:$J$2008,$W48),",",""))),"")) | AI48: =IF($W48="","",IFERROR(IF(ISNUMBER(INDEX($K$9:$K$2008,$W48)),INDEX($K$9:$K$2008,$W48),VALUE(SUBSTITUTE(INDEX($K$9:$K$2008,$W48),",",""))),"")) | AJ48: =IF($W48="","",IFERROR(IF(ISNUMBER(INDEX($L$9:$L$2008,$W48)),INDEX($L$9:$L$2008,$W48),VALUE(SUBSTITUTE(INDEX($L$9:$L$2008,$W48),",",""))),"")) | AK48: =IF($W48="","",IFERROR(IF(ISNUMBER(INDEX($M$9:$M$2008,$W48)),INDEX($M$9:$M$2008,$W48),VALUE(SUBSTITUTE(INDEX($M$9:$M$2008,$W48),",",""))),"")) | AL48: =IF($W48="","",IFERROR(IF(ISNUMBER(INDEX($P$9:$P$2008,$W48)),INDEX($P$9:$P$2008,$W48),VALUE(SUBSTITUTE(INDEX($P$9:$P$2008,$W48),"%",""))/100),""))
S49: =IF(AND(ISTEXT($A49),ISNUMBER(SEARCH(" - ",$A49)),ISERROR(SEARCH("Folio",$A49)),$D49=""),TRIM($A49),$S48) | T49: =IF(AND(ISNUMBER(SEARCH("Folio",$A49)),$D49<>""),1,"") | U49: =IF($T49=1,COUNTIF($T$9:$T49,1),"") | V49: =IF(AND(ISTEXT($A49),LEFT($A50,3)="Pan"),1,"") | W49: =IFERROR(MATCH(41,$U$9:$U$2008,0),"") | X49: =IF($W49="","",IF($R$5<>"",$R$5,$R$6)) | Y49: =IF($W49="","",INDEX($S$9:$S$2008,$W49)) | Z49: =IF($W49="","",IFERROR(TRIM(LEFT(SUBSTITUTE(INDEX($A$9:$A$2008,$W49),CHAR(10)," "),SEARCH("Folio",SUBSTITUTE(INDEX($A$9:$A$2008,$W49),CHAR(10)," "))-1)),TRIM(SUBSTITUTE(INDEX($A$9:$A$2008,$W49),CHAR(10)," ")))) | AA49: =IF($W49="","",IFERROR(TRIM(SUBSTITUTE(MID(SUBSTITUTE(INDEX($A$9:$A$2008,$W49),CHAR(10)," "),SEARCH("Folio",SUBSTITUTE(INDEX($A$9:$A$2008,$W49),CHAR(10)," "))+5,200),":","")),"")) | AB49: =IF($W49="","",IF(ISNUMBER(INDEX($D$9:$D$2008,$W49)),INDEX($D$9:$D$2008,$W49),IFERROR(DATE(2000+VALUE(RIGHT(INDEX($D$9:$D$2008,$W49),2)),VALUE(MID(INDEX($D$9:$D$2008,$W49),4,2)),VALUE(LEFT(INDEX($D$9:$D$2008,$W49),2))),""))) | AC49: =IF($W49="","",IFERROR(IF(ISNUMBER(INDEX($E$9:$E$2008,$W49)),INDEX($E$9:$E$2008,$W49),VALUE(SUBSTITUTE(INDEX($E$9:$E$2008,$W49),",",""))),"")) | AD49: =IF($W49="","",IFERROR(IF(ISNUMBER(INDEX($F$9:$F$2008,$W49)),INDEX($F$9:$F$2008,$W49),VALUE(SUBSTITUTE(INDEX($F$9:$F$2008,$W49),",",""))),"")) | AE49: =IF($W49="","",IFERROR(IF(ISNUMBER(INDEX($G$9:$G$2008,$W49)),INDEX($G$9:$G$2008,$W49),VALUE(SUBSTITUTE(INDEX($G$9:$G$2008,$W49),",",""))),"")) | AF49: =IF($W49="","",IFERROR(IF(ISNUMBER(INDEX($H$9:$H$2008,$W49)),INDEX($H$9:$H$2008,$W49),VALUE(SUBSTITUTE(INDEX($H$9:$H$2008,$W49),",",""))),"")) | AG49: =IF($W49="","",IFERROR(IF(ISNUMBER(INDEX($I$9:$I$2008,$W49)),INDEX($I$9:$I$2008,$W49),VALUE(SUBSTITUTE(INDEX($I$9:$I$2008,$W49),",",""))),"")) | AH49: =IF($W49="","",IFERROR(IF(ISNUMBER(INDEX($J$9:$J$2008,$W49)),INDEX($J$9:$J$2008,$W49),VALUE(SUBSTITUTE(INDEX($J$9:$J$2008,$W49),",",""))),"")) | AI49: =IF($W49="","",IFERROR(IF(ISNUMBER(INDEX($K$9:$K$2008,$W49)),INDEX($K$9:$K$2008,$W49),VALUE(SUBSTITUTE(INDEX($K$9:$K$2008,$W49),",",""))),"")) | AJ49: =IF($W49="","",IFERROR(IF(ISNUMBER(INDEX($L$9:$L$2008,$W49)),INDEX($L$9:$L$2008,$W49),VALUE(SUBSTITUTE(INDEX($L$9:$L$2008,$W49),",",""))),"")) | AK49: =IF($W49="","",IFERROR(IF(ISNUMBER(INDEX($M$9:$M$2008,$W49)),INDEX($M$9:$M$2008,$W49),VALUE(SUBSTITUTE(INDEX($M$9:$M$2008,$W49),",",""))),"")) | AL49: =IF($W49="","",IFERROR(IF(ISNUMBER(INDEX($P$9:$P$2008,$W49)),INDEX($P$9:$P$2008,$W49),VALUE(SUBSTITUTE(INDEX($P$9:$P$2008,$W49),"%",""))/100),""))
S50: =IF(AND(ISTEXT($A50),ISNUMBER(SEARCH(" - ",$A50)),ISERROR(SEARCH("Folio",$A50)),$D50=""),TRIM($A50),$S49) | T50: =IF(AND(ISNUMBER(SEARCH("Folio",$A50)),$D50<>""),1,"") | U50: =IF($T50=1,COUNTIF($T$9:$T50,1),"") | V50: =IF(AND(ISTEXT($A50),LEFT($A51,3)="Pan"),1,"") | W50: =IFERROR(MATCH(42,$U$9:$U$2008,0),"") | X50: =IF($W50="","",IF($R$5<>"",$R$5,$R$6)) | Y50: =IF($W50="","",INDEX($S$9:$S$2008,$W50)) | Z50: =IF($W50="","",IFERROR(TRIM(LEFT(SUBSTITUTE(INDEX($A$9:$A$2008,$W50),CHAR(10)," "),SEARCH("Folio",SUBSTITUTE(INDEX($A$9:$A$2008,$W50),CHAR(10)," "))-1)),TRIM(SUBSTITUTE(INDEX($A$9:$A$2008,$W50),CHAR(10)," ")))) | AA50: =IF($W50="","",IFERROR(TRIM(SUBSTITUTE(MID(SUBSTITUTE(INDEX($A$9:$A$2008,$W50),CHAR(10)," "),SEARCH("Folio",SUBSTITUTE(INDEX($A$9:$A$2008,$W50),CHAR(10)," "))+5,200),":","")),"")) | AB50: =IF($W50="","",IF(ISNUMBER(INDEX($D$9:$D$2008,$W50)),INDEX($D$9:$D$2008,$W50),IFERROR(DATE(2000+VALUE(RIGHT(INDEX($D$9:$D$2008,$W50),2)),VALUE(MID(INDEX($D$9:$D$2008,$W50),4,2)),VALUE(LEFT(INDEX($D$9:$D$2008,$W50),2))),""))) | AC50: =IF($W50="","",IFERROR(IF(ISNUMBER(INDEX($E$9:$E$2008,$W50)),INDEX($E$9:$E$2008,$W50),VALUE(SUBSTITUTE(INDEX($E$9:$E$2008,$W50),",",""))),"")) | AD50: =IF($W50="","",IFERROR(IF(ISNUMBER(INDEX($F$9:$F$2008,$W50)),INDEX($F$9:$F$2008,$W50),VALUE(SUBSTITUTE(INDEX($F$9:$F$2008,$W50),",",""))),"")) | AE50: =IF($W50="","",IFERROR(IF(ISNUMBER(INDEX($G$9:$G$2008,$W50)),INDEX($G$9:$G$2008,$W50),VALUE(SUBSTITUTE(INDEX($G$9:$G$2008,$W50),",",""))),"")) | AF50: =IF($W50="","",IFERROR(IF(ISNUMBER(INDEX($H$9:$H$2008,$W50)),INDEX($H$9:$H$2008,$W50),VALUE(SUBSTITUTE(INDEX($H$9:$H$2008,$W50),",",""))),"")) | AG50: =IF($W50="","",IFERROR(IF(ISNUMBER(INDEX($I$9:$I$2008,$W50)),INDEX($I$9:$I$2008,$W50),VALUE(SUBSTITUTE(INDEX($I$9:$I$2008,$W50),",",""))),"")) | AH50: =IF($W50="","",IFERROR(IF(ISNUMBER(INDEX($J$9:$J$2008,$W50)),INDEX($J$9:$J$2008,$W50),VALUE(SUBSTITUTE(INDEX($J$9:$J$2008,$W50),",",""))),"")) | AI50: =IF($W50="","",IFERROR(IF(ISNUMBER(INDEX($K$9:$K$2008,$W50)),INDEX($K$9:$K$2008,$W50),VALUE(SUBSTITUTE(INDEX($K$9:$K$2008,$W50),",",""))),"")) | AJ50: =IF($W50="","",IFERROR(IF(ISNUMBER(INDEX($L$9:$L$2008,$W50)),INDEX($L$9:$L$2008,$W50),VALUE(SUBSTITUTE(INDEX($L$9:$L$2008,$W50),",",""))),"")) | AK50: =IF($W50="","",IFERROR(IF(ISNUMBER(INDEX($M$9:$M$2008,$W50)),INDEX($M$9:$M$2008,$W50),VALUE(SUBSTITUTE(INDEX($M$9:$M$2008,$W50),",",""))),"")) | AL50: =IF($W50="","",IFERROR(IF(ISNUMBER(INDEX($P$9:$P$2008,$W50)),INDEX($P$9:$P$2008,$W50),VALUE(SUBSTITUTE(INDEX($P$9:$P$2008,$W50),"%",""))/100),""))
S51: =IF(AND(ISTEXT($A51),ISNUMBER(SEARCH(" - ",$A51)),ISERROR(SEARCH("Folio",$A51)),$D51=""),TRIM($A51),$S50) | T51: =IF(AND(ISNUMBER(SEARCH("Folio",$A51)),$D51<>""),1,"") | U51: =IF($T51=1,COUNTIF($T$9:$T51,1),"") | V51: =IF(AND(ISTEXT($A51),LEFT($A52,3)="Pan"),1,"") | W51: =IFERROR(MATCH(43,$U$9:$U$2008,0),"") | X51: =IF($W51="","",IF($R$5<>"",$R$5,$R$6)) | Y51: =IF($W51="","",INDEX($S$9:$S$2008,$W51)) | Z51: =IF($W51="","",IFERROR(TRIM(LEFT(SUBSTITUTE(INDEX($A$9:$A$2008,$W51),CHAR(10)," "),SEARCH("Folio",SUBSTITUTE(INDEX($A$9:$A$2008,$W51),CHAR(10)," "))-1)),TRIM(SUBSTITUTE(INDEX($A$9:$A$2008,$W51),CHAR(10)," ")))) | AA51: =IF($W51="","",IFERROR(TRIM(SUBSTITUTE(MID(SUBSTITUTE(INDEX($A$9:$A$2008,$W51),CHAR(10)," "),SEARCH("Folio",SUBSTITUTE(INDEX($A$9:$A$2008,$W51),CHAR(10)," "))+5,200),":","")),"")) | AB51: =IF($W51="","",IF(ISNUMBER(INDEX($D$9:$D$2008,$W51)),INDEX($D$9:$D$2008,$W51),IFERROR(DATE(2000+VALUE(RIGHT(INDEX($D$9:$D$2008,$W51),2)),VALUE(MID(INDEX($D$9:$D$2008,$W51),4,2)),VALUE(LEFT(INDEX($D$9:$D$2008,$W51),2))),""))) | AC51: =IF($W51="","",IFERROR(IF(ISNUMBER(INDEX($E$9:$E$2008,$W51)),INDEX($E$9:$E$2008,$W51),VALUE(SUBSTITUTE(INDEX($E$9:$E$2008,$W51),",",""))),"")) | AD51: =IF($W51="","",IFERROR(IF(ISNUMBER(INDEX($F$9:$F$2008,$W51)),INDEX($F$9:$F$2008,$W51),VALUE(SUBSTITUTE(INDEX($F$9:$F$2008,$W51),",",""))),"")) | AE51: =IF($W51="","",IFERROR(IF(ISNUMBER(INDEX($G$9:$G$2008,$W51)),INDEX($G$9:$G$2008,$W51),VALUE(SUBSTITUTE(INDEX($G$9:$G$2008,$W51),",",""))),"")) | AF51: =IF($W51="","",IFERROR(IF(ISNUMBER(INDEX($H$9:$H$2008,$W51)),INDEX($H$9:$H$2008,$W51),VALUE(SUBSTITUTE(INDEX($H$9:$H$2008,$W51),",",""))),"")) | AG51: =IF($W51="","",IFERROR(IF(ISNUMBER(INDEX($I$9:$I$2008,$W51)),INDEX($I$9:$I$2008,$W51),VALUE(SUBSTITUTE(INDEX($I$9:$I$2008,$W51),",",""))),"")) | AH51: =IF($W51="","",IFERROR(IF(ISNUMBER(INDEX($J$9:$J$2008,$W51)),INDEX($J$9:$J$2008,$W51),VALUE(SUBSTITUTE(INDEX($J$9:$J$2008,$W51),",",""))),"")) | AI51: =IF($W51="","",IFERROR(IF(ISNUMBER(INDEX($K$9:$K$2008,$W51)),INDEX($K$9:$K$2008,$W51),VALUE(SUBSTITUTE(INDEX($K$9:$K$2008,$W51),",",""))),"")) | AJ51: =IF($W51="","",IFERROR(IF(ISNUMBER(INDEX($L$9:$L$2008,$W51)),INDEX($L$9:$L$2008,$W51),VALUE(SUBSTITUTE(INDEX($L$9:$L$2008,$W51),",",""))),"")) | AK51: =IF($W51="","",IFERROR(IF(ISNUMBER(INDEX($M$9:$M$2008,$W51)),INDEX($M$9:$M$2008,$W51),VALUE(SUBSTITUTE(INDEX($M$9:$M$2008,$W51),",",""))),"")) | AL51: =IF($W51="","",IFERROR(IF(ISNUMBER(INDEX($P$9:$P$2008,$W51)),INDEX($P$9:$P$2008,$W51),VALUE(SUBSTITUTE(INDEX($P$9:$P$2008,$W51),"%",""))/100),""))
S52: =IF(AND(ISTEXT($A52),ISNUMBER(SEARCH(" - ",$A52)),ISERROR(SEARCH("Folio",$A52)),$D52=""),TRIM($A52),$S51) | T52: =IF(AND(ISNUMBER(SEARCH("Folio",$A52)),$D52<>""),1,"") | U52: =IF($T52=1,COUNTIF($T$9:$T52,1),"") | V52: =IF(AND(ISTEXT($A52),LEFT($A53,3)="Pan"),1,"") | W52: =IFERROR(MATCH(44,$U$9:$U$2008,0),"") | X52: =IF($W52="","",IF($R$5<>"",$R$5,$R$6)) | Y52: =IF($W52="","",INDEX($S$9:$S$2008,$W52)) | Z52: =IF($W52="","",IFERROR(TRIM(LEFT(SUBSTITUTE(INDEX($A$9:$A$2008,$W52),CHAR(10)," "),SEARCH("Folio",SUBSTITUTE(INDEX($A$9:$A$2008,$W52),CHAR(10)," "))-1)),TRIM(SUBSTITUTE(INDEX($A$9:$A$2008,$W52),CHAR(10)," ")))) | AA52: =IF($W52="","",IFERROR(TRIM(SUBSTITUTE(MID(SUBSTITUTE(INDEX($A$9:$A$2008,$W52),CHAR(10)," "),SEARCH("Folio",SUBSTITUTE(INDEX($A$9:$A$2008,$W52),CHAR(10)," "))+5,200),":","")),"")) | AB52: =IF($W52="","",IF(ISNUMBER(INDEX($D$9:$D$2008,$W52)),INDEX($D$9:$D$2008,$W52),IFERROR(DATE(2000+VALUE(RIGHT(INDEX($D$9:$D$2008,$W52),2)),VALUE(MID(INDEX($D$9:$D$2008,$W52),4,2)),VALUE(LEFT(INDEX($D$9:$D$2008,$W52),2))),""))) | AC52: =IF($W52="","",IFERROR(IF(ISNUMBER(INDEX($E$9:$E$2008,$W52)),INDEX($E$9:$E$2008,$W52),VALUE(SUBSTITUTE(INDEX($E$9:$E$2008,$W52),",",""))),"")) | AD52: =IF($W52="","",IFERROR(IF(ISNUMBER(INDEX($F$9:$F$2008,$W52)),INDEX($F$9:$F$2008,$W52),VALUE(SUBSTITUTE(INDEX($F$9:$F$2008,$W52),",",""))),"")) | AE52: =IF($W52="","",IFERROR(IF(ISNUMBER(INDEX($G$9:$G$2008,$W52)),INDEX($G$9:$G$2008,$W52),VALUE(SUBSTITUTE(INDEX($G$9:$G$2008,$W52),",",""))),"")) | AF52: =IF($W52="","",IFERROR(IF(ISNUMBER(INDEX($H$9:$H$2008,$W52)),INDEX($H$9:$H$2008,$W52),VALUE(SUBSTITUTE(INDEX($H$9:$H$2008,$W52),",",""))),"")) | AG52: =IF($W52="","",IFERROR(IF(ISNUMBER(INDEX($I$9:$I$2008,$W52)),INDEX($I$9:$I$2008,$W52),VALUE(SUBSTITUTE(INDEX($I$9:$I$2008,$W52),",",""))),"")) | AH52: =IF($W52="","",IFERROR(IF(ISNUMBER(INDEX($J$9:$J$2008,$W52)),INDEX($J$9:$J$2008,$W52),VALUE(SUBSTITUTE(INDEX($J$9:$J$2008,$W52),",",""))),"")) | AI52: =IF($W52="","",IFERROR(IF(ISNUMBER(INDEX($K$9:$K$2008,$W52)),INDEX($K$9:$K$2008,$W52),VALUE(SUBSTITUTE(INDEX($K$9:$K$2008,$W52),",",""))),"")) | AJ52: =IF($W52="","",IFERROR(IF(ISNUMBER(INDEX($L$9:$L$2008,$W52)),INDEX($L$9:$L$2008,$W52),VALUE(SUBSTITUTE(INDEX($L$9:$L$2008,$W52),",",""))),"")) | AK52: =IF($W52="","",IFERROR(IF(ISNUMBER(INDEX($M$9:$M$2008,$W52)),INDEX($M$9:$M$2008,$W52),VALUE(SUBSTITUTE(INDEX($M$9:$M$2008,$W52),",",""))),"")) | AL52: =IF($W52="","",IFERROR(IF(ISNUMBER(INDEX($P$9:$P$2008,$W52)),INDEX($P$9:$P$2008,$W52),VALUE(SUBSTITUTE(INDEX($P$9:$P$2008,$W52),"%",""))/100),""))
S53: =IF(AND(ISTEXT($A53),ISNUMBER(SEARCH(" - ",$A53)),ISERROR(SEARCH("Folio",$A53)),$D53=""),TRIM($A53),$S52) | T53: =IF(AND(ISNUMBER(SEARCH("Folio",$A53)),$D53<>""),1,"") | U53: =IF($T53=1,COUNTIF($T$9:$T53,1),"") | V53: =IF(AND(ISTEXT($A53),LEFT($A54,3)="Pan"),1,"") | W53: =IFERROR(MATCH(45,$U$9:$U$2008,0),"") | X53: =IF($W53="","",IF($R$5<>"",$R$5,$R$6)) | Y53: =IF($W53="","",INDEX($S$9:$S$2008,$W53)) | Z53: =IF($W53="","",IFERROR(TRIM(LEFT(SUBSTITUTE(INDEX($A$9:$A$2008,$W53),CHAR(10)," "),SEARCH("Folio",SUBSTITUTE(INDEX($A$9:$A$2008,$W53),CHAR(10)," "))-1)),TRIM(SUBSTITUTE(INDEX($A$9:$A$2008,$W53),CHAR(10)," ")))) | AA53: =IF($W53="","",IFERROR(TRIM(SUBSTITUTE(MID(SUBSTITUTE(INDEX($A$9:$A$2008,$W53),CHAR(10)," "),SEARCH("Folio",SUBSTITUTE(INDEX($A$9:$A$2008,$W53),CHAR(10)," "))+5,200),":","")),"")) | AB53: =IF($W53="","",IF(ISNUMBER(INDEX($D$9:$D$2008,$W53)),INDEX($D$9:$D$2008,$W53),IFERROR(DATE(2000+VALUE(RIGHT(INDEX($D$9:$D$2008,$W53),2)),VALUE(MID(INDEX($D$9:$D$2008,$W53),4,2)),VALUE(LEFT(INDEX($D$9:$D$2008,$W53),2))),""))) | AC53: =IF($W53="","",IFERROR(IF(ISNUMBER(INDEX($E$9:$E$2008,$W53)),INDEX($E$9:$E$2008,$W53),VALUE(SUBSTITUTE(INDEX($E$9:$E$2008,$W53),",",""))),"")) | AD53: =IF($W53="","",IFERROR(IF(ISNUMBER(INDEX($F$9:$F$2008,$W53)),INDEX($F$9:$F$2008,$W53),VALUE(SUBSTITUTE(INDEX($F$9:$F$2008,$W53),",",""))),"")) | AE53: =IF($W53="","",IFERROR(IF(ISNUMBER(INDEX($G$9:$G$2008,$W53)),INDEX($G$9:$G$2008,$W53),VALUE(SUBSTITUTE(INDEX($G$9:$G$2008,$W53),",",""))),"")) | AF53: =IF($W53="","",IFERROR(IF(ISNUMBER(INDEX($H$9:$H$2008,$W53)),INDEX($H$9:$H$2008,$W53),VALUE(SUBSTITUTE(INDEX($H$9:$H$2008,$W53),",",""))),"")) | AG53: =IF($W53="","",IFERROR(IF(ISNUMBER(INDEX($I$9:$I$2008,$W53)),INDEX($I$9:$I$2008,$W53),VALUE(SUBSTITUTE(INDEX($I$9:$I$2008,$W53),",",""))),"")) | AH53: =IF($W53="","",IFERROR(IF(ISNUMBER(INDEX($J$9:$J$2008,$W53)),INDEX($J$9:$J$2008,$W53),VALUE(SUBSTITUTE(INDEX($J$9:$J$2008,$W53),",",""))),"")) | AI53: =IF($W53="","",IFERROR(IF(ISNUMBER(INDEX($K$9:$K$2008,$W53)),INDEX($K$9:$K$2008,$W53),VALUE(SUBSTITUTE(INDEX($K$9:$K$2008,$W53),",",""))),"")) | AJ53: =IF($W53="","",IFERROR(IF(ISNUMBER(INDEX($L$9:$L$2008,$W53)),INDEX($L$9:$L$2008,$W53),VALUE(SUBSTITUTE(INDEX($L$9:$L$2008,$W53),",",""))),"")) | AK53: =IF($W53="","",IFERROR(IF(ISNUMBER(INDEX($M$9:$M$2008,$W53)),INDEX($M$9:$M$2008,$W53),VALUE(SUBSTITUTE(INDEX($M$9:$M$2008,$W53),",",""))),"")) | AL53: =IF($W53="","",IFERROR(IF(ISNUMBER(INDEX($P$9:$P$2008,$W53)),INDEX($P$9:$P$2008,$W53),VALUE(SUBSTITUTE(INDEX($P$9:$P$2008,$W53),"%",""))/100),""))
S54: =IF(AND(ISTEXT($A54),ISNUMBER(SEARCH(" - ",$A54)),ISERROR(SEARCH("Folio",$A54)),$D54=""),TRIM($A54),$S53) | T54: =IF(AND(ISNUMBER(SEARCH("Folio",$A54)),$D54<>""),1,"") | U54: =IF($T54=1,COUNTIF($T$9:$T54,1),"") | V54: =IF(AND(ISTEXT($A54),LEFT($A55,3)="Pan"),1,"") | W54: =IFERROR(MATCH(46,$U$9:$U$2008,0),"") | X54: =IF($W54="","",IF($R$5<>"",$R$5,$R$6)) | Y54: =IF($W54="","",INDEX($S$9:$S$2008,$W54)) | Z54: =IF($W54="","",IFERROR(TRIM(LEFT(SUBSTITUTE(INDEX($A$9:$A$2008,$W54),CHAR(10)," "),SEARCH("Folio",SUBSTITUTE(INDEX($A$9:$A$2008,$W54),CHAR(10)," "))-1)),TRIM(SUBSTITUTE(INDEX($A$9:$A$2008,$W54),CHAR(10)," ")))) | AA54: =IF($W54="","",IFERROR(TRIM(SUBSTITUTE(MID(SUBSTITUTE(INDEX($A$9:$A$2008,$W54),CHAR(10)," "),SEARCH("Folio",SUBSTITUTE(INDEX($A$9:$A$2008,$W54),CHAR(10)," "))+5,200),":","")),"")) | AB54: =IF($W54="","",IF(ISNUMBER(INDEX($D$9:$D$2008,$W54)),INDEX($D$9:$D$2008,$W54),IFERROR(DATE(2000+VALUE(RIGHT(INDEX($D$9:$D$2008,$W54),2)),VALUE(MID(INDEX($D$9:$D$2008,$W54),4,2)),VALUE(LEFT(INDEX($D$9:$D$2008,$W54),2))),""))) | AC54: =IF($W54="","",IFERROR(IF(ISNUMBER(INDEX($E$9:$E$2008,$W54)),INDEX($E$9:$E$2008,$W54),VALUE(SUBSTITUTE(INDEX($E$9:$E$2008,$W54),",",""))),"")) | AD54: =IF($W54="","",IFERROR(IF(ISNUMBER(INDEX($F$9:$F$2008,$W54)),INDEX($F$9:$F$2008,$W54),VALUE(SUBSTITUTE(INDEX($F$9:$F$2008,$W54),",",""))),"")) | AE54: =IF($W54="","",IFERROR(IF(ISNUMBER(INDEX($G$9:$G$2008,$W54)),INDEX($G$9:$G$2008,$W54),VALUE(SUBSTITUTE(INDEX($G$9:$G$2008,$W54),",",""))),"")) | AF54: =IF($W54="","",IFERROR(IF(ISNUMBER(INDEX($H$9:$H$2008,$W54)),INDEX($H$9:$H$2008,$W54),VALUE(SUBSTITUTE(INDEX($H$9:$H$2008,$W54),",",""))),"")) | AG54: =IF($W54="","",IFERROR(IF(ISNUMBER(INDEX($I$9:$I$2008,$W54)),INDEX($I$9:$I$2008,$W54),VALUE(SUBSTITUTE(INDEX($I$9:$I$2008,$W54),",",""))),"")) | AH54: =IF($W54="","",IFERROR(IF(ISNUMBER(INDEX($J$9:$J$2008,$W54)),INDEX($J$9:$J$2008,$W54),VALUE(SUBSTITUTE(INDEX($J$9:$J$2008,$W54),",",""))),"")) | AI54: =IF($W54="","",IFERROR(IF(ISNUMBER(INDEX($K$9:$K$2008,$W54)),INDEX($K$9:$K$2008,$W54),VALUE(SUBSTITUTE(INDEX($K$9:$K$2008,$W54),",",""))),"")) | AJ54: =IF($W54="","",IFERROR(IF(ISNUMBER(INDEX($L$9:$L$2008,$W54)),INDEX($L$9:$L$2008,$W54),VALUE(SUBSTITUTE(INDEX($L$9:$L$2008,$W54),",",""))),"")) | AK54: =IF($W54="","",IFERROR(IF(ISNUMBER(INDEX($M$9:$M$2008,$W54)),INDEX($M$9:$M$2008,$W54),VALUE(SUBSTITUTE(INDEX($M$9:$M$2008,$W54),",",""))),"")) | AL54: =IF($W54="","",IFERROR(IF(ISNUMBER(INDEX($P$9:$P$2008,$W54)),INDEX($P$9:$P$2008,$W54),VALUE(SUBSTITUTE(INDEX($P$9:$P$2008,$W54),"%",""))/100),""))
S55: =IF(AND(ISTEXT($A55),ISNUMBER(SEARCH(" - ",$A55)),ISERROR(SEARCH("Folio",$A55)),$D55=""),TRIM($A55),$S54) | T55: =IF(AND(ISNUMBER(SEARCH("Folio",$A55)),$D55<>""),1,"") | U55: =IF($T55=1,COUNTIF($T$9:$T55,1),"") | V55: =IF(AND(ISTEXT($A55),LEFT($A56,3)="Pan"),1,"") | W55: =IFERROR(MATCH(47,$U$9:$U$2008,0),"") | X55: =IF($W55="","",IF($R$5<>"",$R$5,$R$6)) | Y55: =IF($W55="","",INDEX($S$9:$S$2008,$W55)) | Z55: =IF($W55="","",IFERROR(TRIM(LEFT(SUBSTITUTE(INDEX($A$9:$A$2008,$W55),CHAR(10)," "),SEARCH("Folio",SUBSTITUTE(INDEX($A$9:$A$2008,$W55),CHAR(10)," "))-1)),TRIM(SUBSTITUTE(INDEX($A$9:$A$2008,$W55),CHAR(10)," ")))) | AA55: =IF($W55="","",IFERROR(TRIM(SUBSTITUTE(MID(SUBSTITUTE(INDEX($A$9:$A$2008,$W55),CHAR(10)," "),SEARCH("Folio",SUBSTITUTE(INDEX($A$9:$A$2008,$W55),CHAR(10)," "))+5,200),":","")),"")) | AB55: =IF($W55="","",IF(ISNUMBER(INDEX($D$9:$D$2008,$W55)),INDEX($D$9:$D$2008,$W55),IFERROR(DATE(2000+VALUE(RIGHT(INDEX($D$9:$D$2008,$W55),2)),VALUE(MID(INDEX($D$9:$D$2008,$W55),4,2)),VALUE(LEFT(INDEX($D$9:$D$2008,$W55),2))),""))) | AC55: =IF($W55="","",IFERROR(IF(ISNUMBER(INDEX($E$9:$E$2008,$W55)),INDEX($E$9:$E$2008,$W55),VALUE(SUBSTITUTE(INDEX($E$9:$E$2008,$W55),",",""))),"")) | AD55: =IF($W55="","",IFERROR(IF(ISNUMBER(INDEX($F$9:$F$2008,$W55)),INDEX($F$9:$F$2008,$W55),VALUE(SUBSTITUTE(INDEX($F$9:$F$2008,$W55),",",""))),"")) | AE55: =IF($W55="","",IFERROR(IF(ISNUMBER(INDEX($G$9:$G$2008,$W55)),INDEX($G$9:$G$2008,$W55),VALUE(SUBSTITUTE(INDEX($G$9:$G$2008,$W55),",",""))),"")) | AF55: =IF($W55="","",IFERROR(IF(ISNUMBER(INDEX($H$9:$H$2008,$W55)),INDEX($H$9:$H$2008,$W55),VALUE(SUBSTITUTE(INDEX($H$9:$H$2008,$W55),",",""))),"")) | AG55: =IF($W55="","",IFERROR(IF(ISNUMBER(INDEX($I$9:$I$2008,$W55)),INDEX($I$9:$I$2008,$W55),VALUE(SUBSTITUTE(INDEX($I$9:$I$2008,$W55),",",""))),"")) | AH55: =IF($W55="","",IFERROR(IF(ISNUMBER(INDEX($J$9:$J$2008,$W55)),INDEX($J$9:$J$2008,$W55),VALUE(SUBSTITUTE(INDEX($J$9:$J$2008,$W55),",",""))),"")) | AI55: =IF($W55="","",IFERROR(IF(ISNUMBER(INDEX($K$9:$K$2008,$W55)),INDEX($K$9:$K$2008,$W55),VALUE(SUBSTITUTE(INDEX($K$9:$K$2008,$W55),",",""))),"")) | AJ55: =IF($W55="","",IFERROR(IF(ISNUMBER(INDEX($L$9:$L$2008,$W55)),INDEX($L$9:$L$2008,$W55),VALUE(SUBSTITUTE(INDEX($L$9:$L$2008,$W55),",",""))),"")) | AK55: =IF($W55="","",IFERROR(IF(ISNUMBER(INDEX($M$9:$M$2008,$W55)),INDEX($M$9:$M$2008,$W55),VALUE(SUBSTITUTE(INDEX($M$9:$M$2008,$W55),",",""))),"")) | AL55: =IF($W55="","",IFERROR(IF(ISNUMBER(INDEX($P$9:$P$2008,$W55)),INDEX($P$9:$P$2008,$W55),VALUE(SUBSTITUTE(INDEX($P$9:$P$2008,$W55),"%",""))/100),""))
S56: =IF(AND(ISTEXT($A56),ISNUMBER(SEARCH(" - ",$A56)),ISERROR(SEARCH("Folio",$A56)),$D56=""),TRIM($A56),$S55) | T56: =IF(AND(ISNUMBER(SEARCH("Folio",$A56)),$D56<>""),1,"") | U56: =IF($T56=1,COUNTIF($T$9:$T56,1),"") | V56: =IF(AND(ISTEXT($A56),LEFT($A57,3)="Pan"),1,"") | W56: =IFERROR(MATCH(48,$U$9:$U$2008,0),"") | X56: =IF($W56="","",IF($R$5<>"",$R$5,$R$6)) | Y56: =IF($W56="","",INDEX($S$9:$S$2008,$W56)) | Z56: =IF($W56="","",IFERROR(TRIM(LEFT(SUBSTITUTE(INDEX($A$9:$A$2008,$W56),CHAR(10)," "),SEARCH("Folio",SUBSTITUTE(INDEX($A$9:$A$2008,$W56),CHAR(10)," "))-1)),TRIM(SUBSTITUTE(INDEX($A$9:$A$2008,$W56),CHAR(10)," ")))) | AA56: =IF($W56="","",IFERROR(TRIM(SUBSTITUTE(MID(SUBSTITUTE(INDEX($A$9:$A$2008,$W56),CHAR(10)," "),SEARCH("Folio",SUBSTITUTE(INDEX($A$9:$A$2008,$W56),CHAR(10)," "))+5,200),":","")),"")) | AB56: =IF($W56="","",IF(ISNUMBER(INDEX($D$9:$D$2008,$W56)),INDEX($D$9:$D$2008,$W56),IFERROR(DATE(2000+VALUE(RIGHT(INDEX($D$9:$D$2008,$W56),2)),VALUE(MID(INDEX($D$9:$D$2008,$W56),4,2)),VALUE(LEFT(INDEX($D$9:$D$2008,$W56),2))),""))) | AC56: =IF($W56="","",IFERROR(IF(ISNUMBER(INDEX($E$9:$E$2008,$W56)),INDEX($E$9:$E$2008,$W56),VALUE(SUBSTITUTE(INDEX($E$9:$E$2008,$W56),",",""))),"")) | AD56: =IF($W56="","",IFERROR(IF(ISNUMBER(INDEX($F$9:$F$2008,$W56)),INDEX($F$9:$F$2008,$W56),VALUE(SUBSTITUTE(INDEX($F$9:$F$2008,$W56),",",""))),"")) | AE56: =IF($W56="","",IFERROR(IF(ISNUMBER(INDEX($G$9:$G$2008,$W56)),INDEX($G$9:$G$2008,$W56),VALUE(SUBSTITUTE(INDEX($G$9:$G$2008,$W56),",",""))),"")) | AF56: =IF($W56="","",IFERROR(IF(ISNUMBER(INDEX($H$9:$H$2008,$W56)),INDEX($H$9:$H$2008,$W56),VALUE(SUBSTITUTE(INDEX($H$9:$H$2008,$W56),",",""))),"")) | AG56: =IF($W56="","",IFERROR(IF(ISNUMBER(INDEX($I$9:$I$2008,$W56)),INDEX($I$9:$I$2008,$W56),VALUE(SUBSTITUTE(INDEX($I$9:$I$2008,$W56),",",""))),"")) | AH56: =IF($W56="","",IFERROR(IF(ISNUMBER(INDEX($J$9:$J$2008,$W56)),INDEX($J$9:$J$2008,$W56),VALUE(SUBSTITUTE(INDEX($J$9:$J$2008,$W56),",",""))),"")) | AI56: =IF($W56="","",IFERROR(IF(ISNUMBER(INDEX($K$9:$K$2008,$W56)),INDEX($K$9:$K$2008,$W56),VALUE(SUBSTITUTE(INDEX($K$9:$K$2008,$W56),",",""))),"")) | AJ56: =IF($W56="","",IFERROR(IF(ISNUMBER(INDEX($L$9:$L$2008,$W56)),INDEX($L$9:$L$2008,$W56),VALUE(SUBSTITUTE(INDEX($L$9:$L$2008,$W56),",",""))),"")) | AK56: =IF($W56="","",IFERROR(IF(ISNUMBER(INDEX($M$9:$M$2008,$W56)),INDEX($M$9:$M$2008,$W56),VALUE(SUBSTITUTE(INDEX($M$9:$M$2008,$W56),",",""))),"")) | AL56: =IF($W56="","",IFERROR(IF(ISNUMBER(INDEX($P$9:$P$2008,$W56)),INDEX($P$9:$P$2008,$W56),VALUE(SUBSTITUTE(INDEX($P$9:$P$2008,$W56),"%",""))/100),""))
S57: =IF(AND(ISTEXT($A57),ISNUMBER(SEARCH(" - ",$A57)),ISERROR(SEARCH("Folio",$A57)),$D57=""),TRIM($A57),$S56) | T57: =IF(AND(ISNUMBER(SEARCH("Folio",$A57)),$D57<>""),1,"") | U57: =IF($T57=1,COUNTIF($T$9:$T57,1),"") | V57: =IF(AND(ISTEXT($A57),LEFT($A58,3)="Pan"),1,"") | W57: =IFERROR(MATCH(49,$U$9:$U$2008,0),"") | X57: =IF($W57="","",IF($R$5<>"",$R$5,$R$6)) | Y57: =IF($W57="","",INDEX($S$9:$S$2008,$W57)) | Z57: =IF($W57="","",IFERROR(TRIM(LEFT(SUBSTITUTE(INDEX($A$9:$A$2008,$W57),CHAR(10)," "),SEARCH("Folio",SUBSTITUTE(INDEX($A$9:$A$2008,$W57),CHAR(10)," "))-1)),TRIM(SUBSTITUTE(INDEX($A$9:$A$2008,$W57),CHAR(10)," ")))) | AA57: =IF($W57="","",IFERROR(TRIM(SUBSTITUTE(MID(SUBSTITUTE(INDEX($A$9:$A$2008,$W57),CHAR(10)," "),SEARCH("Folio",SUBSTITUTE(INDEX($A$9:$A$2008,$W57),CHAR(10)," "))+5,200),":","")),"")) | AB57: =IF($W57="","",IF(ISNUMBER(INDEX($D$9:$D$2008,$W57)),INDEX($D$9:$D$2008,$W57),IFERROR(DATE(2000+VALUE(RIGHT(INDEX($D$9:$D$2008,$W57),2)),VALUE(MID(INDEX($D$9:$D$2008,$W57),4,2)),VALUE(LEFT(INDEX($D$9:$D$2008,$W57),2))),""))) | AC57: =IF($W57="","",IFERROR(IF(ISNUMBER(INDEX($E$9:$E$2008,$W57)),INDEX($E$9:$E$2008,$W57),VALUE(SUBSTITUTE(INDEX($E$9:$E$2008,$W57),",",""))),"")) | AD57: =IF($W57="","",IFERROR(IF(ISNUMBER(INDEX($F$9:$F$2008,$W57)),INDEX($F$9:$F$2008,$W57),VALUE(SUBSTITUTE(INDEX($F$9:$F$2008,$W57),",",""))),"")) | AE57: =IF($W57="","",IFERROR(IF(ISNUMBER(INDEX($G$9:$G$2008,$W57)),INDEX($G$9:$G$2008,$W57),VALUE(SUBSTITUTE(INDEX($G$9:$G$2008,$W57),",",""))),"")) | AF57: =IF($W57="","",IFERROR(IF(ISNUMBER(INDEX($H$9:$H$2008,$W57)),INDEX($H$9:$H$2008,$W57),VALUE(SUBSTITUTE(INDEX($H$9:$H$2008,$W57),",",""))),"")) | AG57: =IF($W57="","",IFERROR(IF(ISNUMBER(INDEX($I$9:$I$2008,$W57)),INDEX($I$9:$I$2008,$W57),VALUE(SUBSTITUTE(INDEX($I$9:$I$2008,$W57),",",""))),"")) | AH57: =IF($W57="","",IFERROR(IF(ISNUMBER(INDEX($J$9:$J$2008,$W57)),INDEX($J$9:$J$2008,$W57),VALUE(SUBSTITUTE(INDEX($J$9:$J$2008,$W57),",",""))),"")) | AI57: =IF($W57="","",IFERROR(IF(ISNUMBER(INDEX($K$9:$K$2008,$W57)),INDEX($K$9:$K$2008,$W57),VALUE(SUBSTITUTE(INDEX($K$9:$K$2008,$W57),",",""))),"")) | AJ57: =IF($W57="","",IFERROR(IF(ISNUMBER(INDEX($L$9:$L$2008,$W57)),INDEX($L$9:$L$2008,$W57),VALUE(SUBSTITUTE(INDEX($L$9:$L$2008,$W57),",",""))),"")) | AK57: =IF($W57="","",IFERROR(IF(ISNUMBER(INDEX($M$9:$M$2008,$W57)),INDEX($M$9:$M$2008,$W57),VALUE(SUBSTITUTE(INDEX($M$9:$M$2008,$W57),",",""))),"")) | AL57: =IF($W57="","",IFERROR(IF(ISNUMBER(INDEX($P$9:$P$2008,$W57)),INDEX($P$9:$P$2008,$W57),VALUE(SUBSTITUTE(INDEX($P$9:$P$2008,$W57),"%",""))/100),""))
S58: =IF(AND(ISTEXT($A58),ISNUMBER(SEARCH(" - ",$A58)),ISERROR(SEARCH("Folio",$A58)),$D58=""),TRIM($A58),$S57) | T58: =IF(AND(ISNUMBER(SEARCH("Folio",$A58)),$D58<>""),1,"") | U58: =IF($T58=1,COUNTIF($T$9:$T58,1),"") | V58: =IF(AND(ISTEXT($A58),LEFT($A59,3)="Pan"),1,"") | W58: =IFERROR(MATCH(50,$U$9:$U$2008,0),"") | X58: =IF($W58="","",IF($R$5<>"",$R$5,$R$6)) | Y58: =IF($W58="","",INDEX($S$9:$S$2008,$W58)) | Z58: =IF($W58="","",IFERROR(TRIM(LEFT(SUBSTITUTE(INDEX($A$9:$A$2008,$W58),CHAR(10)," "),SEARCH("Folio",SUBSTITUTE(INDEX($A$9:$A$2008,$W58),CHAR(10)," "))-1)),TRIM(SUBSTITUTE(INDEX($A$9:$A$2008,$W58),CHAR(10)," ")))) | AA58: =IF($W58="","",IFERROR(TRIM(SUBSTITUTE(MID(SUBSTITUTE(INDEX($A$9:$A$2008,$W58),CHAR(10)," "),SEARCH("Folio",SUBSTITUTE(INDEX($A$9:$A$2008,$W58),CHAR(10)," "))+5,200),":","")),"")) | AB58: =IF($W58="","",IF(ISNUMBER(INDEX($D$9:$D$2008,$W58)),INDEX($D$9:$D$2008,$W58),IFERROR(DATE(2000+VALUE(RIGHT(INDEX($D$9:$D$2008,$W58),2)),VALUE(MID(INDEX($D$9:$D$2008,$W58),4,2)),VALUE(LEFT(INDEX($D$9:$D$2008,$W58),2))),""))) | AC58: =IF($W58="","",IFERROR(IF(ISNUMBER(INDEX($E$9:$E$2008,$W58)),INDEX($E$9:$E$2008,$W58),VALUE(SUBSTITUTE(INDEX($E$9:$E$2008,$W58),",",""))),"")) | AD58: =IF($W58="","",IFERROR(IF(ISNUMBER(INDEX($F$9:$F$2008,$W58)),INDEX($F$9:$F$2008,$W58),VALUE(SUBSTITUTE(INDEX($F$9:$F$2008,$W58),",",""))),"")) | AE58: =IF($W58="","",IFERROR(IF(ISNUMBER(INDEX($G$9:$G$2008,$W58)),INDEX($G$9:$G$2008,$W58),VALUE(SUBSTITUTE(INDEX($G$9:$G$2008,$W58),",",""))),"")) | AF58: =IF($W58="","",IFERROR(IF(ISNUMBER(INDEX($H$9:$H$2008,$W58)),INDEX($H$9:$H$2008,$W58),VALUE(SUBSTITUTE(INDEX($H$9:$H$2008,$W58),",",""))),"")) | AG58: =IF($W58="","",IFERROR(IF(ISNUMBER(INDEX($I$9:$I$2008,$W58)),INDEX($I$9:$I$2008,$W58),VALUE(SUBSTITUTE(INDEX($I$9:$I$2008,$W58),",",""))),"")) | AH58: =IF($W58="","",IFERROR(IF(ISNUMBER(INDEX($J$9:$J$2008,$W58)),INDEX($J$9:$J$2008,$W58),VALUE(SUBSTITUTE(INDEX($J$9:$J$2008,$W58),",",""))),"")) | AI58: =IF($W58="","",IFERROR(IF(ISNUMBER(INDEX($K$9:$K$2008,$W58)),INDEX($K$9:$K$2008,$W58),VALUE(SUBSTITUTE(INDEX($K$9:$K$2008,$W58),",",""))),"")) | AJ58: =IF($W58="","",IFERROR(IF(ISNUMBER(INDEX($L$9:$L$2008,$W58)),INDEX($L$9:$L$2008,$W58),VALUE(SUBSTITUTE(INDEX($L$9:$L$2008,$W58),",",""))),"")) | AK58: =IF($W58="","",IFERROR(IF(ISNUMBER(INDEX($M$9:$M$2008,$W58)),INDEX($M$9:$M$2008,$W58),VALUE(SUBSTITUTE(INDEX($M$9:$M$2008,$W58),",",""))),"")) | AL58: =IF($W58="","",IFERROR(IF(ISNUMBER(INDEX($P$9:$P$2008,$W58)),INDEX($P$9:$P$2008,$W58),VALUE(SUBSTITUTE(INDEX($P$9:$P$2008,$W58),"%",""))/100),""))
S59: =IF(AND(ISTEXT($A59),ISNUMBER(SEARCH(" - ",$A59)),ISERROR(SEARCH("Folio",$A59)),$D59=""),TRIM($A59),$S58) | T59: =IF(AND(ISNUMBER(SEARCH("Folio",$A59)),$D59<>""),1,"") | U59: =IF($T59=1,COUNTIF($T$9:$T59,1),"") | V59: =IF(AND(ISTEXT($A59),LEFT($A60,3)="Pan"),1,"") | W59: =IFERROR(MATCH(51,$U$9:$U$2008,0),"") | X59: =IF($W59="","",IF($R$5<>"",$R$5,$R$6)) | Y59: =IF($W59="","",INDEX($S$9:$S$2008,$W59)) | Z59: =IF($W59="","",IFERROR(TRIM(LEFT(SUBSTITUTE(INDEX($A$9:$A$2008,$W59),CHAR(10)," "),SEARCH("Folio",SUBSTITUTE(INDEX($A$9:$A$2008,$W59),CHAR(10)," "))-1)),TRIM(SUBSTITUTE(INDEX($A$9:$A$2008,$W59),CHAR(10)," ")))) | AA59: =IF($W59="","",IFERROR(TRIM(SUBSTITUTE(MID(SUBSTITUTE(INDEX($A$9:$A$2008,$W59),CHAR(10)," "),SEARCH("Folio",SUBSTITUTE(INDEX($A$9:$A$2008,$W59),CHAR(10)," "))+5,200),":","")),"")) | AB59: =IF($W59="","",IF(ISNUMBER(INDEX($D$9:$D$2008,$W59)),INDEX($D$9:$D$2008,$W59),IFERROR(DATE(2000+VALUE(RIGHT(INDEX($D$9:$D$2008,$W59),2)),VALUE(MID(INDEX($D$9:$D$2008,$W59),4,2)),VALUE(LEFT(INDEX($D$9:$D$2008,$W59),2))),""))) | AC59: =IF($W59="","",IFERROR(IF(ISNUMBER(INDEX($E$9:$E$2008,$W59)),INDEX($E$9:$E$2008,$W59),VALUE(SUBSTITUTE(INDEX($E$9:$E$2008,$W59),",",""))),"")) | AD59: =IF($W59="","",IFERROR(IF(ISNUMBER(INDEX($F$9:$F$2008,$W59)),INDEX($F$9:$F$2008,$W59),VALUE(SUBSTITUTE(INDEX($F$9:$F$2008,$W59),",",""))),"")) | AE59: =IF($W59="","",IFERROR(IF(ISNUMBER(INDEX($G$9:$G$2008,$W59)),INDEX($G$9:$G$2008,$W59),VALUE(SUBSTITUTE(INDEX($G$9:$G$2008,$W59),",",""))),"")) | AF59: =IF($W59="","",IFERROR(IF(ISNUMBER(INDEX($H$9:$H$2008,$W59)),INDEX($H$9:$H$2008,$W59),VALUE(SUBSTITUTE(INDEX($H$9:$H$2008,$W59),",",""))),"")) | AG59: =IF($W59="","",IFERROR(IF(ISNUMBER(INDEX($I$9:$I$2008,$W59)),INDEX($I$9:$I$2008,$W59),VALUE(SUBSTITUTE(INDEX($I$9:$I$2008,$W59),",",""))),"")) | AH59: =IF($W59="","",IFERROR(IF(ISNUMBER(INDEX($J$9:$J$2008,$W59)),INDEX($J$9:$J$2008,$W59),VALUE(SUBSTITUTE(INDEX($J$9:$J$2008,$W59),",",""))),"")) | AI59: =IF($W59="","",IFERROR(IF(ISNUMBER(INDEX($K$9:$K$2008,$W59)),INDEX($K$9:$K$2008,$W59),VALUE(SUBSTITUTE(INDEX($K$9:$K$2008,$W59),",",""))),"")) | AJ59: =IF($W59="","",IFERROR(IF(ISNUMBER(INDEX($L$9:$L$2008,$W59)),INDEX($L$9:$L$2008,$W59),VALUE(SUBSTITUTE(INDEX($L$9:$L$2008,$W59),",",""))),"")) | AK59: =IF($W59="","",IFERROR(IF(ISNUMBER(INDEX($M$9:$M$2008,$W59)),INDEX($M$9:$M$2008,$W59),VALUE(SUBSTITUTE(INDEX($M$9:$M$2008,$W59),",",""))),"")) | AL59: =IF($W59="","",IFERROR(IF(ISNUMBER(INDEX($P$9:$P$2008,$W59)),INDEX($P$9:$P$2008,$W59),VALUE(SUBSTITUTE(INDEX($P$9:$P$2008,$W59),"%",""))/100),""))
S60: =IF(AND(ISTEXT($A60),ISNUMBER(SEARCH(" - ",$A60)),ISERROR(SEARCH("Folio",$A60)),$D60=""),TRIM($A60),$S59) | T60: =IF(AND(ISNUMBER(SEARCH("Folio",$A60)),$D60<>""),1,"") | U60: =IF($T60=1,COUNTIF($T$9:$T60,1),"") | V60: =IF(AND(ISTEXT($A60),LEFT($A61,3)="Pan"),1,"") | W60: =IFERROR(MATCH(52,$U$9:$U$2008,0),"") | X60: =IF($W60="","",IF($R$5<>"",$R$5,$R$6)) | Y60: =IF($W60="","",INDEX($S$9:$S$2008,$W60)) | Z60: =IF($W60="","",IFERROR(TRIM(LEFT(SUBSTITUTE(INDEX($A$9:$A$2008,$W60),CHAR(10)," "),SEARCH("Folio",SUBSTITUTE(INDEX($A$9:$A$2008,$W60),CHAR(10)," "))-1)),TRIM(SUBSTITUTE(INDEX($A$9:$A$2008,$W60),CHAR(10)," ")))) | AA60: =IF($W60="","",IFERROR(TRIM(SUBSTITUTE(MID(SUBSTITUTE(INDEX($A$9:$A$2008,$W60),CHAR(10)," "),SEARCH("Folio",SUBSTITUTE(INDEX($A$9:$A$2008,$W60),CHAR(10)," "))+5,200),":","")),"")) | AB60: =IF($W60="","",IF(ISNUMBER(INDEX($D$9:$D$2008,$W60)),INDEX($D$9:$D$2008,$W60),IFERROR(DATE(2000+VALUE(RIGHT(INDEX($D$9:$D$2008,$W60),2)),VALUE(MID(INDEX($D$9:$D$2008,$W60),4,2)),VALUE(LEFT(INDEX($D$9:$D$2008,$W60),2))),""))) | AC60: =IF($W60="","",IFERROR(IF(ISNUMBER(INDEX($E$9:$E$2008,$W60)),INDEX($E$9:$E$2008,$W60),VALUE(SUBSTITUTE(INDEX($E$9:$E$2008,$W60),",",""))),"")) | AD60: =IF($W60="","",IFERROR(IF(ISNUMBER(INDEX($F$9:$F$2008,$W60)),INDEX($F$9:$F$2008,$W60),VALUE(SUBSTITUTE(INDEX($F$9:$F$2008,$W60),",",""))),"")) | AE60: =IF($W60="","",IFERROR(IF(ISNUMBER(INDEX($G$9:$G$2008,$W60)),INDEX($G$9:$G$2008,$W60),VALUE(SUBSTITUTE(INDEX($G$9:$G$2008,$W60),",",""))),"")) | AF60: =IF($W60="","",IFERROR(IF(ISNUMBER(INDEX($H$9:$H$2008,$W60)),INDEX($H$9:$H$2008,$W60),VALUE(SUBSTITUTE(INDEX($H$9:$H$2008,$W60),",",""))),"")) | AG60: =IF($W60="","",IFERROR(IF(ISNUMBER(INDEX($I$9:$I$2008,$W60)),INDEX($I$9:$I$2008,$W60),VALUE(SUBSTITUTE(INDEX($I$9:$I$2008,$W60),",",""))),"")) | AH60: =IF($W60="","",IFERROR(IF(ISNUMBER(INDEX($J$9:$J$2008,$W60)),INDEX($J$9:$J$2008,$W60),VALUE(SUBSTITUTE(INDEX($J$9:$J$2008,$W60),",",""))),"")) | AI60: =IF($W60="","",IFERROR(IF(ISNUMBER(INDEX($K$9:$K$2008,$W60)),INDEX($K$9:$K$2008,$W60),VALUE(SUBSTITUTE(INDEX($K$9:$K$2008,$W60),",",""))),"")) | AJ60: =IF($W60="","",IFERROR(IF(ISNUMBER(INDEX($L$9:$L$2008,$W60)),INDEX($L$9:$L$2008,$W60),VALUE(SUBSTITUTE(INDEX($L$9:$L$2008,$W60),",",""))),"")) | AK60: =IF($W60="","",IFERROR(IF(ISNUMBER(INDEX($M$9:$M$2008,$W60)),INDEX($M$9:$M$2008,$W60),VALUE(SUBSTITUTE(INDEX($M$9:$M$2008,$W60),",",""))),"")) | AL60: =IF($W60="","",IFERROR(IF(ISNUMBER(INDEX($P$9:$P$2008,$W60)),INDEX($P$9:$P$2008,$W60),VALUE(SUBSTITUTE(INDEX($P$9:$P$2008,$W60),"%",""))/100),""))
S61: =IF(AND(ISTEXT($A61),ISNUMBER(SEARCH(" - ",$A61)),ISERROR(SEARCH("Folio",$A61)),$D61=""),TRIM($A61),$S60) | T61: =IF(AND(ISNUMBER(SEARCH("Folio",$A61)),$D61<>""),1,"") | U61: =IF($T61=1,COUNTIF($T$9:$T61,1),"") | V61: =IF(AND(ISTEXT($A61),LEFT($A62,3)="Pan"),1,"") | W61: =IFERROR(MATCH(53,$U$9:$U$2008,0),"") | X61: =IF($W61="","",IF($R$5<>"",$R$5,$R$6)) | Y61: =IF($W61="","",INDEX($S$9:$S$2008,$W61)) | Z61: =IF($W61="","",IFERROR(TRIM(LEFT(SUBSTITUTE(INDEX($A$9:$A$2008,$W61),CHAR(10)," "),SEARCH("Folio",SUBSTITUTE(INDEX($A$9:$A$2008,$W61),CHAR(10)," "))-1)),TRIM(SUBSTITUTE(INDEX($A$9:$A$2008,$W61),CHAR(10)," ")))) | AA61: =IF($W61="","",IFERROR(TRIM(SUBSTITUTE(MID(SUBSTITUTE(INDEX($A$9:$A$2008,$W61),CHAR(10)," "),SEARCH("Folio",SUBSTITUTE(INDEX($A$9:$A$2008,$W61),CHAR(10)," "))+5,200),":","")),"")) | AB61: =IF($W61="","",IF(ISNUMBER(INDEX($D$9:$D$2008,$W61)),INDEX($D$9:$D$2008,$W61),IFERROR(DATE(2000+VALUE(RIGHT(INDEX($D$9:$D$2008,$W61),2)),VALUE(MID(INDEX($D$9:$D$2008,$W61),4,2)),VALUE(LEFT(INDEX($D$9:$D$2008,$W61),2))),""))) | AC61: =IF($W61="","",IFERROR(IF(ISNUMBER(INDEX($E$9:$E$2008,$W61)),INDEX($E$9:$E$2008,$W61),VALUE(SUBSTITUTE(INDEX($E$9:$E$2008,$W61),",",""))),"")) | AD61: =IF($W61="","",IFERROR(IF(ISNUMBER(INDEX($F$9:$F$2008,$W61)),INDEX($F$9:$F$2008,$W61),VALUE(SUBSTITUTE(INDEX($F$9:$F$2008,$W61),",",""))),"")) | AE61: =IF($W61="","",IFERROR(IF(ISNUMBER(INDEX($G$9:$G$2008,$W61)),INDEX($G$9:$G$2008,$W61),VALUE(SUBSTITUTE(INDEX($G$9:$G$2008,$W61),",",""))),"")) | AF61: =IF($W61="","",IFERROR(IF(ISNUMBER(INDEX($H$9:$H$2008,$W61)),INDEX($H$9:$H$2008,$W61),VALUE(SUBSTITUTE(INDEX($H$9:$H$2008,$W61),",",""))),"")) | AG61: =IF($W61="","",IFERROR(IF(ISNUMBER(INDEX($I$9:$I$2008,$W61)),INDEX($I$9:$I$2008,$W61),VALUE(SUBSTITUTE(INDEX($I$9:$I$2008,$W61),",",""))),"")) | AH61: =IF($W61="","",IFERROR(IF(ISNUMBER(INDEX($J$9:$J$2008,$W61)),INDEX($J$9:$J$2008,$W61),VALUE(SUBSTITUTE(INDEX($J$9:$J$2008,$W61),",",""))),"")) | AI61: =IF($W61="","",IFERROR(IF(ISNUMBER(INDEX($K$9:$K$2008,$W61)),INDEX($K$9:$K$2008,$W61),VALUE(SUBSTITUTE(INDEX($K$9:$K$2008,$W61),",",""))),"")) | AJ61: =IF($W61="","",IFERROR(IF(ISNUMBER(INDEX($L$9:$L$2008,$W61)),INDEX($L$9:$L$2008,$W61),VALUE(SUBSTITUTE(INDEX($L$9:$L$2008,$W61),",",""))),"")) | AK61: =IF($W61="","",IFERROR(IF(ISNUMBER(INDEX($M$9:$M$2008,$W61)),INDEX($M$9:$M$2008,$W61),VALUE(SUBSTITUTE(INDEX($M$9:$M$2008,$W61),",",""))),"")) | AL61: =IF($W61="","",IFERROR(IF(ISNUMBER(INDEX($P$9:$P$2008,$W61)),INDEX($P$9:$P$2008,$W61),VALUE(SUBSTITUTE(INDEX($P$9:$P$2008,$W61),"%",""))/100),""))
S62: =IF(AND(ISTEXT($A62),ISNUMBER(SEARCH(" - ",$A62)),ISERROR(SEARCH("Folio",$A62)),$D62=""),TRIM($A62),$S61) | T62: =IF(AND(ISNUMBER(SEARCH("Folio",$A62)),$D62<>""),1,"") | U62: =IF($T62=1,COUNTIF($T$9:$T62,1),"") | V62: =IF(AND(ISTEXT($A62),LEFT($A63,3)="Pan"),1,"") | W62: =IFERROR(MATCH(54,$U$9:$U$2008,0),"") | X62: =IF($W62="","",IF($R$5<>"",$R$5,$R$6)) | Y62: =IF($W62="","",INDEX($S$9:$S$2008,$W62)) | Z62: =IF($W62="","",IFERROR(TRIM(LEFT(SUBSTITUTE(INDEX($A$9:$A$2008,$W62),CHAR(10)," "),SEARCH("Folio",SUBSTITUTE(INDEX($A$9:$A$2008,$W62),CHAR(10)," "))-1)),TRIM(SUBSTITUTE(INDEX($A$9:$A$2008,$W62),CHAR(10)," ")))) | AA62: =IF($W62="","",IFERROR(TRIM(SUBSTITUTE(MID(SUBSTITUTE(INDEX($A$9:$A$2008,$W62),CHAR(10)," "),SEARCH("Folio",SUBSTITUTE(INDEX($A$9:$A$2008,$W62),CHAR(10)," "))+5,200),":","")),"")) | AB62: =IF($W62="","",IF(ISNUMBER(INDEX($D$9:$D$2008,$W62)),INDEX($D$9:$D$2008,$W62),IFERROR(DATE(2000+VALUE(RIGHT(INDEX($D$9:$D$2008,$W62),2)),VALUE(MID(INDEX($D$9:$D$2008,$W62),4,2)),VALUE(LEFT(INDEX($D$9:$D$2008,$W62),2))),""))) | AC62: =IF($W62="","",IFERROR(IF(ISNUMBER(INDEX($E$9:$E$2008,$W62)),INDEX($E$9:$E$2008,$W62),VALUE(SUBSTITUTE(INDEX($E$9:$E$2008,$W62),",",""))),"")) | AD62: =IF($W62="","",IFERROR(IF(ISNUMBER(INDEX($F$9:$F$2008,$W62)),INDEX($F$9:$F$2008,$W62),VALUE(SUBSTITUTE(INDEX($F$9:$F$2008,$W62),",",""))),"")) | AE62: =IF($W62="","",IFERROR(IF(ISNUMBER(INDEX($G$9:$G$2008,$W62)),INDEX($G$9:$G$2008,$W62),VALUE(SUBSTITUTE(INDEX($G$9:$G$2008,$W62),",",""))),"")) | AF62: =IF($W62="","",IFERROR(IF(ISNUMBER(INDEX($H$9:$H$2008,$W62)),INDEX($H$9:$H$2008,$W62),VALUE(SUBSTITUTE(INDEX($H$9:$H$2008,$W62),",",""))),"")) | AG62: =IF($W62="","",IFERROR(IF(ISNUMBER(INDEX($I$9:$I$2008,$W62)),INDEX($I$9:$I$2008,$W62),VALUE(SUBSTITUTE(INDEX($I$9:$I$2008,$W62),",",""))),"")) | AH62: =IF($W62="","",IFERROR(IF(ISNUMBER(INDEX($J$9:$J$2008,$W62)),INDEX($J$9:$J$2008,$W62),VALUE(SUBSTITUTE(INDEX($J$9:$J$2008,$W62),",",""))),"")) | AI62: =IF($W62="","",IFERROR(IF(ISNUMBER(INDEX($K$9:$K$2008,$W62)),INDEX($K$9:$K$2008,$W62),VALUE(SUBSTITUTE(INDEX($K$9:$K$2008,$W62),",",""))),"")) | AJ62: =IF($W62="","",IFERROR(IF(ISNUMBER(INDEX($L$9:$L$2008,$W62)),INDEX($L$9:$L$2008,$W62),VALUE(SUBSTITUTE(INDEX($L$9:$L$2008,$W62),",",""))),"")) | AK62: =IF($W62="","",IFERROR(IF(ISNUMBER(INDEX($M$9:$M$2008,$W62)),INDEX($M$9:$M$2008,$W62),VALUE(SUBSTITUTE(INDEX($M$9:$M$2008,$W62),",",""))),"")) | AL62: =IF($W62="","",IFERROR(IF(ISNUMBER(INDEX($P$9:$P$2008,$W62)),INDEX($P$9:$P$2008,$W62),VALUE(SUBSTITUTE(INDEX($P$9:$P$2008,$W62),"%",""))/100),""))
S63: =IF(AND(ISTEXT($A63),ISNUMBER(SEARCH(" - ",$A63)),ISERROR(SEARCH("Folio",$A63)),$D63=""),TRIM($A63),$S62) | T63: =IF(AND(ISNUMBER(SEARCH("Folio",$A63)),$D63<>""),1,"") | U63: =IF($T63=1,COUNTIF($T$9:$T63,1),"") | V63: =IF(AND(ISTEXT($A63),LEFT($A64,3)="Pan"),1,"") | W63: =IFERROR(MATCH(55,$U$9:$U$2008,0),"") | X63: =IF($W63="","",IF($R$5<>"",$R$5,$R$6)) | Y63: =IF($W63="","",INDEX($S$9:$S$2008,$W63)) | Z63: =IF($W63="","",IFERROR(TRIM(LEFT(SUBSTITUTE(INDEX($A$9:$A$2008,$W63),CHAR(10)," "),SEARCH("Folio",SUBSTITUTE(INDEX($A$9:$A$2008,$W63),CHAR(10)," "))-1)),TRIM(SUBSTITUTE(INDEX($A$9:$A$2008,$W63),CHAR(10)," ")))) | AA63: =IF($W63="","",IFERROR(TRIM(SUBSTITUTE(MID(SUBSTITUTE(INDEX($A$9:$A$2008,$W63),CHAR(10)," "),SEARCH("Folio",SUBSTITUTE(INDEX($A$9:$A$2008,$W63),CHAR(10)," "))+5,200),":","")),"")) | AB63: =IF($W63="","",IF(ISNUMBER(INDEX($D$9:$D$2008,$W63)),INDEX($D$9:$D$2008,$W63),IFERROR(DATE(2000+VALUE(RIGHT(INDEX($D$9:$D$2008,$W63),2)),VALUE(MID(INDEX($D$9:$D$2008,$W63),4,2)),VALUE(LEFT(INDEX($D$9:$D$2008,$W63),2))),""))) | AC63: =IF($W63="","",IFERROR(IF(ISNUMBER(INDEX($E$9:$E$2008,$W63)),INDEX($E$9:$E$2008,$W63),VALUE(SUBSTITUTE(INDEX($E$9:$E$2008,$W63),",",""))),"")) | AD63: =IF($W63="","",IFERROR(IF(ISNUMBER(INDEX($F$9:$F$2008,$W63)),INDEX($F$9:$F$2008,$W63),VALUE(SUBSTITUTE(INDEX($F$9:$F$2008,$W63),",",""))),"")) | AE63: =IF($W63="","",IFERROR(IF(ISNUMBER(INDEX($G$9:$G$2008,$W63)),INDEX($G$9:$G$2008,$W63),VALUE(SUBSTITUTE(INDEX($G$9:$G$2008,$W63),",",""))),"")) | AF63: =IF($W63="","",IFERROR(IF(ISNUMBER(INDEX($H$9:$H$2008,$W63)),INDEX($H$9:$H$2008,$W63),VALUE(SUBSTITUTE(INDEX($H$9:$H$2008,$W63),",",""))),"")) | AG63: =IF($W63="","",IFERROR(IF(ISNUMBER(INDEX($I$9:$I$2008,$W63)),INDEX($I$9:$I$2008,$W63),VALUE(SUBSTITUTE(INDEX($I$9:$I$2008,$W63),",",""))),"")) | AH63: =IF($W63="","",IFERROR(IF(ISNUMBER(INDEX($J$9:$J$2008,$W63)),INDEX($J$9:$J$2008,$W63),VALUE(SUBSTITUTE(INDEX($J$9:$J$2008,$W63),",",""))),"")) | AI63: =IF($W63="","",IFERROR(IF(ISNUMBER(INDEX($K$9:$K$2008,$W63)),INDEX($K$9:$K$2008,$W63),VALUE(SUBSTITUTE(INDEX($K$9:$K$2008,$W63),",",""))),"")) | AJ63: =IF($W63="","",IFERROR(IF(ISNUMBER(INDEX($L$9:$L$2008,$W63)),INDEX($L$9:$L$2008,$W63),VALUE(SUBSTITUTE(INDEX($L$9:$L$2008,$W63),",",""))),"")) | AK63: =IF($W63="","",IFERROR(IF(ISNUMBER(INDEX($M$9:$M$2008,$W63)),INDEX($M$9:$M$2008,$W63),VALUE(SUBSTITUTE(INDEX($M$9:$M$2008,$W63),",",""))),"")) | AL63: =IF($W63="","",IFERROR(IF(ISNUMBER(INDEX($P$9:$P$2008,$W63)),INDEX($P$9:$P$2008,$W63),VALUE(SUBSTITUTE(INDEX($P$9:$P$2008,$W63),"%",""))/100),""))
S64: =IF(AND(ISTEXT($A64),ISNUMBER(SEARCH(" - ",$A64)),ISERROR(SEARCH("Folio",$A64)),$D64=""),TRIM($A64),$S63) | T64: =IF(AND(ISNUMBER(SEARCH("Folio",$A64)),$D64<>""),1,"") | U64: =IF($T64=1,COUNTIF($T$9:$T64,1),"") | V64: =IF(AND(ISTEXT($A64),LEFT($A65,3)="Pan"),1,"") | W64: =IFERROR(MATCH(56,$U$9:$U$2008,0),"") | X64: =IF($W64="","",IF($R$5<>"",$R$5,$R$6)) | Y64: =IF($W64="","",INDEX($S$9:$S$2008,$W64)) | Z64: =IF($W64="","",IFERROR(TRIM(LEFT(SUBSTITUTE(INDEX($A$9:$A$2008,$W64),CHAR(10)," "),SEARCH("Folio",SUBSTITUTE(INDEX($A$9:$A$2008,$W64),CHAR(10)," "))-1)),TRIM(SUBSTITUTE(INDEX($A$9:$A$2008,$W64),CHAR(10)," ")))) | AA64: =IF($W64="","",IFERROR(TRIM(SUBSTITUTE(MID(SUBSTITUTE(INDEX($A$9:$A$2008,$W64),CHAR(10)," "),SEARCH("Folio",SUBSTITUTE(INDEX($A$9:$A$2008,$W64),CHAR(10)," "))+5,200),":","")),"")) | AB64: =IF($W64="","",IF(ISNUMBER(INDEX($D$9:$D$2008,$W64)),INDEX($D$9:$D$2008,$W64),IFERROR(DATE(2000+VALUE(RIGHT(INDEX($D$9:$D$2008,$W64),2)),VALUE(MID(INDEX($D$9:$D$2008,$W64),4,2)),VALUE(LEFT(INDEX($D$9:$D$2008,$W64),2))),""))) | AC64: =IF($W64="","",IFERROR(IF(ISNUMBER(INDEX($E$9:$E$2008,$W64)),INDEX($E$9:$E$2008,$W64),VALUE(SUBSTITUTE(INDEX($E$9:$E$2008,$W64),",",""))),"")) | AD64: =IF($W64="","",IFERROR(IF(ISNUMBER(INDEX($F$9:$F$2008,$W64)),INDEX($F$9:$F$2008,$W64),VALUE(SUBSTITUTE(INDEX($F$9:$F$2008,$W64),",",""))),"")) | AE64: =IF($W64="","",IFERROR(IF(ISNUMBER(INDEX($G$9:$G$2008,$W64)),INDEX($G$9:$G$2008,$W64),VALUE(SUBSTITUTE(INDEX($G$9:$G$2008,$W64),",",""))),"")) | AF64: =IF($W64="","",IFERROR(IF(ISNUMBER(INDEX($H$9:$H$2008,$W64)),INDEX($H$9:$H$2008,$W64),VALUE(SUBSTITUTE(INDEX($H$9:$H$2008,$W64),",",""))),"")) | AG64: =IF($W64="","",IFERROR(IF(ISNUMBER(INDEX($I$9:$I$2008,$W64)),INDEX($I$9:$I$2008,$W64),VALUE(SUBSTITUTE(INDEX($I$9:$I$2008,$W64),",",""))),"")) | AH64: =IF($W64="","",IFERROR(IF(ISNUMBER(INDEX($J$9:$J$2008,$W64)),INDEX($J$9:$J$2008,$W64),VALUE(SUBSTITUTE(INDEX($J$9:$J$2008,$W64),",",""))),"")) | AI64: =IF($W64="","",IFERROR(IF(ISNUMBER(INDEX($K$9:$K$2008,$W64)),INDEX($K$9:$K$2008,$W64),VALUE(SUBSTITUTE(INDEX($K$9:$K$2008,$W64),",",""))),"")) | AJ64: =IF($W64="","",IFERROR(IF(ISNUMBER(INDEX($L$9:$L$2008,$W64)),INDEX($L$9:$L$2008,$W64),VALUE(SUBSTITUTE(INDEX($L$9:$L$2008,$W64),",",""))),"")) | AK64: =IF($W64="","",IFERROR(IF(ISNUMBER(INDEX($M$9:$M$2008,$W64)),INDEX($M$9:$M$2008,$W64),VALUE(SUBSTITUTE(INDEX($M$9:$M$2008,$W64),",",""))),"")) | AL64: =IF($W64="","",IFERROR(IF(ISNUMBER(INDEX($P$9:$P$2008,$W64)),INDEX($P$9:$P$2008,$W64),VALUE(SUBSTITUTE(INDEX($P$9:$P$2008,$W64),"%",""))/100),""))
S65: =IF(AND(ISTEXT($A65),ISNUMBER(SEARCH(" - ",$A65)),ISERROR(SEARCH("Folio",$A65)),$D65=""),TRIM($A65),$S64) | T65: =IF(AND(ISNUMBER(SEARCH("Folio",$A65)),$D65<>""),1,"") | U65: =IF($T65=1,COUNTIF($T$9:$T65,1),"") | V65: =IF(AND(ISTEXT($A65),LEFT($A66,3)="Pan"),1,"") | W65: =IFERROR(MATCH(57,$U$9:$U$2008,0),"") | X65: =IF($W65="","",IF($R$5<>"",$R$5,$R$6)) | Y65: =IF($W65="","",INDEX($S$9:$S$2008,$W65)) | Z65: =IF($W65="","",IFERROR(TRIM(LEFT(SUBSTITUTE(INDEX($A$9:$A$2008,$W65),CHAR(10)," "),SEARCH("Folio",SUBSTITUTE(INDEX($A$9:$A$2008,$W65),CHAR(10)," "))-1)),TRIM(SUBSTITUTE(INDEX($A$9:$A$2008,$W65),CHAR(10)," ")))) | AA65: =IF($W65="","",IFERROR(TRIM(SUBSTITUTE(MID(SUBSTITUTE(INDEX($A$9:$A$2008,$W65),CHAR(10)," "),SEARCH("Folio",SUBSTITUTE(INDEX($A$9:$A$2008,$W65),CHAR(10)," "))+5,200),":","")),"")) | AB65: =IF($W65="","",IF(ISNUMBER(INDEX($D$9:$D$2008,$W65)),INDEX($D$9:$D$2008,$W65),IFERROR(DATE(2000+VALUE(RIGHT(INDEX($D$9:$D$2008,$W65),2)),VALUE(MID(INDEX($D$9:$D$2008,$W65),4,2)),VALUE(LEFT(INDEX($D$9:$D$2008,$W65),2))),""))) | AC65: =IF($W65="","",IFERROR(IF(ISNUMBER(INDEX($E$9:$E$2008,$W65)),INDEX($E$9:$E$2008,$W65),VALUE(SUBSTITUTE(INDEX($E$9:$E$2008,$W65),",",""))),"")) | AD65: =IF($W65="","",IFERROR(IF(ISNUMBER(INDEX($F$9:$F$2008,$W65)),INDEX($F$9:$F$2008,$W65),VALUE(SUBSTITUTE(INDEX($F$9:$F$2008,$W65),",",""))),"")) | AE65: =IF($W65="","",IFERROR(IF(ISNUMBER(INDEX($G$9:$G$2008,$W65)),INDEX($G$9:$G$2008,$W65),VALUE(SUBSTITUTE(INDEX($G$9:$G$2008,$W65),",",""))),"")) | AF65: =IF($W65="","",IFERROR(IF(ISNUMBER(INDEX($H$9:$H$2008,$W65)),INDEX($H$9:$H$2008,$W65),VALUE(SUBSTITUTE(INDEX($H$9:$H$2008,$W65),",",""))),"")) | AG65: =IF($W65="","",IFERROR(IF(ISNUMBER(INDEX($I$9:$I$2008,$W65)),INDEX($I$9:$I$2008,$W65),VALUE(SUBSTITUTE(INDEX($I$9:$I$2008,$W65),",",""))),"")) | AH65: =IF($W65="","",IFERROR(IF(ISNUMBER(INDEX($J$9:$J$2008,$W65)),INDEX($J$9:$J$2008,$W65),VALUE(SUBSTITUTE(INDEX($J$9:$J$2008,$W65),",",""))),"")) | AI65: =IF($W65="","",IFERROR(IF(ISNUMBER(INDEX($K$9:$K$2008,$W65)),INDEX($K$9:$K$2008,$W65),VALUE(SUBSTITUTE(INDEX($K$9:$K$2008,$W65),",",""))),"")) | AJ65: =IF($W65="","",IFERROR(IF(ISNUMBER(INDEX($L$9:$L$2008,$W65)),INDEX($L$9:$L$2008,$W65),VALUE(SUBSTITUTE(INDEX($L$9:$L$2008,$W65),",",""))),"")) | AK65: =IF($W65="","",IFERROR(IF(ISNUMBER(INDEX($M$9:$M$2008,$W65)),INDEX($M$9:$M$2008,$W65),VALUE(SUBSTITUTE(INDEX($M$9:$M$2008,$W65),",",""))),"")) | AL65: =IF($W65="","",IFERROR(IF(ISNUMBER(INDEX($P$9:$P$2008,$W65)),INDEX($P$9:$P$2008,$W65),VALUE(SUBSTITUTE(INDEX($P$9:$P$2008,$W65),"%",""))/100),""))
S66: =IF(AND(ISTEXT($A66),ISNUMBER(SEARCH(" - ",$A66)),ISERROR(SEARCH("Folio",$A66)),$D66=""),TRIM($A66),$S65) | T66: =IF(AND(ISNUMBER(SEARCH("Folio",$A66)),$D66<>""),1,"") | U66: =IF($T66=1,COUNTIF($T$9:$T66,1),"") | V66: =IF(AND(ISTEXT($A66),LEFT($A67,3)="Pan"),1,"") | W66: =IFERROR(MATCH(58,$U$9:$U$2008,0),"") | X66: =IF($W66="","",IF($R$5<>"",$R$5,$R$6)) | Y66: =IF($W66="","",INDEX($S$9:$S$2008,$W66)) | Z66: =IF($W66="","",IFERROR(TRIM(LEFT(SUBSTITUTE(INDEX($A$9:$A$2008,$W66),CHAR(10)," "),SEARCH("Folio",SUBSTITUTE(INDEX($A$9:$A$2008,$W66),CHAR(10)," "))-1)),TRIM(SUBSTITUTE(INDEX($A$9:$A$2008,$W66),CHAR(10)," ")))) | AA66: =IF($W66="","",IFERROR(TRIM(SUBSTITUTE(MID(SUBSTITUTE(INDEX($A$9:$A$2008,$W66),CHAR(10)," "),SEARCH("Folio",SUBSTITUTE(INDEX($A$9:$A$2008,$W66),CHAR(10)," "))+5,200),":","")),"")) | AB66: =IF($W66="","",IF(ISNUMBER(INDEX($D$9:$D$2008,$W66)),INDEX($D$9:$D$2008,$W66),IFERROR(DATE(2000+VALUE(RIGHT(INDEX($D$9:$D$2008,$W66),2)),VALUE(MID(INDEX($D$9:$D$2008,$W66),4,2)),VALUE(LEFT(INDEX($D$9:$D$2008,$W66),2))),""))) | AC66: =IF($W66="","",IFERROR(IF(ISNUMBER(INDEX($E$9:$E$2008,$W66)),INDEX($E$9:$E$2008,$W66),VALUE(SUBSTITUTE(INDEX($E$9:$E$2008,$W66),",",""))),"")) | AD66: =IF($W66="","",IFERROR(IF(ISNUMBER(INDEX($F$9:$F$2008,$W66)),INDEX($F$9:$F$2008,$W66),VALUE(SUBSTITUTE(INDEX($F$9:$F$2008,$W66),",",""))),"")) | AE66: =IF($W66="","",IFERROR(IF(ISNUMBER(INDEX($G$9:$G$2008,$W66)),INDEX($G$9:$G$2008,$W66),VALUE(SUBSTITUTE(INDEX($G$9:$G$2008,$W66),",",""))),"")) | AF66: =IF($W66="","",IFERROR(IF(ISNUMBER(INDEX($H$9:$H$2008,$W66)),INDEX($H$9:$H$2008,$W66),VALUE(SUBSTITUTE(INDEX($H$9:$H$2008,$W66),",",""))),"")) | AG66: =IF($W66="","",IFERROR(IF(ISNUMBER(INDEX($I$9:$I$2008,$W66)),INDEX($I$9:$I$2008,$W66),VALUE(SUBSTITUTE(INDEX($I$9:$I$2008,$W66),",",""))),"")) | AH66: =IF($W66="","",IFERROR(IF(ISNUMBER(INDEX($J$9:$J$2008,$W66)),INDEX($J$9:$J$2008,$W66),VALUE(SUBSTITUTE(INDEX($J$9:$J$2008,$W66),",",""))),"")) | AI66: =IF($W66="","",IFERROR(IF(ISNUMBER(INDEX($K$9:$K$2008,$W66)),INDEX($K$9:$K$2008,$W66),VALUE(SUBSTITUTE(INDEX($K$9:$K$2008,$W66),",",""))),"")) | AJ66: =IF($W66="","",IFERROR(IF(ISNUMBER(INDEX($L$9:$L$2008,$W66)),INDEX($L$9:$L$2008,$W66),VALUE(SUBSTITUTE(INDEX($L$9:$L$2008,$W66),",",""))),"")) | AK66: =IF($W66="","",IFERROR(IF(ISNUMBER(INDEX($M$9:$M$2008,$W66)),INDEX($M$9:$M$2008,$W66),VALUE(SUBSTITUTE(INDEX($M$9:$M$2008,$W66),",",""))),"")) | AL66: =IF($W66="","",IFERROR(IF(ISNUMBER(INDEX($P$9:$P$2008,$W66)),INDEX($P$9:$P$2008,$W66),VALUE(SUBSTITUTE(INDEX($P$9:$P$2008,$W66),"%",""))/100),""))
S67: =IF(AND(ISTEXT($A67),ISNUMBER(SEARCH(" - ",$A67)),ISERROR(SEARCH("Folio",$A67)),$D67=""),TRIM($A67),$S66) | T67: =IF(AND(ISNUMBER(SEARCH("Folio",$A67)),$D67<>""),1,"") | U67: =IF($T67=1,COUNTIF($T$9:$T67,1),"") | V67: =IF(AND(ISTEXT($A67),LEFT($A68,3)="Pan"),1,"") | W67: =IFERROR(MATCH(59,$U$9:$U$2008,0),"") | X67: =IF($W67="","",IF($R$5<>"",$R$5,$R$6)) | Y67: =IF($W67="","",INDEX($S$9:$S$2008,$W67)) | Z67: =IF($W67="","",IFERROR(TRIM(LEFT(SUBSTITUTE(INDEX($A$9:$A$2008,$W67),CHAR(10)," "),SEARCH("Folio",SUBSTITUTE(INDEX($A$9:$A$2008,$W67),CHAR(10)," "))-1)),TRIM(SUBSTITUTE(INDEX($A$9:$A$2008,$W67),CHAR(10)," ")))) | AA67: =IF($W67="","",IFERROR(TRIM(SUBSTITUTE(MID(SUBSTITUTE(INDEX($A$9:$A$2008,$W67),CHAR(10)," "),SEARCH("Folio",SUBSTITUTE(INDEX($A$9:$A$2008,$W67),CHAR(10)," "))+5,200),":","")),"")) | AB67: =IF($W67="","",IF(ISNUMBER(INDEX($D$9:$D$2008,$W67)),INDEX($D$9:$D$2008,$W67),IFERROR(DATE(2000+VALUE(RIGHT(INDEX($D$9:$D$2008,$W67),2)),VALUE(MID(INDEX($D$9:$D$2008,$W67),4,2)),VALUE(LEFT(INDEX($D$9:$D$2008,$W67),2))),""))) | AC67: =IF($W67="","",IFERROR(IF(ISNUMBER(INDEX($E$9:$E$2008,$W67)),INDEX($E$9:$E$2008,$W67),VALUE(SUBSTITUTE(INDEX($E$9:$E$2008,$W67),",",""))),"")) | AD67: =IF($W67="","",IFERROR(IF(ISNUMBER(INDEX($F$9:$F$2008,$W67)),INDEX($F$9:$F$2008,$W67),VALUE(SUBSTITUTE(INDEX($F$9:$F$2008,$W67),",",""))),"")) | AE67: =IF($W67="","",IFERROR(IF(ISNUMBER(INDEX($G$9:$G$2008,$W67)),INDEX($G$9:$G$2008,$W67),VALUE(SUBSTITUTE(INDEX($G$9:$G$2008,$W67),",",""))),"")) | AF67: =IF($W67="","",IFERROR(IF(ISNUMBER(INDEX($H$9:$H$2008,$W67)),INDEX($H$9:$H$2008,$W67),VALUE(SUBSTITUTE(INDEX($H$9:$H$2008,$W67),",",""))),"")) | AG67: =IF($W67="","",IFERROR(IF(ISNUMBER(INDEX($I$9:$I$2008,$W67)),INDEX($I$9:$I$2008,$W67),VALUE(SUBSTITUTE(INDEX($I$9:$I$2008,$W67),",",""))),"")) | AH67: =IF($W67="","",IFERROR(IF(ISNUMBER(INDEX($J$9:$J$2008,$W67)),INDEX($J$9:$J$2008,$W67),VALUE(SUBSTITUTE(INDEX($J$9:$J$2008,$W67),",",""))),"")) | AI67: =IF($W67="","",IFERROR(IF(ISNUMBER(INDEX($K$9:$K$2008,$W67)),INDEX($K$9:$K$2008,$W67),VALUE(SUBSTITUTE(INDEX($K$9:$K$2008,$W67),",",""))),"")) | AJ67: =IF($W67="","",IFERROR(IF(ISNUMBER(INDEX($L$9:$L$2008,$W67)),INDEX($L$9:$L$2008,$W67),VALUE(SUBSTITUTE(INDEX($L$9:$L$2008,$W67),",",""))),"")) | AK67: =IF($W67="","",IFERROR(IF(ISNUMBER(INDEX($M$9:$M$2008,$W67)),INDEX($M$9:$M$2008,$W67),VALUE(SUBSTITUTE(INDEX($M$9:$M$2008,$W67),",",""))),"")) | AL67: =IF($W67="","",IFERROR(IF(ISNUMBER(INDEX($P$9:$P$2008,$W67)),INDEX($P$9:$P$2008,$W67),VALUE(SUBSTITUTE(INDEX($P$9:$P$2008,$W67),"%",""))/100),""))
S68: =IF(AND(ISTEXT($A68),ISNUMBER(SEARCH(" - ",$A68)),ISERROR(SEARCH("Folio",$A68)),$D68=""),TRIM($A68),$S67) | T68: =IF(AND(ISNUMBER(SEARCH("Folio",$A68)),$D68<>""),1,"") | U68: =IF($T68=1,COUNTIF($T$9:$T68,1),"") | V68: =IF(AND(ISTEXT($A68),LEFT($A69,3)="Pan"),1,"") | W68: =IFERROR(MATCH(60,$U$9:$U$2008,0),"") | X68: =IF($W68="","",IF($R$5<>"",$R$5,$R$6)) | Y68: =IF($W68="","",INDEX($S$9:$S$2008,$W68)) | Z68: =IF($W68="","",IFERROR(TRIM(LEFT(SUBSTITUTE(INDEX($A$9:$A$2008,$W68),CHAR(10)," "),SEARCH("Folio",SUBSTITUTE(INDEX($A$9:$A$2008,$W68),CHAR(10)," "))-1)),TRIM(SUBSTITUTE(INDEX($A$9:$A$2008,$W68),CHAR(10)," ")))) | AA68: =IF($W68="","",IFERROR(TRIM(SUBSTITUTE(MID(SUBSTITUTE(INDEX($A$9:$A$2008,$W68),CHAR(10)," "),SEARCH("Folio",SUBSTITUTE(INDEX($A$9:$A$2008,$W68),CHAR(10)," "))+5,200),":","")),"")) | AB68: =IF($W68="","",IF(ISNUMBER(INDEX($D$9:$D$2008,$W68)),INDEX($D$9:$D$2008,$W68),IFERROR(DATE(2000+VALUE(RIGHT(INDEX($D$9:$D$2008,$W68),2)),VALUE(MID(INDEX($D$9:$D$2008,$W68),4,2)),VALUE(LEFT(INDEX($D$9:$D$2008,$W68),2))),""))) | AC68: =IF($W68="","",IFERROR(IF(ISNUMBER(INDEX($E$9:$E$2008,$W68)),INDEX($E$9:$E$2008,$W68),VALUE(SUBSTITUTE(INDEX($E$9:$E$2008,$W68),",",""))),"")) | AD68: =IF($W68="","",IFERROR(IF(ISNUMBER(INDEX($F$9:$F$2008,$W68)),INDEX($F$9:$F$2008,$W68),VALUE(SUBSTITUTE(INDEX($F$9:$F$2008,$W68),",",""))),"")) | AE68: =IF($W68="","",IFERROR(IF(ISNUMBER(INDEX($G$9:$G$2008,$W68)),INDEX($G$9:$G$2008,$W68),VALUE(SUBSTITUTE(INDEX($G$9:$G$2008,$W68),",",""))),"")) | AF68: =IF($W68="","",IFERROR(IF(ISNUMBER(INDEX($H$9:$H$2008,$W68)),INDEX($H$9:$H$2008,$W68),VALUE(SUBSTITUTE(INDEX($H$9:$H$2008,$W68),",",""))),"")) | AG68: =IF($W68="","",IFERROR(IF(ISNUMBER(INDEX($I$9:$I$2008,$W68)),INDEX($I$9:$I$2008,$W68),VALUE(SUBSTITUTE(INDEX($I$9:$I$2008,$W68),",",""))),"")) | AH68: =IF($W68="","",IFERROR(IF(ISNUMBER(INDEX($J$9:$J$2008,$W68)),INDEX($J$9:$J$2008,$W68),VALUE(SUBSTITUTE(INDEX($J$9:$J$2008,$W68),",",""))),"")) | AI68: =IF($W68="","",IFERROR(IF(ISNUMBER(INDEX($K$9:$K$2008,$W68)),INDEX($K$9:$K$2008,$W68),VALUE(SUBSTITUTE(INDEX($K$9:$K$2008,$W68),",",""))),"")) | AJ68: =IF($W68="","",IFERROR(IF(ISNUMBER(INDEX($L$9:$L$2008,$W68)),INDEX($L$9:$L$2008,$W68),VALUE(SUBSTITUTE(INDEX($L$9:$L$2008,$W68),",",""))),"")) | AK68: =IF($W68="","",IFERROR(IF(ISNUMBER(INDEX($M$9:$M$2008,$W68)),INDEX($M$9:$M$2008,$W68),VALUE(SUBSTITUTE(INDEX($M$9:$M$2008,$W68),",",""))),"")) | AL68: =IF($W68="","",IFERROR(IF(ISNUMBER(INDEX($P$9:$P$2008,$W68)),INDEX($P$9:$P$2008,$W68),VALUE(SUBSTITUTE(INDEX($P$9:$P$2008,$W68),"%",""))/100),""))
S69: =IF(AND(ISTEXT($A69),ISNUMBER(SEARCH(" - ",$A69)),ISERROR(SEARCH("Folio",$A69)),$D69=""),TRIM($A69),$S68) | T69: =IF(AND(ISNUMBER(SEARCH("Folio",$A69)),$D69<>""),1,"") | U69: =IF($T69=1,COUNTIF($T$9:$T69,1),"") | V69: =IF(AND(ISTEXT($A69),LEFT($A70,3)="Pan"),1,"") | W69: =IFERROR(MATCH(61,$U$9:$U$2008,0),"") | X69: =IF($W69="","",IF($R$5<>"",$R$5,$R$6)) | Y69: =IF($W69="","",INDEX($S$9:$S$2008,$W69)) | Z69: =IF($W69="","",IFERROR(TRIM(LEFT(SUBSTITUTE(INDEX($A$9:$A$2008,$W69),CHAR(10)," "),SEARCH("Folio",SUBSTITUTE(INDEX($A$9:$A$2008,$W69),CHAR(10)," "))-1)),TRIM(SUBSTITUTE(INDEX($A$9:$A$2008,$W69),CHAR(10)," ")))) | AA69: =IF($W69="","",IFERROR(TRIM(SUBSTITUTE(MID(SUBSTITUTE(INDEX($A$9:$A$2008,$W69),CHAR(10)," "),SEARCH("Folio",SUBSTITUTE(INDEX($A$9:$A$2008,$W69),CHAR(10)," "))+5,200),":","")),"")) | AB69: =IF($W69="","",IF(ISNUMBER(INDEX($D$9:$D$2008,$W69)),INDEX($D$9:$D$2008,$W69),IFERROR(DATE(2000+VALUE(RIGHT(INDEX($D$9:$D$2008,$W69),2)),VALUE(MID(INDEX($D$9:$D$2008,$W69),4,2)),VALUE(LEFT(INDEX($D$9:$D$2008,$W69),2))),""))) | AC69: =IF($W69="","",IFERROR(IF(ISNUMBER(INDEX($E$9:$E$2008,$W69)),INDEX($E$9:$E$2008,$W69),VALUE(SUBSTITUTE(INDEX($E$9:$E$2008,$W69),",",""))),"")) | AD69: =IF($W69="","",IFERROR(IF(ISNUMBER(INDEX($F$9:$F$2008,$W69)),INDEX($F$9:$F$2008,$W69),VALUE(SUBSTITUTE(INDEX($F$9:$F$2008,$W69),",",""))),"")) | AE69: =IF($W69="","",IFERROR(IF(ISNUMBER(INDEX($G$9:$G$2008,$W69)),INDEX($G$9:$G$2008,$W69),VALUE(SUBSTITUTE(INDEX($G$9:$G$2008,$W69),",",""))),"")) | AF69: =IF($W69="","",IFERROR(IF(ISNUMBER(INDEX($H$9:$H$2008,$W69)),INDEX($H$9:$H$2008,$W69),VALUE(SUBSTITUTE(INDEX($H$9:$H$2008,$W69),",",""))),"")) | AG69: =IF($W69="","",IFERROR(IF(ISNUMBER(INDEX($I$9:$I$2008,$W69)),INDEX($I$9:$I$2008,$W69),VALUE(SUBSTITUTE(INDEX($I$9:$I$2008,$W69),",",""))),"")) | AH69: =IF($W69="","",IFERROR(IF(ISNUMBER(INDEX($J$9:$J$2008,$W69)),INDEX($J$9:$J$2008,$W69),VALUE(SUBSTITUTE(INDEX($J$9:$J$2008,$W69),",",""))),"")) | AI69: =IF($W69="","",IFERROR(IF(ISNUMBER(INDEX($K$9:$K$2008,$W69)),INDEX($K$9:$K$2008,$W69),VALUE(SUBSTITUTE(INDEX($K$9:$K$2008,$W69),",",""))),"")) | AJ69: =IF($W69="","",IFERROR(IF(ISNUMBER(INDEX($L$9:$L$2008,$W69)),INDEX($L$9:$L$2008,$W69),VALUE(SUBSTITUTE(INDEX($L$9:$L$2008,$W69),",",""))),"")) | AK69: =IF($W69="","",IFERROR(IF(ISNUMBER(INDEX($M$9:$M$2008,$W69)),INDEX($M$9:$M$2008,$W69),VALUE(SUBSTITUTE(INDEX($M$9:$M$2008,$W69),",",""))),"")) | AL69: =IF($W69="","",IFERROR(IF(ISNUMBER(INDEX($P$9:$P$2008,$W69)),INDEX($P$9:$P$2008,$W69),VALUE(SUBSTITUTE(INDEX($P$9:$P$2008,$W69),"%",""))/100),""))
S70: =IF(AND(ISTEXT($A70),ISNUMBER(SEARCH(" - ",$A70)),ISERROR(SEARCH("Folio",$A70)),$D70=""),TRIM($A70),$S69) | T70: =IF(AND(ISNUMBER(SEARCH("Folio",$A70)),$D70<>""),1,"") | U70: =IF($T70=1,COUNTIF($T$9:$T70,1),"") | V70: =IF(AND(ISTEXT($A70),LEFT($A71,3)="Pan"),1,"") | W70: =IFERROR(MATCH(62,$U$9:$U$2008,0),"") | X70: =IF($W70="","",IF($R$5<>"",$R$5,$R$6)) | Y70: =IF($W70="","",INDEX($S$9:$S$2008,$W70)) | Z70: =IF($W70="","",IFERROR(TRIM(LEFT(SUBSTITUTE(INDEX($A$9:$A$2008,$W70),CHAR(10)," "),SEARCH("Folio",SUBSTITUTE(INDEX($A$9:$A$2008,$W70),CHAR(10)," "))-1)),TRIM(SUBSTITUTE(INDEX($A$9:$A$2008,$W70),CHAR(10)," ")))) | AA70: =IF($W70="","",IFERROR(TRIM(SUBSTITUTE(MID(SUBSTITUTE(INDEX($A$9:$A$2008,$W70),CHAR(10)," "),SEARCH("Folio",SUBSTITUTE(INDEX($A$9:$A$2008,$W70),CHAR(10)," "))+5,200),":","")),"")) | AB70: =IF($W70="","",IF(ISNUMBER(INDEX($D$9:$D$2008,$W70)),INDEX($D$9:$D$2008,$W70),IFERROR(DATE(2000+VALUE(RIGHT(INDEX($D$9:$D$2008,$W70),2)),VALUE(MID(INDEX($D$9:$D$2008,$W70),4,2)),VALUE(LEFT(INDEX($D$9:$D$2008,$W70),2))),""))) | AC70: =IF($W70="","",IFERROR(IF(ISNUMBER(INDEX($E$9:$E$2008,$W70)),INDEX($E$9:$E$2008,$W70),VALUE(SUBSTITUTE(INDEX($E$9:$E$2008,$W70),",",""))),"")) | AD70: =IF($W70="","",IFERROR(IF(ISNUMBER(INDEX($F$9:$F$2008,$W70)),INDEX($F$9:$F$2008,$W70),VALUE(SUBSTITUTE(INDEX($F$9:$F$2008,$W70),",",""))),"")) | AE70: =IF($W70="","",IFERROR(IF(ISNUMBER(INDEX($G$9:$G$2008,$W70)),INDEX($G$9:$G$2008,$W70),VALUE(SUBSTITUTE(INDEX($G$9:$G$2008,$W70),",",""))),"")) | AF70: =IF($W70="","",IFERROR(IF(ISNUMBER(INDEX($H$9:$H$2008,$W70)),INDEX($H$9:$H$2008,$W70),VALUE(SUBSTITUTE(INDEX($H$9:$H$2008,$W70),",",""))),"")) | AG70: =IF($W70="","",IFERROR(IF(ISNUMBER(INDEX($I$9:$I$2008,$W70)),INDEX($I$9:$I$2008,$W70),VALUE(SUBSTITUTE(INDEX($I$9:$I$2008,$W70),",",""))),"")) | AH70: =IF($W70="","",IFERROR(IF(ISNUMBER(INDEX($J$9:$J$2008,$W70)),INDEX($J$9:$J$2008,$W70),VALUE(SUBSTITUTE(INDEX($J$9:$J$2008,$W70),",",""))),"")) | AI70: =IF($W70="","",IFERROR(IF(ISNUMBER(INDEX($K$9:$K$2008,$W70)),INDEX($K$9:$K$2008,$W70),VALUE(SUBSTITUTE(INDEX($K$9:$K$2008,$W70),",",""))),"")) | AJ70: =IF($W70="","",IFERROR(IF(ISNUMBER(INDEX($L$9:$L$2008,$W70)),INDEX($L$9:$L$2008,$W70),VALUE(SUBSTITUTE(INDEX($L$9:$L$2008,$W70),",",""))),"")) | AK70: =IF($W70="","",IFERROR(IF(ISNUMBER(INDEX($M$9:$M$2008,$W70)),INDEX($M$9:$M$2008,$W70),VALUE(SUBSTITUTE(INDEX($M$9:$M$2008,$W70),",",""))),"")) | AL70: =IF($W70="","",IFERROR(IF(ISNUMBER(INDEX($P$9:$P$2008,$W70)),INDEX($P$9:$P$2008,$W70),VALUE(SUBSTITUTE(INDEX($P$9:$P$2008,$W70),"%",""))/100),""))
S71: =IF(AND(ISTEXT($A71),ISNUMBER(SEARCH(" - ",$A71)),ISERROR(SEARCH("Folio",$A71)),$D71=""),TRIM($A71),$S70) | T71: =IF(AND(ISNUMBER(SEARCH("Folio",$A71)),$D71<>""),1,"") | U71: =IF($T71=1,COUNTIF($T$9:$T71,1),"") | V71: =IF(AND(ISTEXT($A71),LEFT($A72,3)="Pan"),1,"") | W71: =IFERROR(MATCH(63,$U$9:$U$2008,0),"") | X71: =IF($W71="","",IF($R$5<>"",$R$5,$R$6)) | Y71: =IF($W71="","",INDEX($S$9:$S$2008,$W71)) | Z71: =IF($W71="","",IFERROR(TRIM(LEFT(SUBSTITUTE(INDEX($A$9:$A$2008,$W71),CHAR(10)," "),SEARCH("Folio",SUBSTITUTE(INDEX($A$9:$A$2008,$W71),CHAR(10)," "))-1)),TRIM(SUBSTITUTE(INDEX($A$9:$A$2008,$W71),CHAR(10)," ")))) | AA71: =IF($W71="","",IFERROR(TRIM(SUBSTITUTE(MID(SUBSTITUTE(INDEX($A$9:$A$2008,$W71),CHAR(10)," "),SEARCH("Folio",SUBSTITUTE(INDEX($A$9:$A$2008,$W71),CHAR(10)," "))+5,200),":","")),"")) | AB71: =IF($W71="","",IF(ISNUMBER(INDEX($D$9:$D$2008,$W71)),INDEX($D$9:$D$2008,$W71),IFERROR(DATE(2000+VALUE(RIGHT(INDEX($D$9:$D$2008,$W71),2)),VALUE(MID(INDEX($D$9:$D$2008,$W71),4,2)),VALUE(LEFT(INDEX($D$9:$D$2008,$W71),2))),""))) | AC71: =IF($W71="","",IFERROR(IF(ISNUMBER(INDEX($E$9:$E$2008,$W71)),INDEX($E$9:$E$2008,$W71),VALUE(SUBSTITUTE(INDEX($E$9:$E$2008,$W71),",",""))),"")) | AD71: =IF($W71="","",IFERROR(IF(ISNUMBER(INDEX($F$9:$F$2008,$W71)),INDEX($F$9:$F$2008,$W71),VALUE(SUBSTITUTE(INDEX($F$9:$F$2008,$W71),",",""))),"")) | AE71: =IF($W71="","",IFERROR(IF(ISNUMBER(INDEX($G$9:$G$2008,$W71)),INDEX($G$9:$G$2008,$W71),VALUE(SUBSTITUTE(INDEX($G$9:$G$2008,$W71),",",""))),"")) | AF71: =IF($W71="","",IFERROR(IF(ISNUMBER(INDEX($H$9:$H$2008,$W71)),INDEX($H$9:$H$2008,$W71),VALUE(SUBSTITUTE(INDEX($H$9:$H$2008,$W71),",",""))),"")) | AG71: =IF($W71="","",IFERROR(IF(ISNUMBER(INDEX($I$9:$I$2008,$W71)),INDEX($I$9:$I$2008,$W71),VALUE(SUBSTITUTE(INDEX($I$9:$I$2008,$W71),",",""))),"")) | AH71: =IF($W71="","",IFERROR(IF(ISNUMBER(INDEX($J$9:$J$2008,$W71)),INDEX($J$9:$J$2008,$W71),VALUE(SUBSTITUTE(INDEX($J$9:$J$2008,$W71),",",""))),"")) | AI71: =IF($W71="","",IFERROR(IF(ISNUMBER(INDEX($K$9:$K$2008,$W71)),INDEX($K$9:$K$2008,$W71),VALUE(SUBSTITUTE(INDEX($K$9:$K$2008,$W71),",",""))),"")) | AJ71: =IF($W71="","",IFERROR(IF(ISNUMBER(INDEX($L$9:$L$2008,$W71)),INDEX($L$9:$L$2008,$W71),VALUE(SUBSTITUTE(INDEX($L$9:$L$2008,$W71),",",""))),"")) | AK71: =IF($W71="","",IFERROR(IF(ISNUMBER(INDEX($M$9:$M$2008,$W71)),INDEX($M$9:$M$2008,$W71),VALUE(SUBSTITUTE(INDEX($M$9:$M$2008,$W71),",",""))),"")) | AL71: =IF($W71="","",IFERROR(IF(ISNUMBER(INDEX($P$9:$P$2008,$W71)),INDEX($P$9:$P$2008,$W71),VALUE(SUBSTITUTE(INDEX($P$9:$P$2008,$W71),"%",""))/100),""))
S72: =IF(AND(ISTEXT($A72),ISNUMBER(SEARCH(" - ",$A72)),ISERROR(SEARCH("Folio",$A72)),$D72=""),TRIM($A72),$S71) | T72: =IF(AND(ISNUMBER(SEARCH("Folio",$A72)),$D72<>""),1,"") | U72: =IF($T72=1,COUNTIF($T$9:$T72,1),"") | V72: =IF(AND(ISTEXT($A72),LEFT($A73,3)="Pan"),1,"") | W72: =IFERROR(MATCH(64,$U$9:$U$2008,0),"") | X72: =IF($W72="","",IF($R$5<>"",$R$5,$R$6)) | Y72: =IF($W72="","",INDEX($S$9:$S$2008,$W72)) | Z72: =IF($W72="","",IFERROR(TRIM(LEFT(SUBSTITUTE(INDEX($A$9:$A$2008,$W72),CHAR(10)," "),SEARCH("Folio",SUBSTITUTE(INDEX($A$9:$A$2008,$W72),CHAR(10)," "))-1)),TRIM(SUBSTITUTE(INDEX($A$9:$A$2008,$W72),CHAR(10)," ")))) | AA72: =IF($W72="","",IFERROR(TRIM(SUBSTITUTE(MID(SUBSTITUTE(INDEX($A$9:$A$2008,$W72),CHAR(10)," "),SEARCH("Folio",SUBSTITUTE(INDEX($A$9:$A$2008,$W72),CHAR(10)," "))+5,200),":","")),"")) | AB72: =IF($W72="","",IF(ISNUMBER(INDEX($D$9:$D$2008,$W72)),INDEX($D$9:$D$2008,$W72),IFERROR(DATE(2000+VALUE(RIGHT(INDEX($D$9:$D$2008,$W72),2)),VALUE(MID(INDEX($D$9:$D$2008,$W72),4,2)),VALUE(LEFT(INDEX($D$9:$D$2008,$W72),2))),""))) | AC72: =IF($W72="","",IFERROR(IF(ISNUMBER(INDEX($E$9:$E$2008,$W72)),INDEX($E$9:$E$2008,$W72),VALUE(SUBSTITUTE(INDEX($E$9:$E$2008,$W72),",",""))),"")) | AD72: =IF($W72="","",IFERROR(IF(ISNUMBER(INDEX($F$9:$F$2008,$W72)),INDEX($F$9:$F$2008,$W72),VALUE(SUBSTITUTE(INDEX($F$9:$F$2008,$W72),",",""))),"")) | AE72: =IF($W72="","",IFERROR(IF(ISNUMBER(INDEX($G$9:$G$2008,$W72)),INDEX($G$9:$G$2008,$W72),VALUE(SUBSTITUTE(INDEX($G$9:$G$2008,$W72),",",""))),"")) | AF72: =IF($W72="","",IFERROR(IF(ISNUMBER(INDEX($H$9:$H$2008,$W72)),INDEX($H$9:$H$2008,$W72),VALUE(SUBSTITUTE(INDEX($H$9:$H$2008,$W72),",",""))),"")) | AG72: =IF($W72="","",IFERROR(IF(ISNUMBER(INDEX($I$9:$I$2008,$W72)),INDEX($I$9:$I$2008,$W72),VALUE(SUBSTITUTE(INDEX($I$9:$I$2008,$W72),",",""))),"")) | AH72: =IF($W72="","",IFERROR(IF(ISNUMBER(INDEX($J$9:$J$2008,$W72)),INDEX($J$9:$J$2008,$W72),VALUE(SUBSTITUTE(INDEX($J$9:$J$2008,$W72),",",""))),"")) | AI72: =IF($W72="","",IFERROR(IF(ISNUMBER(INDEX($K$9:$K$2008,$W72)),INDEX($K$9:$K$2008,$W72),VALUE(SUBSTITUTE(INDEX($K$9:$K$2008,$W72),",",""))),"")) | AJ72: =IF($W72="","",IFERROR(IF(ISNUMBER(INDEX($L$9:$L$2008,$W72)),INDEX($L$9:$L$2008,$W72),VALUE(SUBSTITUTE(INDEX($L$9:$L$2008,$W72),",",""))),"")) | AK72: =IF($W72="","",IFERROR(IF(ISNUMBER(INDEX($M$9:$M$2008,$W72)),INDEX($M$9:$M$2008,$W72),VALUE(SUBSTITUTE(INDEX($M$9:$M$2008,$W72),",",""))),"")) | AL72: =IF($W72="","",IFERROR(IF(ISNUMBER(INDEX($P$9:$P$2008,$W72)),INDEX($P$9:$P$2008,$W72),VALUE(SUBSTITUTE(INDEX($P$9:$P$2008,$W72),"%",""))/100),""))
S73: =IF(AND(ISTEXT($A73),ISNUMBER(SEARCH(" - ",$A73)),ISERROR(SEARCH("Folio",$A73)),$D73=""),TRIM($A73),$S72) | T73: =IF(AND(ISNUMBER(SEARCH("Folio",$A73)),$D73<>""),1,"") | U73: =IF($T73=1,COUNTIF($T$9:$T73,1),"") | V73: =IF(AND(ISTEXT($A73),LEFT($A74,3)="Pan"),1,"") | W73: =IFERROR(MATCH(65,$U$9:$U$2008,0),"") | X73: =IF($W73="","",IF($R$5<>"",$R$5,$R$6)) | Y73: =IF($W73="","",INDEX($S$9:$S$2008,$W73)) | Z73: =IF($W73="","",IFERROR(TRIM(LEFT(SUBSTITUTE(INDEX($A$9:$A$2008,$W73),CHAR(10)," "),SEARCH("Folio",SUBSTITUTE(INDEX($A$9:$A$2008,$W73),CHAR(10)," "))-1)),TRIM(SUBSTITUTE(INDEX($A$9:$A$2008,$W73),CHAR(10)," ")))) | AA73: =IF($W73="","",IFERROR(TRIM(SUBSTITUTE(MID(SUBSTITUTE(INDEX($A$9:$A$2008,$W73),CHAR(10)," "),SEARCH("Folio",SUBSTITUTE(INDEX($A$9:$A$2008,$W73),CHAR(10)," "))+5,200),":","")),"")) | AB73: =IF($W73="","",IF(ISNUMBER(INDEX($D$9:$D$2008,$W73)),INDEX($D$9:$D$2008,$W73),IFERROR(DATE(2000+VALUE(RIGHT(INDEX($D$9:$D$2008,$W73),2)),VALUE(MID(INDEX($D$9:$D$2008,$W73),4,2)),VALUE(LEFT(INDEX($D$9:$D$2008,$W73),2))),""))) | AC73: =IF($W73="","",IFERROR(IF(ISNUMBER(INDEX($E$9:$E$2008,$W73)),INDEX($E$9:$E$2008,$W73),VALUE(SUBSTITUTE(INDEX($E$9:$E$2008,$W73),",",""))),"")) | AD73: =IF($W73="","",IFERROR(IF(ISNUMBER(INDEX($F$9:$F$2008,$W73)),INDEX($F$9:$F$2008,$W73),VALUE(SUBSTITUTE(INDEX($F$9:$F$2008,$W73),",",""))),"")) | AE73: =IF($W73="","",IFERROR(IF(ISNUMBER(INDEX($G$9:$G$2008,$W73)),INDEX($G$9:$G$2008,$W73),VALUE(SUBSTITUTE(INDEX($G$9:$G$2008,$W73),",",""))),"")) | AF73: =IF($W73="","",IFERROR(IF(ISNUMBER(INDEX($H$9:$H$2008,$W73)),INDEX($H$9:$H$2008,$W73),VALUE(SUBSTITUTE(INDEX($H$9:$H$2008,$W73),",",""))),"")) | AG73: =IF($W73="","",IFERROR(IF(ISNUMBER(INDEX($I$9:$I$2008,$W73)),INDEX($I$9:$I$2008,$W73),VALUE(SUBSTITUTE(INDEX($I$9:$I$2008,$W73),",",""))),"")) | AH73: =IF($W73="","",IFERROR(IF(ISNUMBER(INDEX($J$9:$J$2008,$W73)),INDEX($J$9:$J$2008,$W73),VALUE(SUBSTITUTE(INDEX($J$9:$J$2008,$W73),",",""))),"")) | AI73: =IF($W73="","",IFERROR(IF(ISNUMBER(INDEX($K$9:$K$2008,$W73)),INDEX($K$9:$K$2008,$W73),VALUE(SUBSTITUTE(INDEX($K$9:$K$2008,$W73),",",""))),"")) | AJ73: =IF($W73="","",IFERROR(IF(ISNUMBER(INDEX($L$9:$L$2008,$W73)),INDEX($L$9:$L$2008,$W73),VALUE(SUBSTITUTE(INDEX($L$9:$L$2008,$W73),",",""))),"")) | AK73: =IF($W73="","",IFERROR(IF(ISNUMBER(INDEX($M$9:$M$2008,$W73)),INDEX($M$9:$M$2008,$W73),VALUE(SUBSTITUTE(INDEX($M$9:$M$2008,$W73),",",""))),"")) | AL73: =IF($W73="","",IFERROR(IF(ISNUMBER(INDEX($P$9:$P$2008,$W73)),INDEX($P$9:$P$2008,$W73),VALUE(SUBSTITUTE(INDEX($P$9:$P$2008,$W73),"%",""))/100),""))
S74: =IF(AND(ISTEXT($A74),ISNUMBER(SEARCH(" - ",$A74)),ISERROR(SEARCH("Folio",$A74)),$D74=""),TRIM($A74),$S73) | T74: =IF(AND(ISNUMBER(SEARCH("Folio",$A74)),$D74<>""),1,"") | U74: =IF($T74=1,COUNTIF($T$9:$T74,1),"") | V74: =IF(AND(ISTEXT($A74),LEFT($A75,3)="Pan"),1,"") | W74: =IFERROR(MATCH(66,$U$9:$U$2008,0),"") | X74: =IF($W74="","",IF($R$5<>"",$R$5,$R$6)) | Y74: =IF($W74="","",INDEX($S$9:$S$2008,$W74)) | Z74: =IF($W74="","",IFERROR(TRIM(LEFT(SUBSTITUTE(INDEX($A$9:$A$2008,$W74),CHAR(10)," "),SEARCH("Folio",SUBSTITUTE(INDEX($A$9:$A$2008,$W74),CHAR(10)," "))-1)),TRIM(SUBSTITUTE(INDEX($A$9:$A$2008,$W74),CHAR(10)," ")))) | AA74: =IF($W74="","",IFERROR(TRIM(SUBSTITUTE(MID(SUBSTITUTE(INDEX($A$9:$A$2008,$W74),CHAR(10)," "),SEARCH("Folio",SUBSTITUTE(INDEX($A$9:$A$2008,$W74),CHAR(10)," "))+5,200),":","")),"")) | AB74: =IF($W74="","",IF(ISNUMBER(INDEX($D$9:$D$2008,$W74)),INDEX($D$9:$D$2008,$W74),IFERROR(DATE(2000+VALUE(RIGHT(INDEX($D$9:$D$2008,$W74),2)),VALUE(MID(INDEX($D$9:$D$2008,$W74),4,2)),VALUE(LEFT(INDEX($D$9:$D$2008,$W74),2))),""))) | AC74: =IF($W74="","",IFERROR(IF(ISNUMBER(INDEX($E$9:$E$2008,$W74)),INDEX($E$9:$E$2008,$W74),VALUE(SUBSTITUTE(INDEX($E$9:$E$2008,$W74),",",""))),"")) | AD74: =IF($W74="","",IFERROR(IF(ISNUMBER(INDEX($F$9:$F$2008,$W74)),INDEX($F$9:$F$2008,$W74),VALUE(SUBSTITUTE(INDEX($F$9:$F$2008,$W74),",",""))),"")) | AE74: =IF($W74="","",IFERROR(IF(ISNUMBER(INDEX($G$9:$G$2008,$W74)),INDEX($G$9:$G$2008,$W74),VALUE(SUBSTITUTE(INDEX($G$9:$G$2008,$W74),",",""))),"")) | AF74: =IF($W74="","",IFERROR(IF(ISNUMBER(INDEX($H$9:$H$2008,$W74)),INDEX($H$9:$H$2008,$W74),VALUE(SUBSTITUTE(INDEX($H$9:$H$2008,$W74),",",""))),"")) | AG74: =IF($W74="","",IFERROR(IF(ISNUMBER(INDEX($I$9:$I$2008,$W74)),INDEX($I$9:$I$2008,$W74),VALUE(SUBSTITUTE(INDEX($I$9:$I$2008,$W74),",",""))),"")) | AH74: =IF($W74="","",IFERROR(IF(ISNUMBER(INDEX($J$9:$J$2008,$W74)),INDEX($J$9:$J$2008,$W74),VALUE(SUBSTITUTE(INDEX($J$9:$J$2008,$W74),",",""))),"")) | AI74: =IF($W74="","",IFERROR(IF(ISNUMBER(INDEX($K$9:$K$2008,$W74)),INDEX($K$9:$K$2008,$W74),VALUE(SUBSTITUTE(INDEX($K$9:$K$2008,$W74),",",""))),"")) | AJ74: =IF($W74="","",IFERROR(IF(ISNUMBER(INDEX($L$9:$L$2008,$W74)),INDEX($L$9:$L$2008,$W74),VALUE(SUBSTITUTE(INDEX($L$9:$L$2008,$W74),",",""))),"")) | AK74: =IF($W74="","",IFERROR(IF(ISNUMBER(INDEX($M$9:$M$2008,$W74)),INDEX($M$9:$M$2008,$W74),VALUE(SUBSTITUTE(INDEX($M$9:$M$2008,$W74),",",""))),"")) | AL74: =IF($W74="","",IFERROR(IF(ISNUMBER(INDEX($P$9:$P$2008,$W74)),INDEX($P$9:$P$2008,$W74),VALUE(SUBSTITUTE(INDEX($P$9:$P$2008,$W74),"%",""))/100),""))
S75: =IF(AND(ISTEXT($A75),ISNUMBER(SEARCH(" - ",$A75)),ISERROR(SEARCH("Folio",$A75)),$D75=""),TRIM($A75),$S74) | T75: =IF(AND(ISNUMBER(SEARCH("Folio",$A75)),$D75<>""),1,"") | U75: =IF($T75=1,COUNTIF($T$9:$T75,1),"") | V75: =IF(AND(ISTEXT($A75),LEFT($A76,3)="Pan"),1,"") | W75: =IFERROR(MATCH(67,$U$9:$U$2008,0),"") | X75: =IF($W75="","",IF($R$5<>"",$R$5,$R$6)) | Y75: =IF($W75="","",INDEX($S$9:$S$2008,$W75)) | Z75: =IF($W75="","",IFERROR(TRIM(LEFT(SUBSTITUTE(INDEX($A$9:$A$2008,$W75),CHAR(10)," "),SEARCH("Folio",SUBSTITUTE(INDEX($A$9:$A$2008,$W75),CHAR(10)," "))-1)),TRIM(SUBSTITUTE(INDEX($A$9:$A$2008,$W75),CHAR(10)," ")))) | AA75: =IF($W75="","",IFERROR(TRIM(SUBSTITUTE(MID(SUBSTITUTE(INDEX($A$9:$A$2008,$W75),CHAR(10)," "),SEARCH("Folio",SUBSTITUTE(INDEX($A$9:$A$2008,$W75),CHAR(10)," "))+5,200),":","")),"")) | AB75: =IF($W75="","",IF(ISNUMBER(INDEX($D$9:$D$2008,$W75)),INDEX($D$9:$D$2008,$W75),IFERROR(DATE(2000+VALUE(RIGHT(INDEX($D$9:$D$2008,$W75),2)),VALUE(MID(INDEX($D$9:$D$2008,$W75),4,2)),VALUE(LEFT(INDEX($D$9:$D$2008,$W75),2))),""))) | AC75: =IF($W75="","",IFERROR(IF(ISNUMBER(INDEX($E$9:$E$2008,$W75)),INDEX($E$9:$E$2008,$W75),VALUE(SUBSTITUTE(INDEX($E$9:$E$2008,$W75),",",""))),"")) | AD75: =IF($W75="","",IFERROR(IF(ISNUMBER(INDEX($F$9:$F$2008,$W75)),INDEX($F$9:$F$2008,$W75),VALUE(SUBSTITUTE(INDEX($F$9:$F$2008,$W75),",",""))),"")) | AE75: =IF($W75="","",IFERROR(IF(ISNUMBER(INDEX($G$9:$G$2008,$W75)),INDEX($G$9:$G$2008,$W75),VALUE(SUBSTITUTE(INDEX($G$9:$G$2008,$W75),",",""))),"")) | AF75: =IF($W75="","",IFERROR(IF(ISNUMBER(INDEX($H$9:$H$2008,$W75)),INDEX($H$9:$H$2008,$W75),VALUE(SUBSTITUTE(INDEX($H$9:$H$2008,$W75),",",""))),"")) | AG75: =IF($W75="","",IFERROR(IF(ISNUMBER(INDEX($I$9:$I$2008,$W75)),INDEX($I$9:$I$2008,$W75),VALUE(SUBSTITUTE(INDEX($I$9:$I$2008,$W75),",",""))),"")) | AH75: =IF($W75="","",IFERROR(IF(ISNUMBER(INDEX($J$9:$J$2008,$W75)),INDEX($J$9:$J$2008,$W75),VALUE(SUBSTITUTE(INDEX($J$9:$J$2008,$W75),",",""))),"")) | AI75: =IF($W75="","",IFERROR(IF(ISNUMBER(INDEX($K$9:$K$2008,$W75)),INDEX($K$9:$K$2008,$W75),VALUE(SUBSTITUTE(INDEX($K$9:$K$2008,$W75),",",""))),"")) | AJ75: =IF($W75="","",IFERROR(IF(ISNUMBER(INDEX($L$9:$L$2008,$W75)),INDEX($L$9:$L$2008,$W75),VALUE(SUBSTITUTE(INDEX($L$9:$L$2008,$W75),",",""))),"")) | AK75: =IF($W75="","",IFERROR(IF(ISNUMBER(INDEX($M$9:$M$2008,$W75)),INDEX($M$9:$M$2008,$W75),VALUE(SUBSTITUTE(INDEX($M$9:$M$2008,$W75),",",""))),"")) | AL75: =IF($W75="","",IFERROR(IF(ISNUMBER(INDEX($P$9:$P$2008,$W75)),INDEX($P$9:$P$2008,$W75),VALUE(SUBSTITUTE(INDEX($P$9:$P$2008,$W75),"%",""))/100),""))
S76: =IF(AND(ISTEXT($A76),ISNUMBER(SEARCH(" - ",$A76)),ISERROR(SEARCH("Folio",$A76)),$D76=""),TRIM($A76),$S75) | T76: =IF(AND(ISNUMBER(SEARCH("Folio",$A76)),$D76<>""),1,"") | U76: =IF($T76=1,COUNTIF($T$9:$T76,1),"") | V76: =IF(AND(ISTEXT($A76),LEFT($A77,3)="Pan"),1,"") | W76: =IFERROR(MATCH(68,$U$9:$U$2008,0),"") | X76: =IF($W76="","",IF($R$5<>"",$R$5,$R$6)) | Y76: =IF($W76="","",INDEX($S$9:$S$2008,$W76)) | Z76: =IF($W76="","",IFERROR(TRIM(LEFT(SUBSTITUTE(INDEX($A$9:$A$2008,$W76),CHAR(10)," "),SEARCH("Folio",SUBSTITUTE(INDEX($A$9:$A$2008,$W76),CHAR(10)," "))-1)),TRIM(SUBSTITUTE(INDEX($A$9:$A$2008,$W76),CHAR(10)," ")))) | AA76: =IF($W76="","",IFERROR(TRIM(SUBSTITUTE(MID(SUBSTITUTE(INDEX($A$9:$A$2008,$W76),CHAR(10)," "),SEARCH("Folio",SUBSTITUTE(INDEX($A$9:$A$2008,$W76),CHAR(10)," "))+5,200),":","")),"")) | AB76: =IF($W76="","",IF(ISNUMBER(INDEX($D$9:$D$2008,$W76)),INDEX($D$9:$D$2008,$W76),IFERROR(DATE(2000+VALUE(RIGHT(INDEX($D$9:$D$2008,$W76),2)),VALUE(MID(INDEX($D$9:$D$2008,$W76),4,2)),VALUE(LEFT(INDEX($D$9:$D$2008,$W76),2))),""))) | AC76: =IF($W76="","",IFERROR(IF(ISNUMBER(INDEX($E$9:$E$2008,$W76)),INDEX($E$9:$E$2008,$W76),VALUE(SUBSTITUTE(INDEX($E$9:$E$2008,$W76),",",""))),"")) | AD76: =IF($W76="","",IFERROR(IF(ISNUMBER(INDEX($F$9:$F$2008,$W76)),INDEX($F$9:$F$2008,$W76),VALUE(SUBSTITUTE(INDEX($F$9:$F$2008,$W76),",",""))),"")) | AE76: =IF($W76="","",IFERROR(IF(ISNUMBER(INDEX($G$9:$G$2008,$W76)),INDEX($G$9:$G$2008,$W76),VALUE(SUBSTITUTE(INDEX($G$9:$G$2008,$W76),",",""))),"")) | AF76: =IF($W76="","",IFERROR(IF(ISNUMBER(INDEX($H$9:$H$2008,$W76)),INDEX($H$9:$H$2008,$W76),VALUE(SUBSTITUTE(INDEX($H$9:$H$2008,$W76),",",""))),"")) | AG76: =IF($W76="","",IFERROR(IF(ISNUMBER(INDEX($I$9:$I$2008,$W76)),INDEX($I$9:$I$2008,$W76),VALUE(SUBSTITUTE(INDEX($I$9:$I$2008,$W76),",",""))),"")) | AH76: =IF($W76="","",IFERROR(IF(ISNUMBER(INDEX($J$9:$J$2008,$W76)),INDEX($J$9:$J$2008,$W76),VALUE(SUBSTITUTE(INDEX($J$9:$J$2008,$W76),",",""))),"")) | AI76: =IF($W76="","",IFERROR(IF(ISNUMBER(INDEX($K$9:$K$2008,$W76)),INDEX($K$9:$K$2008,$W76),VALUE(SUBSTITUTE(INDEX($K$9:$K$2008,$W76),",",""))),"")) | AJ76: =IF($W76="","",IFERROR(IF(ISNUMBER(INDEX($L$9:$L$2008,$W76)),INDEX($L$9:$L$2008,$W76),VALUE(SUBSTITUTE(INDEX($L$9:$L$2008,$W76),",",""))),"")) | AK76: =IF($W76="","",IFERROR(IF(ISNUMBER(INDEX($M$9:$M$2008,$W76)),INDEX($M$9:$M$2008,$W76),VALUE(SUBSTITUTE(INDEX($M$9:$M$2008,$W76),",",""))),"")) | AL76: =IF($W76="","",IFERROR(IF(ISNUMBER(INDEX($P$9:$P$2008,$W76)),INDEX($P$9:$P$2008,$W76),VALUE(SUBSTITUTE(INDEX($P$9:$P$2008,$W76),"%",""))/100),""))
S77: =IF(AND(ISTEXT($A77),ISNUMBER(SEARCH(" - ",$A77)),ISERROR(SEARCH("Folio",$A77)),$D77=""),TRIM($A77),$S76) | T77: =IF(AND(ISNUMBER(SEARCH("Folio",$A77)),$D77<>""),1,"") | U77: =IF($T77=1,COUNTIF($T$9:$T77,1),"") | V77: =IF(AND(ISTEXT($A77),LEFT($A78,3)="Pan"),1,"") | W77: =IFERROR(MATCH(69,$U$9:$U$2008,0),"") | X77: =IF($W77="","",IF($R$5<>"",$R$5,$R$6)) | Y77: =IF($W77="","",INDEX($S$9:$S$2008,$W77)) | Z77: =IF($W77="","",IFERROR(TRIM(LEFT(SUBSTITUTE(INDEX($A$9:$A$2008,$W77),CHAR(10)," "),SEARCH("Folio",SUBSTITUTE(INDEX($A$9:$A$2008,$W77),CHAR(10)," "))-1)),TRIM(SUBSTITUTE(INDEX($A$9:$A$2008,$W77),CHAR(10)," ")))) | AA77: =IF($W77="","",IFERROR(TRIM(SUBSTITUTE(MID(SUBSTITUTE(INDEX($A$9:$A$2008,$W77),CHAR(10)," "),SEARCH("Folio",SUBSTITUTE(INDEX($A$9:$A$2008,$W77),CHAR(10)," "))+5,200),":","")),"")) | AB77: =IF($W77="","",IF(ISNUMBER(INDEX($D$9:$D$2008,$W77)),INDEX($D$9:$D$2008,$W77),IFERROR(DATE(2000+VALUE(RIGHT(INDEX($D$9:$D$2008,$W77),2)),VALUE(MID(INDEX($D$9:$D$2008,$W77),4,2)),VALUE(LEFT(INDEX($D$9:$D$2008,$W77),2))),""))) | AC77: =IF($W77="","",IFERROR(IF(ISNUMBER(INDEX($E$9:$E$2008,$W77)),INDEX($E$9:$E$2008,$W77),VALUE(SUBSTITUTE(INDEX($E$9:$E$2008,$W77),",",""))),"")) | AD77: =IF($W77="","",IFERROR(IF(ISNUMBER(INDEX($F$9:$F$2008,$W77)),INDEX($F$9:$F$2008,$W77),VALUE(SUBSTITUTE(INDEX($F$9:$F$2008,$W77),",",""))),"")) | AE77: =IF($W77="","",IFERROR(IF(ISNUMBER(INDEX($G$9:$G$2008,$W77)),INDEX($G$9:$G$2008,$W77),VALUE(SUBSTITUTE(INDEX($G$9:$G$2008,$W77),",",""))),"")) | AF77: =IF($W77="","",IFERROR(IF(ISNUMBER(INDEX($H$9:$H$2008,$W77)),INDEX($H$9:$H$2008,$W77),VALUE(SUBSTITUTE(INDEX($H$9:$H$2008,$W77),",",""))),"")) | AG77: =IF($W77="","",IFERROR(IF(ISNUMBER(INDEX($I$9:$I$2008,$W77)),INDEX($I$9:$I$2008,$W77),VALUE(SUBSTITUTE(INDEX($I$9:$I$2008,$W77),",",""))),"")) | AH77: =IF($W77="","",IFERROR(IF(ISNUMBER(INDEX($J$9:$J$2008,$W77)),INDEX($J$9:$J$2008,$W77),VALUE(SUBSTITUTE(INDEX($J$9:$J$2008,$W77),",",""))),"")) | AI77: =IF($W77="","",IFERROR(IF(ISNUMBER(INDEX($K$9:$K$2008,$W77)),INDEX($K$9:$K$2008,$W77),VALUE(SUBSTITUTE(INDEX($K$9:$K$2008,$W77),",",""))),"")) | AJ77: =IF($W77="","",IFERROR(IF(ISNUMBER(INDEX($L$9:$L$2008,$W77)),INDEX($L$9:$L$2008,$W77),VALUE(SUBSTITUTE(INDEX($L$9:$L$2008,$W77),",",""))),"")) | AK77: =IF($W77="","",IFERROR(IF(ISNUMBER(INDEX($M$9:$M$2008,$W77)),INDEX($M$9:$M$2008,$W77),VALUE(SUBSTITUTE(INDEX($M$9:$M$2008,$W77),",",""))),"")) | AL77: =IF($W77="","",IFERROR(IF(ISNUMBER(INDEX($P$9:$P$2008,$W77)),INDEX($P$9:$P$2008,$W77),VALUE(SUBSTITUTE(INDEX($P$9:$P$2008,$W77),"%",""))/100),""))
S78: =IF(AND(ISTEXT($A78),ISNUMBER(SEARCH(" - ",$A78)),ISERROR(SEARCH("Folio",$A78)),$D78=""),TRIM($A78),$S77) | T78: =IF(AND(ISNUMBER(SEARCH("Folio",$A78)),$D78<>""),1,"") | U78: =IF($T78=1,COUNTIF($T$9:$T78,1),"") | V78: =IF(AND(ISTEXT($A78),LEFT($A79,3)="Pan"),1,"") | W78: =IFERROR(MATCH(70,$U$9:$U$2008,0),"") | X78: =IF($W78="","",IF($R$5<>"",$R$5,$R$6)) | Y78: =IF($W78="","",INDEX($S$9:$S$2008,$W78)) | Z78: =IF($W78="","",IFERROR(TRIM(LEFT(SUBSTITUTE(INDEX($A$9:$A$2008,$W78),CHAR(10)," "),SEARCH("Folio",SUBSTITUTE(INDEX($A$9:$A$2008,$W78),CHAR(10)," "))-1)),TRIM(SUBSTITUTE(INDEX($A$9:$A$2008,$W78),CHAR(10)," ")))) | AA78: =IF($W78="","",IFERROR(TRIM(SUBSTITUTE(MID(SUBSTITUTE(INDEX($A$9:$A$2008,$W78),CHAR(10)," "),SEARCH("Folio",SUBSTITUTE(INDEX($A$9:$A$2008,$W78),CHAR(10)," "))+5,200),":","")),"")) | AB78: =IF($W78="","",IF(ISNUMBER(INDEX($D$9:$D$2008,$W78)),INDEX($D$9:$D$2008,$W78),IFERROR(DATE(2000+VALUE(RIGHT(INDEX($D$9:$D$2008,$W78),2)),VALUE(MID(INDEX($D$9:$D$2008,$W78),4,2)),VALUE(LEFT(INDEX($D$9:$D$2008,$W78),2))),""))) | AC78: =IF($W78="","",IFERROR(IF(ISNUMBER(INDEX($E$9:$E$2008,$W78)),INDEX($E$9:$E$2008,$W78),VALUE(SUBSTITUTE(INDEX($E$9:$E$2008,$W78),",",""))),"")) | AD78: =IF($W78="","",IFERROR(IF(ISNUMBER(INDEX($F$9:$F$2008,$W78)),INDEX($F$9:$F$2008,$W78),VALUE(SUBSTITUTE(INDEX($F$9:$F$2008,$W78),",",""))),"")) | AE78: =IF($W78="","",IFERROR(IF(ISNUMBER(INDEX($G$9:$G$2008,$W78)),INDEX($G$9:$G$2008,$W78),VALUE(SUBSTITUTE(INDEX($G$9:$G$2008,$W78),",",""))),"")) | AF78: =IF($W78="","",IFERROR(IF(ISNUMBER(INDEX($H$9:$H$2008,$W78)),INDEX($H$9:$H$2008,$W78),VALUE(SUBSTITUTE(INDEX($H$9:$H$2008,$W78),",",""))),"")) | AG78: =IF($W78="","",IFERROR(IF(ISNUMBER(INDEX($I$9:$I$2008,$W78)),INDEX($I$9:$I$2008,$W78),VALUE(SUBSTITUTE(INDEX($I$9:$I$2008,$W78),",",""))),"")) | AH78: =IF($W78="","",IFERROR(IF(ISNUMBER(INDEX($J$9:$J$2008,$W78)),INDEX($J$9:$J$2008,$W78),VALUE(SUBSTITUTE(INDEX($J$9:$J$2008,$W78),",",""))),"")) | AI78: =IF($W78="","",IFERROR(IF(ISNUMBER(INDEX($K$9:$K$2008,$W78)),INDEX($K$9:$K$2008,$W78),VALUE(SUBSTITUTE(INDEX($K$9:$K$2008,$W78),",",""))),"")) | AJ78: =IF($W78="","",IFERROR(IF(ISNUMBER(INDEX($L$9:$L$2008,$W78)),INDEX($L$9:$L$2008,$W78),VALUE(SUBSTITUTE(INDEX($L$9:$L$2008,$W78),",",""))),"")) | AK78: =IF($W78="","",IFERROR(IF(ISNUMBER(INDEX($M$9:$M$2008,$W78)),INDEX($M$9:$M$2008,$W78),VALUE(SUBSTITUTE(INDEX($M$9:$M$2008,$W78),",",""))),"")) | AL78: =IF($W78="","",IFERROR(IF(ISNUMBER(INDEX($P$9:$P$2008,$W78)),INDEX($P$9:$P$2008,$W78),VALUE(SUBSTITUTE(INDEX($P$9:$P$2008,$W78),"%",""))/100),""))
S79: =IF(AND(ISTEXT($A79),ISNUMBER(SEARCH(" - ",$A79)),ISERROR(SEARCH("Folio",$A79)),$D79=""),TRIM($A79),$S78) | T79: =IF(AND(ISNUMBER(SEARCH("Folio",$A79)),$D79<>""),1,"") | U79: =IF($T79=1,COUNTIF($T$9:$T79,1),"") | V79: =IF(AND(ISTEXT($A79),LEFT($A80,3)="Pan"),1,"") | W79: =IFERROR(MATCH(71,$U$9:$U$2008,0),"") | X79: =IF($W79="","",IF($R$5<>"",$R$5,$R$6)) | Y79: =IF($W79="","",INDEX($S$9:$S$2008,$W79)) | Z79: =IF($W79="","",IFERROR(TRIM(LEFT(SUBSTITUTE(INDEX($A$9:$A$2008,$W79),CHAR(10)," "),SEARCH("Folio",SUBSTITUTE(INDEX($A$9:$A$2008,$W79),CHAR(10)," "))-1)),TRIM(SUBSTITUTE(INDEX($A$9:$A$2008,$W79),CHAR(10)," ")))) | AA79: =IF($W79="","",IFERROR(TRIM(SUBSTITUTE(MID(SUBSTITUTE(INDEX($A$9:$A$2008,$W79),CHAR(10)," "),SEARCH("Folio",SUBSTITUTE(INDEX($A$9:$A$2008,$W79),CHAR(10)," "))+5,200),":","")),"")) | AB79: =IF($W79="","",IF(ISNUMBER(INDEX($D$9:$D$2008,$W79)),INDEX($D$9:$D$2008,$W79),IFERROR(DATE(2000+VALUE(RIGHT(INDEX($D$9:$D$2008,$W79),2)),VALUE(MID(INDEX($D$9:$D$2008,$W79),4,2)),VALUE(LEFT(INDEX($D$9:$D$2008,$W79),2))),""))) | AC79: =IF($W79="","",IFERROR(IF(ISNUMBER(INDEX($E$9:$E$2008,$W79)),INDEX($E$9:$E$2008,$W79),VALUE(SUBSTITUTE(INDEX($E$9:$E$2008,$W79),",",""))),"")) | AD79: =IF($W79="","",IFERROR(IF(ISNUMBER(INDEX($F$9:$F$2008,$W79)),INDEX($F$9:$F$2008,$W79),VALUE(SUBSTITUTE(INDEX($F$9:$F$2008,$W79),",",""))),"")) | AE79: =IF($W79="","",IFERROR(IF(ISNUMBER(INDEX($G$9:$G$2008,$W79)),INDEX($G$9:$G$2008,$W79),VALUE(SUBSTITUTE(INDEX($G$9:$G$2008,$W79),",",""))),"")) | AF79: =IF($W79="","",IFERROR(IF(ISNUMBER(INDEX($H$9:$H$2008,$W79)),INDEX($H$9:$H$2008,$W79),VALUE(SUBSTITUTE(INDEX($H$9:$H$2008,$W79),",",""))),"")) | AG79: =IF($W79="","",IFERROR(IF(ISNUMBER(INDEX($I$9:$I$2008,$W79)),INDEX($I$9:$I$2008,$W79),VALUE(SUBSTITUTE(INDEX($I$9:$I$2008,$W79),",",""))),"")) | AH79: =IF($W79="","",IFERROR(IF(ISNUMBER(INDEX($J$9:$J$2008,$W79)),INDEX($J$9:$J$2008,$W79),VALUE(SUBSTITUTE(INDEX($J$9:$J$2008,$W79),",",""))),"")) | AI79: =IF($W79="","",IFERROR(IF(ISNUMBER(INDEX($K$9:$K$2008,$W79)),INDEX($K$9:$K$2008,$W79),VALUE(SUBSTITUTE(INDEX($K$9:$K$2008,$W79),",",""))),"")) | AJ79: =IF($W79="","",IFERROR(IF(ISNUMBER(INDEX($L$9:$L$2008,$W79)),INDEX($L$9:$L$2008,$W79),VALUE(SUBSTITUTE(INDEX($L$9:$L$2008,$W79),",",""))),"")) | AK79: =IF($W79="","",IFERROR(IF(ISNUMBER(INDEX($M$9:$M$2008,$W79)),INDEX($M$9:$M$2008,$W79),VALUE(SUBSTITUTE(INDEX($M$9:$M$2008,$W79),",",""))),"")) | AL79: =IF($W79="","",IFERROR(IF(ISNUMBER(INDEX($P$9:$P$2008,$W79)),INDEX($P$9:$P$2008,$W79),VALUE(SUBSTITUTE(INDEX($P$9:$P$2008,$W79),"%",""))/100),""))
S80: =IF(AND(ISTEXT($A80),ISNUMBER(SEARCH(" - ",$A80)),ISERROR(SEARCH("Folio",$A80)),$D80=""),TRIM($A80),$S79) | T80: =IF(AND(ISNUMBER(SEARCH("Folio",$A80)),$D80<>""),1,"") | U80: =IF($T80=1,COUNTIF($T$9:$T80,1),"") | V80: =IF(AND(ISTEXT($A80),LEFT($A81,3)="Pan"),1,"") | W80: =IFERROR(MATCH(72,$U$9:$U$2008,0),"") | X80: =IF($W80="","",IF($R$5<>"",$R$5,$R$6)) | Y80: =IF($W80="","",INDEX($S$9:$S$2008,$W80)) | Z80: =IF($W80="","",IFERROR(TRIM(LEFT(SUBSTITUTE(INDEX($A$9:$A$2008,$W80),CHAR(10)," "),SEARCH("Folio",SUBSTITUTE(INDEX($A$9:$A$2008,$W80),CHAR(10)," "))-1)),TRIM(SUBSTITUTE(INDEX($A$9:$A$2008,$W80),CHAR(10)," ")))) | AA80: =IF($W80="","",IFERROR(TRIM(SUBSTITUTE(MID(SUBSTITUTE(INDEX($A$9:$A$2008,$W80),CHAR(10)," "),SEARCH("Folio",SUBSTITUTE(INDEX($A$9:$A$2008,$W80),CHAR(10)," "))+5,200),":","")),"")) | AB80: =IF($W80="","",IF(ISNUMBER(INDEX($D$9:$D$2008,$W80)),INDEX($D$9:$D$2008,$W80),IFERROR(DATE(2000+VALUE(RIGHT(INDEX($D$9:$D$2008,$W80),2)),VALUE(MID(INDEX($D$9:$D$2008,$W80),4,2)),VALUE(LEFT(INDEX($D$9:$D$2008,$W80),2))),""))) | AC80: =IF($W80="","",IFERROR(IF(ISNUMBER(INDEX($E$9:$E$2008,$W80)),INDEX($E$9:$E$2008,$W80),VALUE(SUBSTITUTE(INDEX($E$9:$E$2008,$W80),",",""))),"")) | AD80: =IF($W80="","",IFERROR(IF(ISNUMBER(INDEX($F$9:$F$2008,$W80)),INDEX($F$9:$F$2008,$W80),VALUE(SUBSTITUTE(INDEX($F$9:$F$2008,$W80),",",""))),"")) | AE80: =IF($W80="","",IFERROR(IF(ISNUMBER(INDEX($G$9:$G$2008,$W80)),INDEX($G$9:$G$2008,$W80),VALUE(SUBSTITUTE(INDEX($G$9:$G$2008,$W80),",",""))),"")) | AF80: =IF($W80="","",IFERROR(IF(ISNUMBER(INDEX($H$9:$H$2008,$W80)),INDEX($H$9:$H$2008,$W80),VALUE(SUBSTITUTE(INDEX($H$9:$H$2008,$W80),",",""))),"")) | AG80: =IF($W80="","",IFERROR(IF(ISNUMBER(INDEX($I$9:$I$2008,$W80)),INDEX($I$9:$I$2008,$W80),VALUE(SUBSTITUTE(INDEX($I$9:$I$2008,$W80),",",""))),"")) | AH80: =IF($W80="","",IFERROR(IF(ISNUMBER(INDEX($J$9:$J$2008,$W80)),INDEX($J$9:$J$2008,$W80),VALUE(SUBSTITUTE(INDEX($J$9:$J$2008,$W80),",",""))),"")) | AI80: =IF($W80="","",IFERROR(IF(ISNUMBER(INDEX($K$9:$K$2008,$W80)),INDEX($K$9:$K$2008,$W80),VALUE(SUBSTITUTE(INDEX($K$9:$K$2008,$W80),",",""))),"")) | AJ80: =IF($W80="","",IFERROR(IF(ISNUMBER(INDEX($L$9:$L$2008,$W80)),INDEX($L$9:$L$2008,$W80),VALUE(SUBSTITUTE(INDEX($L$9:$L$2008,$W80),",",""))),"")) | AK80: =IF($W80="","",IFERROR(IF(ISNUMBER(INDEX($M$9:$M$2008,$W80)),INDEX($M$9:$M$2008,$W80),VALUE(SUBSTITUTE(INDEX($M$9:$M$2008,$W80),",",""))),"")) | AL80: =IF($W80="","",IFERROR(IF(ISNUMBER(INDEX($P$9:$P$2008,$W80)),INDEX($P$9:$P$2008,$W80),VALUE(SUBSTITUTE(INDEX($P$9:$P$2008,$W80),"%",""))/100),""))
S81: =IF(AND(ISTEXT($A81),ISNUMBER(SEARCH(" - ",$A81)),ISERROR(SEARCH("Folio",$A81)),$D81=""),TRIM($A81),$S80) | T81: =IF(AND(ISNUMBER(SEARCH("Folio",$A81)),$D81<>""),1,"") | U81: =IF($T81=1,COUNTIF($T$9:$T81,1),"") | V81: =IF(AND(ISTEXT($A81),LEFT($A82,3)="Pan"),1,"") | W81: =IFERROR(MATCH(73,$U$9:$U$2008,0),"") | X81: =IF($W81="","",IF($R$5<>"",$R$5,$R$6)) | Y81: =IF($W81="","",INDEX($S$9:$S$2008,$W81)) | Z81: =IF($W81="","",IFERROR(TRIM(LEFT(SUBSTITUTE(INDEX($A$9:$A$2008,$W81),CHAR(10)," "),SEARCH("Folio",SUBSTITUTE(INDEX($A$9:$A$2008,$W81),CHAR(10)," "))-1)),TRIM(SUBSTITUTE(INDEX($A$9:$A$2008,$W81),CHAR(10)," ")))) | AA81: =IF($W81="","",IFERROR(TRIM(SUBSTITUTE(MID(SUBSTITUTE(INDEX($A$9:$A$2008,$W81),CHAR(10)," "),SEARCH("Folio",SUBSTITUTE(INDEX($A$9:$A$2008,$W81),CHAR(10)," "))+5,200),":","")),"")) | AB81: =IF($W81="","",IF(ISNUMBER(INDEX($D$9:$D$2008,$W81)),INDEX($D$9:$D$2008,$W81),IFERROR(DATE(2000+VALUE(RIGHT(INDEX($D$9:$D$2008,$W81),2)),VALUE(MID(INDEX($D$9:$D$2008,$W81),4,2)),VALUE(LEFT(INDEX($D$9:$D$2008,$W81),2))),""))) | AC81: =IF($W81="","",IFERROR(IF(ISNUMBER(INDEX($E$9:$E$2008,$W81)),INDEX($E$9:$E$2008,$W81),VALUE(SUBSTITUTE(INDEX($E$9:$E$2008,$W81),",",""))),"")) | AD81: =IF($W81="","",IFERROR(IF(ISNUMBER(INDEX($F$9:$F$2008,$W81)),INDEX($F$9:$F$2008,$W81),VALUE(SUBSTITUTE(INDEX($F$9:$F$2008,$W81),",",""))),"")) | AE81: =IF($W81="","",IFERROR(IF(ISNUMBER(INDEX($G$9:$G$2008,$W81)),INDEX($G$9:$G$2008,$W81),VALUE(SUBSTITUTE(INDEX($G$9:$G$2008,$W81),",",""))),"")) | AF81: =IF($W81="","",IFERROR(IF(ISNUMBER(INDEX($H$9:$H$2008,$W81)),INDEX($H$9:$H$2008,$W81),VALUE(SUBSTITUTE(INDEX($H$9:$H$2008,$W81),",",""))),"")) | AG81: =IF($W81="","",IFERROR(IF(ISNUMBER(INDEX($I$9:$I$2008,$W81)),INDEX($I$9:$I$2008,$W81),VALUE(SUBSTITUTE(INDEX($I$9:$I$2008,$W81),",",""))),"")) | AH81: =IF($W81="","",IFERROR(IF(ISNUMBER(INDEX($J$9:$J$2008,$W81)),INDEX($J$9:$J$2008,$W81),VALUE(SUBSTITUTE(INDEX($J$9:$J$2008,$W81),",",""))),"")) | AI81: =IF($W81="","",IFERROR(IF(ISNUMBER(INDEX($K$9:$K$2008,$W81)),INDEX($K$9:$K$2008,$W81),VALUE(SUBSTITUTE(INDEX($K$9:$K$2008,$W81),",",""))),"")) | AJ81: =IF($W81="","",IFERROR(IF(ISNUMBER(INDEX($L$9:$L$2008,$W81)),INDEX($L$9:$L$2008,$W81),VALUE(SUBSTITUTE(INDEX($L$9:$L$2008,$W81),",",""))),"")) | AK81: =IF($W81="","",IFERROR(IF(ISNUMBER(INDEX($M$9:$M$2008,$W81)),INDEX($M$9:$M$2008,$W81),VALUE(SUBSTITUTE(INDEX($M$9:$M$2008,$W81),",",""))),"")) | AL81: =IF($W81="","",IFERROR(IF(ISNUMBER(INDEX($P$9:$P$2008,$W81)),INDEX($P$9:$P$2008,$W81),VALUE(SUBSTITUTE(INDEX($P$9:$P$2008,$W81),"%",""))/100),""))
S82: =IF(AND(ISTEXT($A82),ISNUMBER(SEARCH(" - ",$A82)),ISERROR(SEARCH("Folio",$A82)),$D82=""),TRIM($A82),$S81) | T82: =IF(AND(ISNUMBER(SEARCH("Folio",$A82)),$D82<>""),1,"") | U82: =IF($T82=1,COUNTIF($T$9:$T82,1),"") | V82: =IF(AND(ISTEXT($A82),LEFT($A83,3)="Pan"),1,"") | W82: =IFERROR(MATCH(74,$U$9:$U$2008,0),"") | X82: =IF($W82="","",IF($R$5<>"",$R$5,$R$6)) | Y82: =IF($W82="","",INDEX($S$9:$S$2008,$W82)) | Z82: =IF($W82="","",IFERROR(TRIM(LEFT(SUBSTITUTE(INDEX($A$9:$A$2008,$W82),CHAR(10)," "),SEARCH("Folio",SUBSTITUTE(INDEX($A$9:$A$2008,$W82),CHAR(10)," "))-1)),TRIM(SUBSTITUTE(INDEX($A$9:$A$2008,$W82),CHAR(10)," ")))) | AA82: =IF($W82="","",IFERROR(TRIM(SUBSTITUTE(MID(SUBSTITUTE(INDEX($A$9:$A$2008,$W82),CHAR(10)," "),SEARCH("Folio",SUBSTITUTE(INDEX($A$9:$A$2008,$W82),CHAR(10)," "))+5,200),":","")),"")) | AB82: =IF($W82="","",IF(ISNUMBER(INDEX($D$9:$D$2008,$W82)),INDEX($D$9:$D$2008,$W82),IFERROR(DATE(2000+VALUE(RIGHT(INDEX($D$9:$D$2008,$W82),2)),VALUE(MID(INDEX($D$9:$D$2008,$W82),4,2)),VALUE(LEFT(INDEX($D$9:$D$2008,$W82),2))),""))) | AC82: =IF($W82="","",IFERROR(IF(ISNUMBER(INDEX($E$9:$E$2008,$W82)),INDEX($E$9:$E$2008,$W82),VALUE(SUBSTITUTE(INDEX($E$9:$E$2008,$W82),",",""))),"")) | AD82: =IF($W82="","",IFERROR(IF(ISNUMBER(INDEX($F$9:$F$2008,$W82)),INDEX($F$9:$F$2008,$W82),VALUE(SUBSTITUTE(INDEX($F$9:$F$2008,$W82),",",""))),"")) | AE82: =IF($W82="","",IFERROR(IF(ISNUMBER(INDEX($G$9:$G$2008,$W82)),INDEX($G$9:$G$2008,$W82),VALUE(SUBSTITUTE(INDEX($G$9:$G$2008,$W82),",",""))),"")) | AF82: =IF($W82="","",IFERROR(IF(ISNUMBER(INDEX($H$9:$H$2008,$W82)),INDEX($H$9:$H$2008,$W82),VALUE(SUBSTITUTE(INDEX($H$9:$H$2008,$W82),",",""))),"")) | AG82: =IF($W82="","",IFERROR(IF(ISNUMBER(INDEX($I$9:$I$2008,$W82)),INDEX($I$9:$I$2008,$W82),VALUE(SUBSTITUTE(INDEX($I$9:$I$2008,$W82),",",""))),"")) | AH82: =IF($W82="","",IFERROR(IF(ISNUMBER(INDEX($J$9:$J$2008,$W82)),INDEX($J$9:$J$2008,$W82),VALUE(SUBSTITUTE(INDEX($J$9:$J$2008,$W82),",",""))),"")) | AI82: =IF($W82="","",IFERROR(IF(ISNUMBER(INDEX($K$9:$K$2008,$W82)),INDEX($K$9:$K$2008,$W82),VALUE(SUBSTITUTE(INDEX($K$9:$K$2008,$W82),",",""))),"")) | AJ82: =IF($W82="","",IFERROR(IF(ISNUMBER(INDEX($L$9:$L$2008,$W82)),INDEX($L$9:$L$2008,$W82),VALUE(SUBSTITUTE(INDEX($L$9:$L$2008,$W82),",",""))),"")) | AK82: =IF($W82="","",IFERROR(IF(ISNUMBER(INDEX($M$9:$M$2008,$W82)),INDEX($M$9:$M$2008,$W82),VALUE(SUBSTITUTE(INDEX($M$9:$M$2008,$W82),",",""))),"")) | AL82: =IF($W82="","",IFERROR(IF(ISNUMBER(INDEX($P$9:$P$2008,$W82)),INDEX($P$9:$P$2008,$W82),VALUE(SUBSTITUTE(INDEX($P$9:$P$2008,$W82),"%",""))/100),""))
S83: =IF(AND(ISTEXT($A83),ISNUMBER(SEARCH(" - ",$A83)),ISERROR(SEARCH("Folio",$A83)),$D83=""),TRIM($A83),$S82) | T83: =IF(AND(ISNUMBER(SEARCH("Folio",$A83)),$D83<>""),1,"") | U83: =IF($T83=1,COUNTIF($T$9:$T83,1),"") | V83: =IF(AND(ISTEXT($A83),LEFT($A84,3)="Pan"),1,"") | W83: =IFERROR(MATCH(75,$U$9:$U$2008,0),"") | X83: =IF($W83="","",IF($R$5<>"",$R$5,$R$6)) | Y83: =IF($W83="","",INDEX($S$9:$S$2008,$W83)) | Z83: =IF($W83="","",IFERROR(TRIM(LEFT(SUBSTITUTE(INDEX($A$9:$A$2008,$W83),CHAR(10)," "),SEARCH("Folio",SUBSTITUTE(INDEX($A$9:$A$2008,$W83),CHAR(10)," "))-1)),TRIM(SUBSTITUTE(INDEX($A$9:$A$2008,$W83),CHAR(10)," ")))) | AA83: =IF($W83="","",IFERROR(TRIM(SUBSTITUTE(MID(SUBSTITUTE(INDEX($A$9:$A$2008,$W83),CHAR(10)," "),SEARCH("Folio",SUBSTITUTE(INDEX($A$9:$A$2008,$W83),CHAR(10)," "))+5,200),":","")),"")) | AB83: =IF($W83="","",IF(ISNUMBER(INDEX($D$9:$D$2008,$W83)),INDEX($D$9:$D$2008,$W83),IFERROR(DATE(2000+VALUE(RIGHT(INDEX($D$9:$D$2008,$W83),2)),VALUE(MID(INDEX($D$9:$D$2008,$W83),4,2)),VALUE(LEFT(INDEX($D$9:$D$2008,$W83),2))),""))) | AC83: =IF($W83="","",IFERROR(IF(ISNUMBER(INDEX($E$9:$E$2008,$W83)),INDEX($E$9:$E$2008,$W83),VALUE(SUBSTITUTE(INDEX($E$9:$E$2008,$W83),",",""))),"")) | AD83: =IF($W83="","",IFERROR(IF(ISNUMBER(INDEX($F$9:$F$2008,$W83)),INDEX($F$9:$F$2008,$W83),VALUE(SUBSTITUTE(INDEX($F$9:$F$2008,$W83),",",""))),"")) | AE83: =IF($W83="","",IFERROR(IF(ISNUMBER(INDEX($G$9:$G$2008,$W83)),INDEX($G$9:$G$2008,$W83),VALUE(SUBSTITUTE(INDEX($G$9:$G$2008,$W83),",",""))),"")) | AF83: =IF($W83="","",IFERROR(IF(ISNUMBER(INDEX($H$9:$H$2008,$W83)),INDEX($H$9:$H$2008,$W83),VALUE(SUBSTITUTE(INDEX($H$9:$H$2008,$W83),",",""))),"")) | AG83: =IF($W83="","",IFERROR(IF(ISNUMBER(INDEX($I$9:$I$2008,$W83)),INDEX($I$9:$I$2008,$W83),VALUE(SUBSTITUTE(INDEX($I$9:$I$2008,$W83),",",""))),"")) | AH83: =IF($W83="","",IFERROR(IF(ISNUMBER(INDEX($J$9:$J$2008,$W83)),INDEX($J$9:$J$2008,$W83),VALUE(SUBSTITUTE(INDEX($J$9:$J$2008,$W83),",",""))),"")) | AI83: =IF($W83="","",IFERROR(IF(ISNUMBER(INDEX($K$9:$K$2008,$W83)),INDEX($K$9:$K$2008,$W83),VALUE(SUBSTITUTE(INDEX($K$9:$K$2008,$W83),",",""))),"")) | AJ83: =IF($W83="","",IFERROR(IF(ISNUMBER(INDEX($L$9:$L$2008,$W83)),INDEX($L$9:$L$2008,$W83),VALUE(SUBSTITUTE(INDEX($L$9:$L$2008,$W83),",",""))),"")) | AK83: =IF($W83="","",IFERROR(IF(ISNUMBER(INDEX($M$9:$M$2008,$W83)),INDEX($M$9:$M$2008,$W83),VALUE(SUBSTITUTE(INDEX($M$9:$M$2008,$W83),",",""))),"")) | AL83: =IF($W83="","",IFERROR(IF(ISNUMBER(INDEX($P$9:$P$2008,$W83)),INDEX($P$9:$P$2008,$W83),VALUE(SUBSTITUTE(INDEX($P$9:$P$2008,$W83),"%",""))/100),""))
S84: =IF(AND(ISTEXT($A84),ISNUMBER(SEARCH(" - ",$A84)),ISERROR(SEARCH("Folio",$A84)),$D84=""),TRIM($A84),$S83) | T84: =IF(AND(ISNUMBER(SEARCH("Folio",$A84)),$D84<>""),1,"") | U84: =IF($T84=1,COUNTIF($T$9:$T84,1),"") | V84: =IF(AND(ISTEXT($A84),LEFT($A85,3)="Pan"),1,"") | W84: =IFERROR(MATCH(76,$U$9:$U$2008,0),"") | X84: =IF($W84="","",IF($R$5<>"",$R$5,$R$6)) | Y84: =IF($W84="","",INDEX($S$9:$S$2008,$W84)) | Z84: =IF($W84="","",IFERROR(TRIM(LEFT(SUBSTITUTE(INDEX($A$9:$A$2008,$W84),CHAR(10)," "),SEARCH("Folio",SUBSTITUTE(INDEX($A$9:$A$2008,$W84),CHAR(10)," "))-1)),TRIM(SUBSTITUTE(INDEX($A$9:$A$2008,$W84),CHAR(10)," ")))) | AA84: =IF($W84="","",IFERROR(TRIM(SUBSTITUTE(MID(SUBSTITUTE(INDEX($A$9:$A$2008,$W84),CHAR(10)," "),SEARCH("Folio",SUBSTITUTE(INDEX($A$9:$A$2008,$W84),CHAR(10)," "))+5,200),":","")),"")) | AB84: =IF($W84="","",IF(ISNUMBER(INDEX($D$9:$D$2008,$W84)),INDEX($D$9:$D$2008,$W84),IFERROR(DATE(2000+VALUE(RIGHT(INDEX($D$9:$D$2008,$W84),2)),VALUE(MID(INDEX($D$9:$D$2008,$W84),4,2)),VALUE(LEFT(INDEX($D$9:$D$2008,$W84),2))),""))) | AC84: =IF($W84="","",IFERROR(IF(ISNUMBER(INDEX($E$9:$E$2008,$W84)),INDEX($E$9:$E$2008,$W84),VALUE(SUBSTITUTE(INDEX($E$9:$E$2008,$W84),",",""))),"")) | AD84: =IF($W84="","",IFERROR(IF(ISNUMBER(INDEX($F$9:$F$2008,$W84)),INDEX($F$9:$F$2008,$W84),VALUE(SUBSTITUTE(INDEX($F$9:$F$2008,$W84),",",""))),"")) | AE84: =IF($W84="","",IFERROR(IF(ISNUMBER(INDEX($G$9:$G$2008,$W84)),INDEX($G$9:$G$2008,$W84),VALUE(SUBSTITUTE(INDEX($G$9:$G$2008,$W84),",",""))),"")) | AF84: =IF($W84="","",IFERROR(IF(ISNUMBER(INDEX($H$9:$H$2008,$W84)),INDEX($H$9:$H$2008,$W84),VALUE(SUBSTITUTE(INDEX($H$9:$H$2008,$W84),",",""))),"")) | AG84: =IF($W84="","",IFERROR(IF(ISNUMBER(INDEX($I$9:$I$2008,$W84)),INDEX($I$9:$I$2008,$W84),VALUE(SUBSTITUTE(INDEX($I$9:$I$2008,$W84),",",""))),"")) | AH84: =IF($W84="","",IFERROR(IF(ISNUMBER(INDEX($J$9:$J$2008,$W84)),INDEX($J$9:$J$2008,$W84),VALUE(SUBSTITUTE(INDEX($J$9:$J$2008,$W84),",",""))),"")) | AI84: =IF($W84="","",IFERROR(IF(ISNUMBER(INDEX($K$9:$K$2008,$W84)),INDEX($K$9:$K$2008,$W84),VALUE(SUBSTITUTE(INDEX($K$9:$K$2008,$W84),",",""))),"")) | AJ84: =IF($W84="","",IFERROR(IF(ISNUMBER(INDEX($L$9:$L$2008,$W84)),INDEX($L$9:$L$2008,$W84),VALUE(SUBSTITUTE(INDEX($L$9:$L$2008,$W84),",",""))),"")) | AK84: =IF($W84="","",IFERROR(IF(ISNUMBER(INDEX($M$9:$M$2008,$W84)),INDEX($M$9:$M$2008,$W84),VALUE(SUBSTITUTE(INDEX($M$9:$M$2008,$W84),",",""))),"")) | AL84: =IF($W84="","",IFERROR(IF(ISNUMBER(INDEX($P$9:$P$2008,$W84)),INDEX($P$9:$P$2008,$W84),VALUE(SUBSTITUTE(INDEX($P$9:$P$2008,$W84),"%",""))/100),""))
