Workbook

Sheet Summary
A1: PORTFOLIO FUND ANALYSIS REPORT
A2: Converted from the 9-page PDF dated 2 September 2026. Blue figures are read off the report; black figures are computed here from the Holdings sheet.
A4: HEADLINE NUMBERS
A5: Metric | B5: As stated | C5: Computed | D5: Difference | E5: Comment
A6: Total funds | B6: 19 | C6: =COUNTA(Holdings!$B$5:$B$23) | D6: =$C6-$B6 | E6: Matches.
A7: Top fund holding | B7: 0.1519 | C7: =LARGE((Holdings!$D$5:$D$23),1) | D7: =$C7-$B7 | E7: TRUSTMF Small Cap. Matches.
A8: Top 3 funds | B8: 0.3616 | C8: =LARGE((Holdings!$D$5:$D$23),1)+LARGE((Holdings!$D$5:$D$23),2)+LARGE((Holdings!$D$5:$D$23),3) | D8: =$C8-$B8 | E8: Report states 36.16%; the three largest holdings add to 37.16%.
A9: Top 5 funds | B9: 0.4817 | C9: =LARGE((Holdings!$D$5:$D$23),1)+LARGE((Holdings!$D$5:$D$23),2)+LARGE((Holdings!$D$5:$D$23),3)+LARGE((Holdings!$D$5:$D$23),4)+LARGE((Holdings!$D$5:$D$23),5) | D9: =$C9-$B9 | E9: Report states 48.17%; the five largest holdings add to 54.16%.
A10: Allocation total | B10: 1 | C10: =SUM(Holdings!$D$5:$D$23) | D10: =$C10-$B10 | E10: The 19 printed allocations sum to exactly 100%.
A11: Funds kept in target | B11: 7 | C11: =COUNTIF(Holdings!$G$5:$G$23,"KEEP") | D11: =$C11-$B11 | E11: Matches the 7-fund proposed portfolio.
A12: Funds exited | B12: 12 | C12: =COUNTIF(Holdings!$G$5:$G$23,"EXIT") | D12: =$C12-$B12 | E12: Matches the report's "12 redundant funds".
A14: CRITICAL ISSUE (as printed)
A15: Your portfolio shows severe concentration risk with the top 3 funds controlling 36.16% of your portfolio. This creates unnecessary risk and limits diversification benefits.
A18: KEY FINDINGS & ISSUES
A19: Finding | E19: Detail
A20: Extreme Concentration Risk | E20: Top 3 funds = 36.16% of portfolio. Recommended maximum is 10-12% per fund.
A21: Thematic Overlap | E21: 26% of portfolio in Business Cycle funds (2 different funds with similar strategy).
A22: Flexi Cap Redundancy | E22: 4 Flexi Cap funds doing similar work, fragmenting capital across overlapping strategies.
A23: Tail End Holdings | E23: 4 funds below 1% allocation (essentially dead weight from a portfolio perspective).
A24: Fee Inefficiency | E24: Managing 19 funds creates higher administrative burden and fee drag from lower-quality holdings.
A25: Diversification Problem | E25: You have 19 funds but lack true diversification - too concentrated in small cap and thematic bets.
A27: CONCENTRATION RISK (report's own limits)
A28: Level | B28: Stated | C28: Computed | D28: Limit | E28: Verdict
A29: Top 1 fund | B29: 0.1519 | C29: =LARGE((Holdings!$D$5:$D$23),1) | D29: max 10-12% | E29: =IF($C29>0.12,"OVER by "&TEXT($C29-0.12,"0.00%"),"Within limit")
A30: Top 3 funds | B30: 0.3616 | C30: =LARGE((Holdings!$D$5:$D$23),1)+LARGE((Holdings!$D$5:$D$23),2)+LARGE((Holdings!$D$5:$D$23),3) | D30: max 25-30% | E30: =IF($C30>0.3,"OVER by "&TEXT($C30-0.3,"0.00%"),"Within limit")
A31: Top 5 funds | B31: 0.4817 | C31: =LARGE((Holdings!$D$5:$D$23),1)+LARGE((Holdings!$D$5:$D$23),2)+LARGE((Holdings!$D$5:$D$23),3)+LARGE((Holdings!$D$5:$D$23),4)+LARGE((Holdings!$D$5:$D$23),5) | D31: healthy 40-45% | E31: =IF($C31>0.45,"OVER by "&TEXT($C31-0.45,"0.00%"),"Within limit")
A33: FUNDS REQUIRING IMMEDIATE ATTENTION
A34: Issue | B34: Fund | D34: Allocation | E34: Report's comment
A35: Over-Allocated (>10%) | B35: TRUSTMF Small Cap Fund | D35: 0.1519 | E35: Concentration risk. Best 1Y returns but questionable as largest holding.
A36: Over-Allocated (>10%) | B36: Aditya Birla SL Quant Fund | D36: 0.1132 | E36: Adequate holding but not a "core" fund in most portfolios.
A37: Over-Allocated (>10%) | B37: Bandhan Business Cycle Fund | D37: 0.1065 | E37: Thematic bet taking up excessive space.
A38: Over-Allocated (>10%) | B38: Tata Business Cycle Fund | D38: 0.1001 | E38: Duplicate thematic exposure with Bandhan BC Fund.
A39: Micro-Position (<1%) | B39: TRUSTMF Money Market Fund | D39: 0.0027 | E39: Too small to matter, creates tracking burden.
A40: Micro-Position (<1%) | B40: Mahindra Manulife Value Fund | D40: 0.0006 | E40: Essentially negligible, not even a rounding error.
A41: Redundant | B41: 4 Flexi Cap Funds | D41: 0.1121 | E41: Aditya Birla SL (2.47%), TRUSTMF (4.51%), Bandhan (2.70%), MM (1.53%) across overlapping strategies.
A42: Redundant | B42: 2 Business Cycle Funds | D42: 0.2066 | E42: Bandhan (10.65%) + Tata (10.01%) in the same thematic bet.
A43: Redundant | B43: Small Cap Duplication | D43: 0.2091 | E43: TRUSTMF (15.19%) + MM Small Cap (5.72%) concentrated in small-cap segment.
A45: NOTE ON THE SOURCE
A46: The PDF is a scan with no text layer, so every figure here was read off the rendered pages rather than extracted. Three of the report's own headline percentages do not reconcile against its 19-fund table: top 3 (36.16% stated vs 37.16% computed), top 5 (48.17% vs 54.16%) and Small Cap (26.90% stated vs 20.91% for the two small-cap funds, which is the figure the report itself uses on its own page 5). The stated figures are kept in the "As stated" column and nothing has been silently corrected - check them against the source data before acting.

Sheet Holdings
A1: COMPLETE PORTFOLIO HOLDINGS - 19 FUNDS
A2: Rank, fund, allocation, category and concentration exactly as printed in the report. Tier and Proposed % come from the report's 7-fund target portfolio.
A4: Rank | B4: Fund Name | C4: AMC | D4: Allocation % | E4: Category | F4: Concentration | G4: Keep / Exit | H4: Proposed % | I4: Change
A5: 1 | B5: TRUSTMF Small Cap Fund - Regular (G) | C5: TRUSTMF | D5: 0.1519 | E5: Small Cap | F5: HIGH | G5: EXIT | H5: 0 | I5: =-$D5
A6: 2 | B6: Aditya Birla SL Quant Fund - Regular (G) | C6: Aditya Birla | D6: 0.1132 | E6: Multi-Cap/Quant | F6: HIGH | G6: EXIT | H6: 0 | I6: =-$D6
A7: 3 | B7: Bandhan Business Cycle Fund - Regular (G) | C7: Bandhan | D7: 0.1065 | E7: Thematic | F7: HIGH | G7: EXIT | H7: 0 | I7: =-$D7
A8: 4 | B8: Tata Business Cycle Fund (G) | C8: Tata | D8: 0.1001 | E8: Thematic | F8: HIGH | G8: KEEP | H8: 0.1 | I8: =$H8-$D8
A9: 5 | B9: Mahindra Manulife Mid Cap Fund (G) | C9: Mahindra Manulife | D9: 0.0699 | E9: Mid Cap | F9: MEDIUM | G9: KEEP | H9: 0.2 | I9: =$H9-$D9
A10: 6 | B10: Mahindra Manulife Large & Mid Cap Fund-Reg (G) | C10: Mahindra Manulife | D10: 0.0573 | E10: Large & Mid Cap | F10: MEDIUM | G10: KEEP | H10: 0.15 | I10: =$H10-$D10
A11: 7 | B11: Mahindra Manulife Small Cap Fund - Regular (G) | C11: Mahindra Manulife | D11: 0.0572 | E11: Small Cap | F11: MEDIUM | G11: KEEP | H11: 0.15 | I11: =$H11-$D11
A12: 8 | B12: Mahindra Manulife Focused Fund (G) | C12: Mahindra Manulife | D12: 0.0561 | E12: Focused/Multi-Cap | F12: MEDIUM | G12: KEEP | H12: 0.07 | I12: =$H12-$D12
A13: 9 | B13: Mahindra Manulife Business Cycle Fund - Reg (G) | C13: Mahindra Manulife | D13: 0.0523 | E13: Thematic | F13: MEDIUM | G13: EXIT | H13: 0 | I13: =-$D13
A14: 10 | B14: Tata India Innovation Fund - Regular (G) | C14: Tata | D14: 0.0514 | E14: Thematic | F14: MEDIUM | G14: EXIT | H14: 0 | I14: =-$D14
A15: 11 | B15: TRUSTMF Flexi Cap Fund - Regular (G) | C15: TRUSTMF | D15: 0.0451 | E15: Flexi Cap | F15: MEDIUM | G15: EXIT | H15: 0 | I15: =-$D15
A16: 12 | B16: Aditya Birla SL Ultra Short to Short Term Fund-Reg (G) | C16: Aditya Birla | D16: 0.0311 | E16: Debt/Short Term | F16: LOW | G16: EXIT | H16: 0 | I16: =-$D16
A17: 13 | B17: Bandhan Ultra Short Term Fund - Reg (G) | C17: Bandhan | D17: 0.029 | E17: Debt/Short Term | F17: LOW | G17: KEEP | H17: 0.08 | I17: =$H17-$D17
A18: 14 | B18: Bandhan Flexi Cap Fund (G) | C18: Bandhan | D18: 0.027 | E18: Flexi Cap | F18: LOW | G18: EXIT | H18: 0 | I18: =-$D18
A19: 15 | B19: Aditya Birla SL Flexi Cap Fund (G) | C19: Aditya Birla | D19: 0.0247 | E19: Flexi Cap | F19: LOW | G19: KEEP | H19: 0.25 | I19: =$H19-$D19
A20: 16 | B20: Mahindra Manulife Flexi Cap Fund (G) | C20: Mahindra Manulife | D20: 0.0153 | E20: Flexi Cap | F20: LOW | G20: EXIT | H20: 0 | I20: =-$D20
A21: 17 | B21: Tata Ultra Short Term Fund - Regular (G) | C21: Tata | D21: 0.0086 | E21: Debt/Short Term | F21: LOW | G21: EXIT | H21: 0 | I21: =-$D21
A22: 18 | B22: TRUSTMF Money Market Fund (G) | C22: TRUSTMF | D22: 0.0027 | E22: Money Market | F22: LOW | G22: EXIT | H22: 0 | I22: =-$D22
A23: 19 | B23: Mahindra Manulife Value Fund - Regular (G) | C23: Mahindra Manulife | D23: 0.0006 | E23: Value | F23: LOW | G23: EXIT | H23: 0 | I23: =-$D23
B24: TOTAL (19 funds) | D24: =SUM($D$5:$D$23) | F24: =COUNTIF($G$5:$G$23,"KEEP")&" keep / "&COUNTIF($G$5:$G$23,"EXIT")&" exit" | H24: =SUM($H$5:$H$23)

Sheet Category
A1: PORTFOLIO BY CATEGORY
A2: Top block is computed live from the Holdings sheet. Bottom block is the report's own panel, reproduced as printed - the two do not agree everywhere.
A4: COMPUTED FROM HOLDINGS
A5: Category | B5: Funds | C5: Allocation % | D5: Share of Equity
A6: Small Cap | B6: =COUNTIF(Holdings!$E$5:$E$23,$A6) | C6: =SUMIF(Holdings!$E$5:$E$23,$A6,Holdings!$D$5:$D$23) | D6: =IF($C$16=0,"",$C6/$C$16)
A7: Mid Cap | B7: =COUNTIF(Holdings!$E$5:$E$23,$A7) | C7: =SUMIF(Holdings!$E$5:$E$23,$A7,Holdings!$D$5:$D$23) | D7: =IF($C$16=0,"",$C7/$C$16)
A8: Large & Mid Cap | B8: =COUNTIF(Holdings!$E$5:$E$23,$A8) | C8: =SUMIF(Holdings!$E$5:$E$23,$A8,Holdings!$D$5:$D$23) | D8: =IF($C$16=0,"",$C8/$C$16)
A9: Flexi Cap | B9: =COUNTIF(Holdings!$E$5:$E$23,$A9) | C9: =SUMIF(Holdings!$E$5:$E$23,$A9,Holdings!$D$5:$D$23) | D9: =IF($C$16=0,"",$C9/$C$16)
A10: Focused/Multi-Cap | B10: =COUNTIF(Holdings!$E$5:$E$23,$A10) | C10: =SUMIF(Holdings!$E$5:$E$23,$A10,Holdings!$D$5:$D$23) | D10: =IF($C$16=0,"",$C10/$C$16)
A11: Multi-Cap/Quant | B11: =COUNTIF(Holdings!$E$5:$E$23,$A11) | C11: =SUMIF(Holdings!$E$5:$E$23,$A11,Holdings!$D$5:$D$23) | D11: =IF($C$16=0,"",$C11/$C$16)
A12: Thematic | B12: =COUNTIF(Holdings!$E$5:$E$23,$A12) | C12: =SUMIF(Holdings!$E$5:$E$23,$A12,Holdings!$D$5:$D$23) | D12: =IF($C$16=0,"",$C12/$C$16)
A13: Debt/Short Term | B13: =COUNTIF(Holdings!$E$5:$E$23,$A13) | C13: =SUMIF(Holdings!$E$5:$E$23,$A13,Holdings!$D$5:$D$23) | D13: =IF($C$16=0,"",$C13/$C$16)
A14: Money Market | B14: =COUNTIF(Holdings!$E$5:$E$23,$A14) | C14: =SUMIF(Holdings!$E$5:$E$23,$A14,Holdings!$D$5:$D$23) | D14: =IF($C$16=0,"",$C14/$C$16)
A15: Value | B15: =COUNTIF(Holdings!$E$5:$E$23,$A15) | C15: =SUMIF(Holdings!$E$5:$E$23,$A15,Holdings!$D$5:$D$23) | D15: =IF($C$16=0,"",$C15/$C$16)
A16: TOTAL | B16: =SUM(B6:B15) | C16: =SUM(C6:C15)
A18: AS STATED IN THE REPORT
A19: Category (report wording) | B19: Stated % | C19: Funds | D19: Report's fund list | E19: Note
A20: Small Cap | B20: 0.269 | C20: 3 | D20: TRUSTMF, MM, others | E20: Report's own text elsewhere gives TRUSTMF + MM Small Cap = 20.91%.
A21: Business Cycle (Thematic) | B21: 0.2589 | C21: 3 | D21: Bandhan, Tata, MM | E21: Reconciles: 10.65 + 10.01 + 5.23 = 25.89%.
A22: Flexi Cap | B22: 0.1121 | C22: 4 | D22: Aditya Birla, TRUSTMF, Bandhan, MM | E22: Reconciles: 4.51 + 2.70 + 2.47 + 1.53 = 11.21%.
A23: Multi-Cap & Others | B23: 0.1132 | C23: 2 | D23: Aditya Birla Quant, Tata Innovation | E23: 11.32% is Aditya Birla Quant alone; Tata Innovation (5.14%) not included.
A24: Large & Mid Cap | B24: 0.1272 | C24: 2 | D24: MM Large & Mid Cap, MM Focused | E24: Named funds total 5.73 + 5.61 = 11.34%.
A25: Debt & Money Market | B25: 0.0714 | C25: 4 | D25: Ultra Short Term, Money Market | E25: Reconciles: 3.11 + 2.90 + 0.86 + 0.27 = 7.14%.
A26: TOTAL AS STATED | B26: =SUM(B20:B25) | C26: =SUM(C20:C25) | E26: The six stated buckets do not sum to 100%.

Sheet Proposed Portfolio
A1: PROPOSED OPTIMIZED PORTFOLIO - 7 FUNDS
A2: The report's target portfolio: 19 funds down to 7, in three tiers.
A4: Tier | B4: Fund | C4: Current % | D4: Proposed % | E4: Change | F4: Rationale
A5: Tier 1: Core Holdings - 60% allocation
A6: Tier 1 | B6: Aditya Birla SL Flexi Cap Fund | C6: 0.0247 | D6: 0.25 | E6: =$D6-$C6 | F6: Best quality, consolidate other flexi caps here
A7: Tier 1 | B7: Mahindra Manulife Small Cap Fund | C7: 0.0572 | D7: 0.15 | E7: =$D7-$C7 | F7: Consolidate TRUSTMF SC here, reduce concentration
A8: Tier 1 | B8: Mahindra Manulife Mid Cap Fund | C8: 0.0699 | D8: 0.2 | E8: =$D8-$C8 | F8: Strong performer, expand position
B9: Tier 1 subtotal | C9: =SUM(C6:C8) | D9: =SUM(D6:D8) | E9: =$D9-$C9 | F9: Target 60%
A11: Tier 2: Balanced Holdings - 22% allocation
A12: Tier 2 | B12: Mahindra Manulife Large & Mid Cap Fund | C12: 0.0573 | D12: 0.15 | E12: =$D12-$C12 | F12: Steady performer, lower volatility
A13: Tier 2 | B13: Mahindra Manulife Focused Fund | C13: 0.0561 | D13: 0.07 | E13: =$D13-$C13 | F13: Satellite position, controlled exposure
B14: Tier 2 subtotal | C14: =SUM(C12:C13) | D14: =SUM(D12:D13) | E14: =$D14-$C14 | F14: Target 22%
A16: Tier 3: Stability & Defensive - 18% allocation
A17: Tier 3 | B17: Tata Business Cycle Fund | C17: 0.1001 | D17: 0.1 | E17: =$D17-$C17 | F17: Single thematic bet (capped), exit Bandhan duplicate
A18: Tier 3 | B18: Bandhan Ultra Short Term Fund | C18: 0.029 | D18: 0.08 | E18: =$D18-$C18 | F18: Safety buffer, best debt fund quality
B19: Tier 3 subtotal | C19: =SUM(C17:C18) | D19: =SUM(D17:D18) | E19: =$D19-$C19 | F19: Target 18%
B21: TOTAL (7 funds) | C21: =C6+C7+C8+C12+C13+C17+C18 | D21: =D6+D7+D8+D12+D13+D17+D18 | E21: =$D21-$C21 | F21: The 12 funds not listed here are exited.

Sheet Action Plan
A1: STRATEGIC RECOMMENDATIONS & 30-DAY ACTION PLAN
A2: Reproduced from the report. Owner and Done columns are blank for you to fill in.
A4: Recommendation 1: Immediate Fund Consolidation
A5: Reduce from 19 funds to 7 core holdings to eliminate redundancy and reduce fee drag.
B6: Consolidate 4 Flexi Cap funds into 1 best-performing one
B7: Keep only 1 Business Cycle thematic bet (keep Tata, exit Bandhan)
B8: Reduce small cap concentration from 26.90% to 15-20%
B9: Exit all micro-positions (<0.5%)
A11: Recommendation 2: Rebalance Top Holdings
A12: Bring the largest holdings to healthier concentration levels (10-12% maximum).
B13: Reduce TRUSTMF Small Cap from 15.19% to 12%
B14: Reduce Aditya Birla Quant from 11.32% to 10%
B15: Reduce Bandhan BC from 10.65% to exit
B16: Reduce Tata BC from 10.01% to 8%
A18: Recommendation 3: Tax-Efficient Exit Strategy
A19: Implement over 6 months to minimize capital gains tax impact.
B20: Phase 1 (Weeks 1-2): Redirect new SIPs away from 12 redundant funds
B21: Phase 2 (Weeks 3-8): Exit micro-positions and worst performers
B22: Phase 3 (Months 2-4): Exit redundant flexi caps and thematic duplicates
B23: Phase 4 (Months 4-6): Finalize rebalancing and tax documentation
A25: ACTION PLAN: NEXT 30 DAYS
A26: When | B26: Action | D26: Owner | E26: Done
A27: Week 1 | B27: Consult your CA about tax implications of fund consolidation and switching to Direct plans
A28: Week 1 | B28: Review your distributor relationship and fee structure (Regular vs Direct)
A29: Week 2 | B29: Document current holdings and cost basis for tax planning
A30: Week 2-3 | B30: Begin Phase 1 - Redirect all new SIPs to the 7 core funds only
A31: Week 3-4 | B31: Exit micro-positions (funds <0.5% allocation)
A32: Week 4+ | B32: Plan Phase 2 exits with CA guidance on timing
A33: Ongoing | B33: Monitor quarterly, rebalance once yearly
A35: Disclaimer (from the report): This analysis is based on current allocation data and general investment principles. Before implementing any changes, consult your financial advisor and CA for tax planning and suitability assessment for your specific financial situation, goals, and time horizon. Report generated: September 2, 2026.
