Workbook

Sheet Summary
A1: WITHDRAWAL & RETURNS REVIEW - PRAMOD NIKALJE FAMILY
A2: As on 30 September 2026. Opulencia Capital Private Limited - AMFI Registered Mutual Fund Distributor (ARN-207036)
A4: HOW MUCH CAN BE WITHDRAWN
B5: Amount | E5: Explanation
A6: Available today, no charge | B6: =Withdrawal!$D$5 | E6: Load-free units across both holders. No exit load, no lock-in.
A7: Maximum if exit load is paid | B7: =Withdrawal!$D$5+Withdrawal!$D$6 | E7: Adds Rs 1,15,026.64 of load-applicable units - both at a loss today.
A8: Locked and unavailable | B8: =Withdrawal!$D$7 | E8: Two ELSS funds inside the statutory three-year lock-in.
A9: Total portfolio | B9: =Withdrawal!$D$8 | E9: Pramod Rs 10,97,208.99 and Amita Rs 1,02,934.78.
A11: WHAT XIRR HE GOT
A12: Load-free money (Pramod) | B12: 0.1374 | E12: Rs 4,24,984 invested, now Rs 7,11,289.45. This is the headline number - and it covers only that bucket.
A13: of which HDFC Retirement Equity Plan | B13: 0.1608 | E13: 172.60% absolute over roughly 6.7 years. Rs 1,59,997 is now Rs 4,36,157.
A14: of which Union Retirement Fund | B14: 0.0451 | E14: Rs 1,59,992 is now Rs 1,70,851.
A15: of which HDFC Retirement Hybrid | B15: -0.0034 | E15: Rs 1,04,995 is now Rs 1,04,281.
A16: Load-applicable money (Pramod) | B16: -0.1038 | E16: HDFC Retirement Hybrid Equity Plan.
A17: Lock-in money (Pramod) | B17: -0.0014 | E17: The two ELSS funds, close to flat.
A18: Load-free money (Amita) | B18: -0.0078 | E18: Nippon India Flexi Cap.
A19: Load-applicable money (Amita) | B19: -0.0522 | E19: Nippon India Flexi Cap.
A20: Whole family, absolute return | B20: =Holdings!$I$13 | E20: Rs 9,19,960 invested is now Rs 12,00,143.77. There is no single portfolio XIRR on the report, and bucket XIRRs cannot be averaged.
A22: WHAT THIS ACTUALLY SAYS
A23: One fund carries the portfolio | B23: HDFC Retirement Equity Plan has turned Rs 1,59,997 into Rs 4,36,157. That single holding is Rs 2,76,160 of the family's Rs 2,80,184 total gain. Without it the rest of the portfolio is roughly flat.
A24: Five of eight holdings are below cost | B24: Both ELSS funds, both HDFC Hybrid positions and Nippon Flexi Cap.
A25: The load-applicable money is the worst of both | B25: Rs 1,15,026.64 that would be charged to exit and is already at a loss. Wait for the load period unless the money is needed.
A26: Tax, not exit load, is the real cost | B26: Rs 2.86 lakh of gain sits in the load-free bucket. The tax on redeeming it will dwarf any exit load elsewhere.

Sheet Holdings
A1: HOLDINGS BY EXIT-LOAD STATUS - PRAMOD NIKALJE FAMILY
A2: As on 30 September 2026. A scheme can appear twice - units bought at different times carry different load status. Gain, absolute return and totals are computed.
A4: Holder | B4: Folio | C4: Scheme | D4: Bucket | E4: Units | F4: Invested | G4: Current Value | H4: Gain / Loss | I4: Abs. Rtn. | J4: XIRR
A5: Pramod Nikalje | B5: 9713877/79 | C5: HDFC Retirement Fund - Equity Plan - Regular Plan | D5: Load Free | E5: 9398.933 | F5: 159997.25 | G5: 436157.49 | H5: =$G5-$F5 | I5: =IF($F5=0,"",$H5/$F5) | J5: 0.1608
A6: Pramod Nikalje | B6: 10868589 | C6: Union Retirement Fund - Regular Plan | D6: Load Free | E6: 10772.438 | F6: 159992 | G6: 170850.87 | H6: =$G6-$F6 | I6: =IF($F6=0,"",$H6/$F6) | J6: 0.0451
A7: Pramod Nikalje | B7: 9713877/79 | C7: HDFC Retirement Fund - Hybrid Equity Plan - Regular Plan | D7: Load Free | E7: 2921.694 | F7: 104994.75 | G7: 104281.1 | H7: =$G7-$F7 | I7: =IF($F7=0,"",$H7/$F7) | J7: -0.0034
A8: Amita Pramod Nikalje | B8: 499249672482 | C8: Nippon India Flexi Cap Fund - Regular Plan | D8: Load Free | E8: 2779.927 | F8: 44998 | G8: 44507.19 | H8: =$G8-$F8 | I8: =IF($F8=0,"",$H8/$F8) | J8: -0.0078
A9: Amita Pramod Nikalje | B9: 499249672482 | C9: Nippon India Flexi Cap Fund - Regular Plan | D9: Load Applicable | E9: 3649.398 | F9: 59997 | G9: 58427.59 | H9: =$G9-$F9 | I9: =IF($F9=0,"",$H9/$F9) | J9: -0.0522
A10: Pramod Nikalje | B10: 9713877/79 | C10: HDFC Retirement Fund - Hybrid Equity Plan - Regular Plan | D10: Load Applicable | E10: 1585.763 | F10: 59997 | G10: 56599.05 | H10: =$G10-$F10 | I10: =IF($F10=0,"",$H10/$F10) | J10: -0.1038
A11: Pramod Nikalje | B11: 4710370 | C11: Kotak ELSS Tax Saver Fund - Regular Plan | D11: Lock In | E11: 1502.628 | F11: 164992 | G11: 169712.82 | H11: =$G11-$F11 | I11: =IF($F11=0,"",$H11/$F11) | J11: 0.0191
A12: Pramod Nikalje | B12: 1000075469 | C12: Mahindra Manulife ELSS Tax Saver Fund - Regular Plan | D12: Lock In | E12: 6138.662 | F12: 164992 | G12: 159607.67 | H12: =$G12-$F12 | I12: =IF($F12=0,"",$H12/$F12) | J12: -0.0222
C13: FAMILY TOTAL | F13: =SUM(F5:F12) | G13: =SUM(G5:G12) | H13: =SUM(H5:H12) | I13: =$H13/$F13 | J13: see note
A15: XIRR is printed per bucket on the source report and is shown per scheme above. It is a money-weighted rate and cannot be averaged or summed across rows, so no single portfolio XIRR is stated here. The one whole-portfolio figure that is sound is the absolute return in the total row.

Sheet Withdrawal
A1: WHAT CAN BE WITHDRAWN
A2: As on 30 September 2026. Every figure sums the Holdings sheet.
A4: Bucket | B4: Pramod | C4: Amita | D4: Family | E4: What it means
A5: Load Free | B5: =SUMIFS(Holdings!$G$5:$G$12,Holdings!$D$5:$D$12,$A5,Holdings!$A$5:$A$12,"Pramod Nikalje") | C5: =SUMIFS(Holdings!$G$5:$G$12,Holdings!$D$5:$D$12,$A5,Holdings!$A$5:$A$12,"Amita Pramod Nikalje") | D5: =$B5+$C5 | E5: Withdraw today. No exit load, no lock-in. Capital gains tax still applies.
A6: Load Applicable | B6: =SUMIFS(Holdings!$G$5:$G$12,Holdings!$D$5:$D$12,$A6,Holdings!$A$5:$A$12,"Pramod Nikalje") | C6: =SUMIFS(Holdings!$G$5:$G$12,Holdings!$D$5:$D$12,$A6,Holdings!$A$5:$A$12,"Amita Pramod Nikalje") | D6: =$B6+$C6 | E6: Can be withdrawn, but an exit load is charged. Both holdings here are at a loss, so exiting now means paying a charge to book a loss.
A7: Lock In | B7: =SUMIFS(Holdings!$G$5:$G$12,Holdings!$D$5:$D$12,$A7,Holdings!$A$5:$A$12,"Pramod Nikalje") | C7: =SUMIFS(Holdings!$G$5:$G$12,Holdings!$D$5:$D$12,$A7,Holdings!$A$5:$A$12,"Amita Pramod Nikalje") | D7: =$B7+$C7 | E7: Cannot be withdrawn. Both are ELSS funds inside the statutory three-year lock-in. No fee will release them early.
A8: PORTFOLIO | B8: =SUM(B5:B7) | C8: =SUM(C5:C7) | D8: =SUM(D5:D7)
A10: THE ANSWER
A11: Withdraw today, no charge | B11: =$D5 | E11: Load-free value. This is the figure to quote.
A12: Maximum withdrawable today | B12: =$D5+$D6 | E12: Adds the load-applicable money. An exit load is charged on that part.
A13: Cannot be withdrawn | B13: =$D7 | E13: ELSS lock-in. No fee releases it early.
A14: Gain sitting in the load-free money | B14: =SUMIFS(Holdings!$H$5:$H$12,Holdings!$D$5:$D$12,"Load Free") | E14: Capital gains tax applies on withdrawal - confirm the rates with the CA.

Sheet XIRR
A1: RETURNS BY BUCKET
A2: XIRR exactly as printed on the source report. It is money-weighted, so these cannot be averaged into one number.
A4: Holder | B4: Bucket | C4: Invested | D4: Current Value | E4: Gain / Loss | F4: XIRR
A5: Pramod Nikalje | B5: Load Free | C5: =SUMIFS(Holdings!$F$5:$F$12,Holdings!$D$5:$D$12,$B5,Holdings!$A$5:$A$12,$A5) | D5: =SUMIFS(Holdings!$G$5:$G$12,Holdings!$D$5:$D$12,$B5,Holdings!$A$5:$A$12,$A5) | E5: =SUMIFS(Holdings!$H$5:$H$12,Holdings!$D$5:$D$12,$B5,Holdings!$A$5:$A$12,$A5) | F5: 0.1374
A6: Pramod Nikalje | B6: Load Applicable | C6: =SUMIFS(Holdings!$F$5:$F$12,Holdings!$D$5:$D$12,$B6,Holdings!$A$5:$A$12,$A6) | D6: =SUMIFS(Holdings!$G$5:$G$12,Holdings!$D$5:$D$12,$B6,Holdings!$A$5:$A$12,$A6) | E6: =SUMIFS(Holdings!$H$5:$H$12,Holdings!$D$5:$D$12,$B6,Holdings!$A$5:$A$12,$A6) | F6: -0.1038
A7: Pramod Nikalje | B7: Lock In | C7: =SUMIFS(Holdings!$F$5:$F$12,Holdings!$D$5:$D$12,$B7,Holdings!$A$5:$A$12,$A7) | D7: =SUMIFS(Holdings!$G$5:$G$12,Holdings!$D$5:$D$12,$B7,Holdings!$A$5:$A$12,$A7) | E7: =SUMIFS(Holdings!$H$5:$H$12,Holdings!$D$5:$D$12,$B7,Holdings!$A$5:$A$12,$A7) | F7: -0.0014
A8: Amita Pramod Nikalje | B8: Load Free | C8: =SUMIFS(Holdings!$F$5:$F$12,Holdings!$D$5:$D$12,$B8,Holdings!$A$5:$A$12,$A8) | D8: =SUMIFS(Holdings!$G$5:$G$12,Holdings!$D$5:$D$12,$B8,Holdings!$A$5:$A$12,$A8) | E8: =SUMIFS(Holdings!$H$5:$H$12,Holdings!$D$5:$D$12,$B8,Holdings!$A$5:$A$12,$A8) | F8: -0.0078
A9: Amita Pramod Nikalje | B9: Load Applicable | C9: =SUMIFS(Holdings!$F$5:$F$12,Holdings!$D$5:$D$12,$B9,Holdings!$A$5:$A$12,$A9) | D9: =SUMIFS(Holdings!$G$5:$G$12,Holdings!$D$5:$D$12,$B9,Holdings!$A$5:$A$12,$A9) | E9: =SUMIFS(Holdings!$H$5:$H$12,Holdings!$D$5:$D$12,$B9,Holdings!$A$5:$A$12,$A9) | F9: -0.0522
A10: FAMILY | C10: =SUM(C5:C9) | D10: =SUM(D5:D9) | E10: =SUM(E5:E9) | F10: not additive
A12: The 13.74% is the XIRR on Pramod's load-free money only - Rs 4,24,984 invested, now Rs 7,11,289.45. It is not the family's return. Almost all of it comes from one holding: HDFC Retirement Fund - Equity Plan, up 172.60% in absolute terms at 16.08% XIRR, which alone accounts for Rs 2,76,160 of the family's Rs 2,80,184 total gain. Five of the eight holdings are below cost.

Sheet Client Message
A1: DRAFT MESSAGE TO THE CLIENT
A2: Ready to copy into email. A short WhatsApp version is at the bottom.
A4: Subject | B4: Your portfolio - what is available to withdraw, as on 30 September 2026
B6: Dear Dr. Nikalje,
B8: Here is where your family portfolio stands as on 30 September 2026.
A10: WHAT YOU CAN WITHDRAW
B11: The family portfolio is worth Rs 12,00,143.77. It sits in three parts:
B12: - Rs 7,55,796.64 can be withdrawn immediately, with no exit load.
B13: - Rs 1,15,026.64 can be withdrawn, but an exit load will be charged.
B14: - Rs 3,29,320.48 is in ELSS funds and is locked under the statutory three-year rule.
B16: So the amount freely available to you today is Rs 7,55,796.64 - Rs 7,11,289.45 in your name and Rs 44,507.19 in Mrs. Nikalje's.
A18: HOW THE MONEY HAS DONE
B19: The load-free portion has earned an XIRR of 13.74%. Rs 4,24,984 invested is now Rs 7,11,289.45.
B21: This is led by HDFC Retirement Fund - Equity Plan, which has grown from Rs 1,59,997 to Rs 4,36,157 - 172.60% in absolute terms, 16.08% XIRR, over roughly six and a half years. It has been the standout holding.
B23: Across the whole family portfolio, Rs 9,19,960 invested is now worth Rs 12,00,143.77, an absolute gain of 30.46%.
A25: TWO POINTS BEFORE YOU WITHDRAW
B26: 1. Withdrawing is not tax-free. The load-free holdings carry gains of about Rs 2.86 lakh and capital gains tax will apply. Please tell me before you redeem and I will work the tax out with your CA so we can plan the timing.
B28: 2. The Rs 1,15,026.64 in the load-applicable part is at a small loss today. Exiting now means paying a charge to book a loss, so unless the money is needed urgently I would suggest waiting for the load period to end.
B30: Happy to take you through any of this on a call.
B32: Warm regards,
B33: Opulencia Capital Private Limited
B34: AMFI Registered Mutual Fund Distributor - ARN-207036
B35: 9850099777 | info@opulencemoney.com
A37: SHORT / WHATSAPP
A38: Dear Dr. Nikalje, your family portfolio as on 30 Sep 2026 is Rs 12,00,143.77. Rs 7,55,796.64 can be withdrawn today with no exit load; Rs 1,15,026.64 would attract an exit load; Rs 3,29,320.48 is in ELSS and locked in. The load-free part has earned 13.74% XIRR, led by HDFC Retirement Equity Plan at 16.08%. Do note that withdrawing attracts capital gains tax - please check with me before redeeming so we can plan it with your CA. - Opulencia Capital

Sheet Action Plan
A1: ACTION PLAN
A2: Owner and Done are yours to fill in.
A4: When | B4: Step | C4: What happens | D4: Owner | E4: Done
A5: Before the call | B5: Confirm the need | C5: Ask how much is actually needed and by when. Rs 7,55,796.64 is available without charge; anything beyond that costs an exit load or is locked.
A6: Before the call | B6: Get the tax number | C6: Work the capital gains on the load-free holdings out with the CA - about Rs 2.86 lakh of gain sits there. Confirm the rates in force.
A7: At the call | B7: Set the order of withdrawal | C7: Take from the load-free bucket first. Leave the load-applicable money alone - both holdings are at a loss and would also be charged to exit.
A8: At the call | B8: Flag the concentration | C8: HDFC Retirement Equity Plan is Rs 4,36,157 of a Rs 12,00,144 portfolio and carries nearly the whole gain. Redeeming it first realises the largest tax bill; leaving it keeps the portfolio dependent on one fund.
A9: After | B9: Diarise the ELSS | C9: Note when each ELSS tranche leaves its three-year lock-in so the Rs 3,29,320.48 can be planned rather than waited on.
A10: Ongoing | B10: Review | C10: Five of the eight holdings are below cost. Schedule a performance review separate from this withdrawal question.
A12: Mutual fund investments are subject to market risk. Read all scheme-related documents carefully. Capital gains tax treatment depends on the rates in force and on each investor's position - confirm with a CA before redeeming.
